Workbook

Sheet DATA
A1: INDEX | B1: VERSION | C1: start | D1: end | E1: today | F1: Bienvenidos a la encuesta de agricultores para la evaluación final del proyecto: "Aumento de las medidas de resiliencia climática en los agroecosistemas del corredor seco de El Salvador (RECLIMA) - (Versión final 25UN/2026) El Salvador, junio 2026 | G1: Nombre del encuestador | H1: Nombre del supervisor | I1: Fecha de la entrevista | J1: Encuestador: rellene estos datos con la información entregada por su supervisor | K1: ¿Cuál es el nombre completo del productor? | L1: ¿Cuál es la edad del productor? | M1: ¿Cuál es el sexo del productor? | N1: ¿Cuál es el domicilio del productor? | O1: Departamento | P1: Municipio | Q1: Distrito | R1: Cantón | S1: Caserío | T1: Identificador de encuestado | U1: Encuestador: pida conversar con una persona mayor de 18 años que conozca la actividad productiva y/o económica que realiza en el hogar, así como quien pueda brindar información sobre el lugar donde habita. Recuerde que está persona puede ser o no el mismo productor. | V1: ¿Cuál es su nombre? | W1: ¿Es usted mayor de edad? | X1: ¿Hay otras personas del hogar mayores de edad que puedan brindar información sobre lo que produce? | Y1: ¿Cuál es su relación con el productor? | Z1: ¿Cuál es su relación con el productor? | AA1: Encuestador: muestre y lea el texto del consentimiento informado que tiene en papel. Si el productor o informante acepta, marque la opción "Sí". Si no acepta, marque "No" y cierre la encuesta. "Actualmente, se está llevando a cabo la evaluación final del proyecto “Aumento de las medidas de resiliencia climática en los agroecosistemas del corredor seco de El Salvador (RECLIMA)”, ejecutado por la Organización de las Naciones Unidas para la Alimentación y la Agricultura (FAO) con el fin de conocer los resultados alcanzados, las experiencias de las personas beneficiarias y las oportunidades de mejora en futuras intervenciones. En este contexto, se le invita a participar en el proceso de recopilación de información, que puede incluir encuestas, entrevistas, grupos focales y, en algunos casos, la verificación en campo de prácticas productivas implementadas en su parcela. Condiciones de participación: Su participación es totalmente voluntaria: * Puede abstenerse de responder cualquier pregunta o retirarse en cualquier momento, sin que esto le genere ningún perjuicio. * La información proporcionada será tratada de manera confidencial y utilizada únicamente con fines de análisis y evaluación. * Su participación no implica ningún costo ni beneficio económico directo. Autorización: Mediante la firma del presente documento, autorizo a la Organización de las Naciones Unidas para la Alimentación y la Agricultura (FAO) a utilizar la información proporcionada durante este proceso, exclusivamente para fines de análisis, evaluación y elaboración de informes del proyecto." | AB1: ¿El productor o informante autoriza realizar la encuesta? | AC1: Fin de encuesta | AD1: ¿El productor o algún miembro de la unidad de producción participó en el Censo Agropecuario y de Pesca 2025? | AE1: Notas del encuestador | AF1: Durante la temporada agrícola de mayo 2025 a abril 2026, ¿el productor poseía o cultivaba tierras? Incluya las tierras forestales. | AG1: ¿Cuántos TERRENOS o PARCELAS separadas una de la otra tuvo en total? | AH1: ¿Cuántos TIPOS DE CULTIVOS tuvo en total en esos terrenos o parcelas? | AI1: n_parcela_limit | AJ1: Durante la misma temporada, ¿cuánto gastaron en total por la compra de la SEMILLA de su(s) cultivo(s) en la(s) parcela(s)? | AK1: Durante la misma temporada, ¿cuánto gastaron en total por la compra de FERTILIZANTES para su(s) cultivo(s) en la(s) parcela(s)? | AL1: Sin considerar los fertilizantes, ¿cuánto gastaron en total por la compra de AGROQUÍMICOS para su(s) cultivo(s) en la(s) parcela(s) durante esa temporada? | AM1: Durante la misma temporada, ¿cuánto gastaron en total por contratación de mano de obra o jornales para su(s) cultivo(s) en la(s) parcela(s)? | AN1: Durante esa temporada, ¿Cuánto fue el ingreso total obtenido por la venta de su(s) cultivo(s) en la(s) parcela(s)? | AO1: Durante la temporada agrícola de mayo 2025 a abril 2026, ¿usted poseía ganado de alguno de los siguientes grupos? | AP1: Durante la temporada agrícola de mayo 2025 a abril 2026, ¿usted poseía ganado de alguno de los siguientes grupos?/Bovinos (vacas, terneros, novillos, bueyes, toros) | AQ1: Durante la temporada agrícola de mayo 2025 a abril 2026, ¿usted poseía ganado de alguno de los siguientes grupos?/Porcinos (cerdos) | AR1: Durante la temporada agrícola de mayo 2025 a abril 2026, ¿usted poseía ganado de alguno de los siguientes grupos?/Aves (gallinas, pollos, gallos) | AS1: Durante la temporada agrícola de mayo 2025 a abril 2026, ¿usted poseía ganado de alguno de los siguientes grupos?/Cabras | AT1: Durante la temporada agrícola de mayo 2025 a abril 2026, ¿usted poseía ganado de alguno de los siguientes grupos?/Equinos (caballos, burros, mulas) | AU1: Durante la temporada agrícola de mayo 2025 a abril 2026, ¿usted poseía ganado de alguno de los siguientes grupos?/Equinos (caballos, burros, mulas) | AV1: ¿Nos pude confirmar que el productor aceptó ser parte del proyecto RECLIMA? | AW1: ¿Cuándo inició usted o el productor su participación en el proyecto RECLIMA? | AX1: ¿El productor participó de la Escuela de Campo para Agricultores? | AY1: ¿El productor participó en el desarrollo de planes de finca? | AZ1: ¿Cuál era el nombre del Promotor Comunitario de la Escuale de Campo para Agricultores? | BA1: ¿El productor participó en las actividades de restauración de la vegetación de las áreas cercanas fuera de su parcela? | BB1: Durante la temporada agrícola de mayo 2025 a abril 2026, ¿en qué tipo de prácticas de restauración de ecosistemas participó el productor fuera de su parcela? | BC1: Durante la temporada agrícola de mayo 2025 a abril 2026, ¿su comunidad cuenta con un vivero activo para producir plantas forestales? | BD1: Durante la temporada agrícola de mayo 2025 a abril 2026, ¿el productor recibió asesoramiento técnico relacionado a las actividades de restauración de ecosistemas fuera de su parcela? | BE1: Durante la temporada agrícola de mayo 2025 a abril 2026, ¿qué institución le brindó asistencia técnica? | BF1: Durante la temporada agrícola de mayo 2025 a abril 2026, ¿qué institución le brindó asistencia técnica?/Entidad de gobierno central | BG1: Durante la temporada agrícola de mayo 2025 a abril 2026, ¿qué institución le brindó asistencia técnica?/RECLIMA | BH1: Durante la temporada agrícola de mayo 2025 a abril 2026, ¿qué institución le brindó asistencia técnica?/Organismo Internacional | BI1: Durante la temporada agrícola de mayo 2025 a abril 2026, ¿qué institución le brindó asistencia técnica?/ONG | BJ1: Durante la temporada agrícola de mayo 2025 a abril 2026, ¿qué institución le brindó asistencia técnica?/Asociación de productores | BK1: Durante la temporada agrícola de mayo 2025 a abril 2026, ¿qué institución le brindó asistencia técnica?/Cooperativa | BL1: Después de aplicar las medidas de restauración en la temporada agrícola de mayo 2025 a abril 2026, la disponibilidad de agua en la comunidad… | BM1: Durante la temporada agrícola de mayo 2025 a abril 2026, ¿cuál considera que fue la mayor amenaza para los árboles recién plantados en las zonas de restauración de su comunidad? | BN1: Especifique | BO1: Durante la temporada agrícola de mayo 2025 a abril 2026, ¿usted o algún miembro de la unidad de producción u hogar, ya sea propio o en sociedad, tuvo...? | BP1: Durante la temporada agrícola de mayo 2025 a abril 2026, ¿usted o algún miembro de la unidad de producción u hogar, ya sea propio o en sociedad, tuvo...?/Tractor | BQ1: Durante la temporada agrícola de mayo 2025 a abril 2026, ¿usted o algún miembro de la unidad de producción u hogar, ya sea propio o en sociedad, tuvo...?/Rastra | BR1: Durante la temporada agrícola de mayo 2025 a abril 2026, ¿usted o algún miembro de la unidad de producción u hogar, ya sea propio o en sociedad, tuvo...?/Cultivadora | BS1: Durante la temporada agrícola de mayo 2025 a abril 2026, ¿usted o algún miembro de la unidad de producción u hogar, ya sea propio o en sociedad, tuvo...?/Sembradora | BT1: Durante la temporada agrícola de mayo 2025 a abril 2026, ¿usted o algún miembro de la unidad de producción u hogar, ya sea propio o en sociedad, tuvo...?/Podadora | BU1: Durante la temporada agrícola de mayo 2025 a abril 2026, ¿usted o algún miembro de la unidad de producción u hogar, ya sea propio o en sociedad, tuvo...?/Equipo de fumigación | BV1: Durante la temporada agrícola de mayo 2025 a abril 2026, ¿usted o algún miembro de la unidad de producción u hogar, ya sea propio o en sociedad, tuvo...?/Tanque para almacenamiento de agua | BW1: Durante la temporada agrícola de mayo 2025 a abril 2026, ¿usted o algún miembro de la unidad de producción u hogar, ya sea propio o en sociedad, tuvo...?/Bomba de agua | BX1: Durante la temporada agrícola de mayo 2025 a abril 2026, ¿usted o algún miembro de la unidad de producción u hogar, ya sea propio o en sociedad, tuvo...?/Equipo para la cría o engorda de animales | BY1: Durante la temporada agrícola de mayo 2025 a abril 2026, ¿usted o algún miembro de la unidad de producción u hogar, ya sea propio o en sociedad, tuvo...?/Autos particulares | BZ1: Durante la temporada agrícola de mayo 2025 a abril 2026, ¿usted o algún miembro de la unidad de producción u hogar, ya sea propio o en sociedad, tuvo...?/Camioneta o camión | CA1: Durante la temporada agrícola de mayo 2025 a abril 2026, ¿usted o algún miembro de la unidad de producción u hogar, ya sea propio o en sociedad, tuvo...?/Bodega | CB1: Durante la temporada agrícola de mayo 2025 a abril 2026, ¿usted o algún miembro de la unidad de producción u hogar, ya sea propio o en sociedad, tuvo...?/Ningún activo | CC1: Durante la temporada agrícola de mayo 2025 a abril 2026, ¿perdieron toda o parte de la cosecha o de sus animales por… | CD1: Durante la temporada agrícola de mayo 2025 a abril 2026, ¿perdieron toda o parte de la cosecha o de sus animales por…/Plagas o enfermedades | CE1: Durante la temporada agrícola de mayo 2025 a abril 2026, ¿perdieron toda o parte de la cosecha o de sus animales por…/Sequías | CF1: Durante la temporada agrícola de mayo 2025 a abril 2026, ¿perdieron toda o parte de la cosecha o de sus animales por…/Lluvia o inundaciones | CG1: Durante la temporada agrícola de mayo 2025 a abril 2026, ¿perdieron toda o parte de la cosecha o de sus animales por…/Heladas y granizadas | CH1: Durante la temporada agrícola de mayo 2025 a abril 2026, ¿perdieron toda o parte de la cosecha o de sus animales por…/Vientos fuertes | CI1: Durante la temporada agrícola de mayo 2025 a abril 2026, ¿perdieron toda o parte de la cosecha o de sus animales por…/Derrumbes | CJ1: Durante la temporada agrícola de mayo 2025 a abril 2026, ¿perdieron toda o parte de la cosecha o de sus animales por…/Incendios | CK1: Durante la temporada agrícola de mayo 2025 a abril 2026, ¿perdieron toda o parte de la cosecha o de sus animales por…/Robo | CL1: Durante la temporada agrícola de mayo 2025 a abril 2026, ¿perdieron toda o parte de la cosecha o de sus animales por…/No sufrió pérdidas de cosecha o animales | CM1: ¿Cuántas personas habitan al día de hoy el hogar del productor? | CN1: Enliste los nombres de pila de los miembros que integran el hogar del productor empezando con el jefe o jefa del hogar. Recuerde registrar a los recien nacidos, ancianos y aquellas personas que al momento de la encuesta se encuentran temporalmente ausentes por motivo de trabajo, vacaciones, enfermedad, etc. | CO1: Durante la temporada agrícola de mayo 2025 a abril 2026, ¿cuál es la principal fuente de ingresos económicos del hogar del productor? | CP1: ¿En los últimos TRES MESES, por falta de dinero u otros recursos alguna vez usted se preocupó porque los alimentos se acabaran en su hogar? | CQ1: ¿En los últimos TRES MESES, por falta de dinero u otros recursos alguna vez en su hogar se quedaron sin alimentos? | CR1: ¿En los últimos TRES MESES, por falta de dinero u otros recursos alguna vez en su hogar dejaron de tener una alimentación saludable*? | CS1: ¿En los últimos TRES MESES, por falta de dinero u otros recursos alguna vez usted o algún adulto en su hogar tuvo una alimentación basada en poca variedad de alimentos? | CT1: ¿En los últimos TRES MESES, por falta de dinero u otros recursos alguna vez usted o algún adulto en su hogar dejó de desayunar, almorzar o cenar? | CU1: ¿En los últimos TRES MESES, por falta de dinero u otros recursos alguna vez usted o algún adulto en su hogar comió menos de lo que debía comer? | CV1: ¿En los últimos TRES MESES, por falta de dinero u otros recursos alguna vez usted o algún adulto en su hogar sintió hambre pero no comió? | CW1: ¿En los últimos TRES MESES, por falta de dinero u otros recursos alguna vez usted o algún adulto en su hogar solo comió una vez al día o dejó de comer durante todo un día? | CX1: ¿En su hogar viven personas menores de 18 años? | CY1: ¿En los últimos TRES MESES, por falta de dinero u otros recursos, alguna vez algún menor de 18 años en su hogar dejó de tener una alimentación saludable y balanceada? | CZ1: ¿En los últimos TRES MESES, por falta de dinero u otros recursos, alguna vez algún menor de 18 años en su hogar tuvo una alimentación basada en poca variedad de alimentos? | DA1: ¿En los últimos TRES MESES, por falta de dinero u otros recursos, alguna vez algún menor de 18 años de su hogar dejó de desayunar, almorzar o cenar? | DB1: ¿En los últimos TRES MESES, por falta de dinero u otros recursos, alguna vez algún menor de 18 años de su hogar comió menos de lo que debía? | DC1: ¿En los últimos TRES MESES, por falta de dinero u otros recursos, alguna vez tuvieron que disminuir la cantidad servida en las comidas a algún menor de 18 años en su hogar? | DD1: ¿En los últimos TRES MESES, por falta de dinero u otros recursos, alguna vez algún menor de 18 años en su hogar sintió hambre pero no comió? | DE1: ¿En los últimos TRES MESES, por falta de dinero u otros recursos, alguna vez algún menor de 18 años en su hogar solo comió una vez al día o dejó de comer todo un día? | DF1: En la última semana, ¿Cuántos días los miembros del hogar del productor consumieron los siguientes grupos de alimentos...? | DG1: CEREALES Y TUBÉRCULOS | DH1: LEGUMINOSAS, NUECES y SEMILLAS SECAS | DI1: PRODUCTOS LÁCTEOS | DJ1: PRODUCTOS CÁRNICOS | DK1: VEGETALES | DL1: FRUTAS | DM1: ACEITES / GRASAS o MANTEQUILLA | DN1: AZÚCAR O DULCES | DO1: En su hogar, ¿tienen acceso a fuentes de agua? | DP1: ¿Qué tipo de fuente de agua posee? | DQ1: Especifique | DR1: ¿Esa fuente de agua es confiable? | DS1: ¿Esa fuente de agua es segura? | DT1: ¿En qué meses del año tiene mayor acceso a agua? | DU1: ¿En qué meses del año tiene mayor acceso a agua?/Ene | DV1: ¿En qué meses del año tiene mayor acceso a agua?/Feb | DW1: ¿En qué meses del año tiene mayor acceso a agua?/Mar | DX1: ¿En qué meses del año tiene mayor acceso a agua?/Abr | DY1: ¿En qué meses del año tiene mayor acceso a agua?/May | DZ1: ¿En qué meses del año tiene mayor acceso a agua?/Jun | EA1: ¿En qué meses del año tiene mayor acceso a agua?/Jul | EB1: ¿En qué meses del año tiene mayor acceso a agua?/Ago | EC1: ¿En qué meses del año tiene mayor acceso a agua?/Sep | ED1: ¿En qué meses del año tiene mayor acceso a agua?/Oct | EE1: ¿En qué meses del año tiene mayor acceso a agua?/Nov | EF1: ¿En qué meses del año tiene mayor acceso a agua?/Dic | EG1: Encuestador: muestre y lea al productor o informante clave el segundo consentimiento referido al registro de la ubicación y área de la parcela principal. "Hemos finalizada la recolección de datos sobre su parcela, cultivos y hogar del productor. La evaluación también requiere registrar la ubicación y el área de la parcela principal mediante un dispositivo GPS. Por lo tanto, quisiéramos invitarlo a participar en este proceso que consiste en que un técnico recorrerá el perímetro o los puntos principales de la parcela usando una aplicación móvil para obtener su forma y área aproximadas. Es importante que sepa que esta información se utilizará únicamente con fines analíticos para evaluar el proyecto RECLIMA y, por lo tanto, no constituye un trámite legal ni define límites de propiedad ni tiene efectos sobre la tenencia de la tierra. Al igual que en la encuesta, su participación es totalmente voluntaria, lo que implica que: * Puede abstenerse del registro de la ubicación y del área de la parcela principal, sin que ello le genere ningún perjuicio. * La información proporcionada será tratada de manera confidencial y utilizada únicamente con fines de análisis y evaluación. * Su participación no implica ningún costo ni beneficio económico directo. Autorización: Mediante la firma del presente documento, autorizo a la Organización de las Naciones Unidas para la Alimentación y la Agricultura (FAO) a utilizar la información proporcionada durante este proceso exclusivamente con fines de análisis, evaluación y elaboración de informes del proyecto." | EH1: ¿El productor o informante autoriza registrar las coordenadas de la parcela donde se encuentra? | EI1: Registre las coordenadas de la esquina de la parcela | EJ1: Si no registró las coordenadas GPS, especifique el motivo | EK1: ¿Cuál es el número de teléfono del productor? | EL1: ¿Podría darnos otro número de contacto o correo electrónico del productor? | EM1: Hemos llegado al final de la encuesta. Le agradecemos su participación y le deseamos un buen día. Hasta luego. | EN1: Encuestador, incluya notas o comentarios si los tiene. | EO1: Si respuesta es No, pause la encuesta y pida hablar con productor o informante | EP1: ¿Cuál es su función en las actividades agrícolas, pecuarias o forestales? | EQ1: Durante la (temporada agrícola de mayo 2025 a abril 2026), ¿cuál es la principal fuente de ingresos económicos en su hogar? | ER1: ¿Recuerda el nombre del Promotor Comunitario de su Escuela de Campo? | ES1: _id | ET1: _uuid | EU1: _submission_time | EV1: _validation_status | EW1: _notes | EX1: _status | EY1: _submitted_by | EZ1: __version__ | FA1: _tags | FB1: meta/rootUuid | FC1: KoboIndex
A2: ="V"&B2&"-R"&FC2 -> V1-R1 | B2: 1 | C2: 46199.414 | D2: 46199.419 | E2: 46199 | G2: William | H2: Rigoberto | I2: 46199 | K2: ANA YESENIA REYES AGUIRRE | L2: 40 | M2: Mujer | O2: La Paz | P2: La Paz Centro | Q2: San Juan Tepezontes | R2: LOS LAURELES | S2: LOS LAURELES | V2: ANA YESENIA REYESAGUIRRE | W2: Sí | Y2: Productor | AB2: Sí | AD2: No sabe / no responde | AF2: No | EK2: 78077117 | ES2: 22169725 | ET2: c27bf41a-5a46-4ff0-8891-ba6f899821e0 | EU2: 46199.669 | EX2: submitted_via_web | EY2: encuestador_adepro | EZ2: vx3xVKqsiQtpxk6VuQQ43v | FB2: uuid:c27bf41a-5a46-4ff0-8891-ba6f899821e0 | FC2: 1
A3: ="V"&B3&"-R"&FC3 -> V1-R2 | B3: 1 | C3: 46199.432 | D3: 46199.436 | E3: 46199 | G3: Wendy | H3: Rigoberto | I3: 46199 | K3: VICENTE HERNANDEZ | L3: 63 | M3: Hombre | O3: La Paz | R3: SAN JERONIMO | S3: SAN JERONIMO | V3: VICENTE HERNANDEZ | W3: Sí | AB3: Sí | AF3: No | EH3: Sí | EI3: PENDIENTE | EK3: 74263711 | ES3: 22170005 | ET3: 68e6f4cb-93f4-4199-b80b-31248180af63 | EU3: 46199.698 | EX3: submitted_via_web | EY3: encuestador_adepro | EZ3: vx3xVKqsiQtpxk6VuQQ43v | FB3: uuid:68e6f4cb-93f4-4199-b80b-31248180af63 | FC3: 2
A4: ="V"&B4&"-R"&FC4 -> V1-R3 | B4: 1 | C4: 46199.437 | D4: 46199.448 | E4: 46199 | V4: VICENTE HERNANDEZ | W4: Sí | AB4: Sí | AD4: Sí | AF4: No | EH4: Sí | EI4: 13.5302145 -88.907325 0.0 0.0;13.538104792939846 -88.89374367892742 0.0 0.0;13.545652935769432 -88.88331055641174 0.0 0.0;13.552622621472658 -88.86587116867304 0.0 0.0;13.544064576342993 -88.86467322707176 0.0 0.0;13.533598023217413 -88.85741081088781 0.0 0.0;13.52911203041512 -88.8476700335741 0.0 0.0;13.519300704714041 -88.84321823716164 0.0 0.0;13.508328740164771 -88.85714024305344 0.0 0.0;13.5302145 -88.907325 0.0 0.0 | EK4: 74263031 | ES4: 22170006 | ET4: d17de3ac-af9a-4c3c-aacb-113ffdeb3ef5 | EU4: 46199.698 | EX4: submitted_via_web | EY4: encuestador_adepro | EZ4: vx3xVKqsiQtpxk6VuQQ43v | FB4: uuid:d17de3ac-af9a-4c3c-aacb-113ffdeb3ef5 | FC4: 3
A5: ="V"&B5&"-R"&FC5 -> V1-R4 | B5: 1 | C5: 46199.464 | D5: 46199.474 | E5: 46199 | G5: Iván | H5: Milagro | I5: 46199 | K5: ELIA DEL CARMEN PORTILLO | L5: 83 | M5: Mujer | O5: La Paz | P5: La Paz Centro | Q5: El Rosario | R5: EL TUNAL | S5: LA COQUERA | V5: ELIA PORTILLO | W5: Sí | Y5: Productor | AB5: Sí | AD5: No | AF5: No | EH5: Sí | EI5: 13.5000084 -89.004493 0.0 0.0;13.5000944 -89.0046434 0.0 0.0;13.5002997 -89.0044582 0.0 0.0;13.5002343 -89.0043771 0.0 0.0;13.5000084 -89.004493 0.0 0.0 | EK5: 68542233 | ES5: 22324058 | ET5: 37111e0c-945e-4344-bb3e-3dc046ff4190 | EU5: 46211.125 | EX5: submitted_via_web | EY5: encuestador_adepro | EZ5: vx3xVKqsiQtpxk6VuQQ43v | FB5: uuid:37111e0c-945e-4344-bb3e-3dc046ff4190 | FC5: 4
A6: ="V"&B6&"-R"&FC6 -> V1-R5 | B6: 1 | C6: 46199.352 | D6: 46199.365 | E6: 46199 | G6: Iván | H6: Milagro | I6: 46199 | K6: GERSON ANTONIO PEREZ | L6: 25 | M6: Hombre | O6: La Paz | P6: La Paz Centro | Q6: El Rosario | R6: EL TUNAL | S6: PUENTE VIEJO | V6: GERSON PEREZ | W6: Sí | Y6: Productor | AB6: Sí | AF6: No | EH6: No | EJ6: Lejanía, dentro del distritio | EK6: 60776103 | ES6: 22325150 | ET6: 0847d69c-3f4c-4045-a801-cdfdc6a97c0b | EU6: 46211.166 | EX6: submitted_via_web | EY6: encuestador_adepro | EZ6: vx3xVKqsiQtpxk6VuQQ43v | FB6: uuid:0847d69c-3f4c-4045-a801-cdfdc6a97c0b | FC6: 5
A7: ="V"&B7&"-R"&FC7 -> V2-R1 | B7: 2 | C7: 46202.371 | D7: 46202.416 | E7: 46201 | G7: Javier | H7: Milagro | I7: 46202 | K7: WILLIAM GEOVANNY RIVERA AYALA | L7: 29 | M7: Hombre | O7: Usulután | P7: Usulután Oeste | Q7: Jiquilisco | R7: COMUNIDAD LOS LOTES | V7: WILLIAM GEOVANNY RIVERA AYALA | W7: Sí | Y7: Productor | AB7: Sí | AD7: Sí | AF7: Sí | AG7: 1 | AH7: 1 | AI7: 1 | AJ7: 50 | AK7: 40 | AL7: 200 | AM7: 90 | AN7: 250 | AV7: Sí | AW7: 2020 | AX7: Sí | AY7: No | AZ7: SARAI EMERITA | BA7: Sí | BB7: Regeneración artificial (plantación de árboles) | BC7: No | BD7: No | BL7: Sin cambió | BM7: Otra, especificar | BN7: PLAGAS | BO7: Tractor Equipo de fumigación | BP7: 1 | BQ7: 0 | BR7: 0 | BS7: 0 | BT7: 0 | BU7: 1 | BV7: 0 | BW7: 0 | BX7: 0 | BY7: 0 | BZ7: 0 | CA7: 0 | CB7: 0 | CC7: Sequías | CD7: 0 | CE7: 1 | CF7: 0 | CG7: 0 | CH7: 0 | CI7: 0 | CJ7: 0 | CK7: 0 | CL7: 0 | CM7: 2 | CO7: Oficios varios (artesanías, carpintería, albañilería, etc.) | CP7: Sí | CQ7: No | CR7: No | CS7: No | CT7: No | CU7: No | CV7: No | CW7: No | CX7: No | DG7: 5 | DH7: 0 | DI7: 3 | DJ7: 1 | DK7: 2 | DL7: 3 | DM7: 6 | DN7: 7 | DO7: Sí | DP7: Pozo | DR7: Sí | DS7: Sí | DT7: Jul | DU7: 0 | DV7: 0 | DW7: 0 | DX7: 0 | DY7: 0 | DZ7: 0 | EA7: 1 | EB7: 0 | EC7: 0 | ED7: 0 | EE7: 0 | EF7: 0 | EH7: Sí | EI7: 13.390987 -88.668225 40.74118598854011 10.495014000000001;13.390987 -88.668225 40.74118598854011 10.495014000000001;13.390987 -88.668225 40.74118598854011 10.495014000000001;13.390987 -88.668225 40.74118598854011 10.495014000000001;13.390987 -88.668225 40.74118598854011 10.495014000000001;13.390987 -88.668225 40.74118598854011 10.495014000000001;13.390987 -88.668225 40.74118598854011 10.495014000000001;13.390987 -88.668225 40.74118598854011 10.495014000000001;13.390987 -88.668225 40.74118598854011 10.495014000000001;13.390987 -88.668225 40.74118598854011 10.495014000000001;13.390987 -88.668225 40.74118598854011 10.495014000000001;13.390987 -88.668225 40.74118598854011 10.495014000000001;13.390987 -88.668225 40.74118598854011 10.495014000000001;13.390987 -88.668225 40.74118598854011 10.495014000000001;13.390987 -88.668225 40.74118598854011 10.495014000000001;13.390987 -88.668225 40.74118598854011 10.495014000000001;13.390987 -88.668225 40.74118598854011 10.495014000000001;13.390987 -88.668225 40.74118598854011 10.495014000000001;13.390987 -88.668225 40.74118598854011 10.495014000000001;13.390987 -88.668225 40.74118598854011 10.495014000000001;13.390987 -88.668225 40.74118598854011 10.495014000000001;13.390987 -88.668225 40.74118598854011 10.495014000000001;13.390987 -88.668225 40.74118598854011 10.495014000000001;13.390987 -88.668225 40.74118598854011 10.495014000000001;13.390987 -88.668225 40.74118598854011 10.495014000000001;13.390987 -88.668225 40.74118598854011 10.495014000000001;13.390987 -88.668225 40.74118598854011 10.495014000000001;13.390987 -88.668225 40.74118598854011 10.495014000000001;13.390987 -88.668225 40.74118598854011 10.495014000000001;13.390987 -88.668225 40.74118598854011 10.495014000000001;13.390987 -88.668225 40.74118598854011 10.495014000000001;13.390987 -88.668225 40.74118598854011 10.495014000000001;13.390987 -88.668225 40.74118598854011 10.495014000000001;13.390987 -88.668225 40.74118598854011 10.495014000000001;13.390987 -88.668225 40.74118598854011 10.495014000000001;13.390987 -88.668225 40.74118598854011 10.495014000000001;13.390987 -88.668225 40.74118598854011 10.495014000000001;13.390987 -88.668225 40.74118598854011 10.495014000000001;13.390987 -88.668225 40.74118598854011 10.495014000000001;13.390987 -88.668225 40.74118598854011 10.495014000000001;13.390987 -88.668225 40.74118598854011 10.495014000000001;13.390987 -88.668225 40.74118598854011 10.495014000000001;13.390987 -88.668225 40.74118598854011 10.495014000000001;13.390987 -88.668225 40.74118598854011 10.495014000000001;13.390987 -88.668225 40.74118598854011 10.495014000000001;13.390987 -88.668225 40.74118598854011 10.495014000000001;13.390987 -88.668225 40.74118598854011 10.495014000000001;13.390987 -88.668225 40.74118598854011 10.495014000000001;13.390987 -88.668225 40.74118598854011 10.495014000000001 | EK7: 63009520 | EL7: 79634644 | EN7: NINGUNO | ES7: 22204810 | ET7: c98c95d6-65c9-4baf-881b-81a1715fc4c6 | EU7: 46202.678 | EX7: submitted_via_web | EY7: adepro | EZ7: vzzpoqrQEmZ8kFXEawwS6F | FB7: uuid:c98c95d6-65c9-4baf-881b-81a1715fc4c6 | FC7: 1
A8: ="V"&B8&"-R"&FC8 -> V2-R2 | B8: 2 | C8: 46202.416 | D8: 46202.449 | E8: 46201 | G8: Javier | H8: Milagro | I8: 46202 | K8: JONATHAN ALEJANDRO AMAYA CLIMACO | L8: 33 | M8: Hombre | O8: Usulután | P8: Usulután Oeste | Q8: Jiquilisco | R8: LA NORIA | V8: JONATHAN ALEJANDRO AMAYA CLIMACO | W8: Sí | Y8: Productor | AB8: Sí | AD8: Sí | AF8: Sí | AG8: 1 | AH8: 3 | AI8: 1 | AJ8: 300 | AK8: 150 | AL8: 30 | AM8: 50 | AN8: 600 | AV8: Sí | AW8: 2020 | AX8: Sí | AY8: Sí | AZ8: NO SABE | BA8: No | BO8: Ningún activo | BP8: 0 | BQ8: 0 | BR8: 0 | BS8: 0 | BT8: 0 | BU8: 0 | BV8: 0 | BW8: 0 | BX8: 0 | BY8: 0 | BZ8: 0 | CA8: 0 | CB8: 1 | CC8: Sequías | CD8: 0 | CE8: 1 | CF8: 0 | CG8: 0 | CH8: 0 | CI8: 0 | CJ8: 0 | CK8: 0 | CL8: 0 | CM8: 1 | CO8: Jornalero agropecuario | CP8: Sí | CQ8: No | CR8: No | CS8: No | CT8: No | CU8: No | CV8: No | CW8: No | CX8: No | DG8: 3 | DH8: 2 | DI8: 7 | DJ8: 2 | DK8: 3 | DL8: 3 | DM8: 7 | DN8: 7 | DO8: Sí | DP8: Pozo | DR8: Sí | DS8: Sí | DT8: Ago | DU8: 0 | DV8: 0 | DW8: 0 | DX8: 0 | DY8: 0 | DZ8: 0 | EA8: 0 | EB8: 1 | EC8: 0 | ED8: 0 | EE8: 0 | EF8: 0 | EH8: Sí | EI8: 13.385908 -88.67585 31.642824482172728 4.7486515301917995;13.385633 -88.675305 0 0;13.38606 -88.675058 0 0;13.3864 -88.675058 0 0;13.386927 -88.675144 0 0;13.387125 -88.67552 0 0;13.386895 -88.675928 0 0;13.386661 -88.676131 0 0;13.386462 -88.676233 0 0;13.385977 -88.675917 0 0;13.385908 -88.67585 31.642824482172728 4.7486515301917995 | EK8: 79592066 | EN8: NINGUNO | ES8: 22205258 | ET8: 6f0cebe3-270d-4422-a021-d10d5811ee1d | EU8: 46202.699 | EX8: submitted_via_web | EY8: adepro | EZ8: vzzpoqrQEmZ8kFXEawwS6F | FB8: uuid:6f0cebe3-270d-4422-a021-d10d5811ee1d | FC8: 2
A9: ="V"&B9&"-R"&FC9 -> V2-R3 | B9: 2 | C9: 46202.505 | D9: 46202.529 | E9: 46202 | G9: Juan | H9: Rigoberto | K9: JUAN PABLO CARRANZA GIRON | L9: 42 | M9: Hombre | O9: San Miguel | P9: San Miguel Oeste | Q9: El Transito | R9: CALLE NUEVA | S9: LA LINEA | V9: JUAN PABLO CARRANZA | W9: Sí | AB9: Sí | AD9: No | AF9: Sí | AG9: 1 | AH9: 1 | AI9: 1 | AJ9: 45 | AK9: 100 | AL9: 50 | AM9: 150 | AV9: Sí | AW9: 2025 | AX9: No | AY9: No | BA9: No | BO9: Arado Equipo de fumigación | BP9: 0 | BQ9: 0 | BR9: 0 | BS9: 0 | BT9: 0 | BU9: 1 | BV9: 0 | BW9: 0 | BX9: 0 | BY9: 0 | BZ9: 0 | CA9: 0 | CB9: 0 | CC9: Sequías Vientos fuertes | CD9: 0 | CE9: 1 | CF9: 0 | CG9: 0 | CH9: 1 | CI9: 0 | CJ9: 0 | CK9: 0 | CL9: 0 | CM9: 5 | CO9: Producción agropecuaria | CP9: Sí | CQ9: Sí | CR9: Sí | CS9: Sí | CT9: No | CU9: Sí | CV9: Sí | CW9: Sí | CX9: Sí | CY9: Sí | CZ9: Sí | DA9: No | DB9: Sí | DC9: Sí | DD9: No | DE9: No | DG9: 7 | DH9: 0 | DI9: 7 | DJ9: 3 | DK9: 0 | DL9: 7 | DM9: 7 | DN9: 7 | DO9: Sí | DP9: Pozo | DR9: Sí | DS9: No | DT9: Ene Feb Mar Abr Ago Jun Jul May Sep Oct Nov Dic | DU9: 1 | DV9: 1 | DW9: 1 | DX9: 1 | DY9: 1 | DZ9: 1 | EA9: 1 | EB9: 1 | EC9: 1 | ED9: 1 | EE9: 1 | EF9: 1 | EH9: No | EJ9: Otra | EK9: 74182063 | EL9: 74182063 | EN9: NO SE MIDIO LA PARCELA POR MOTIVOS DE HERENCIA QUE NO ESTA DEFINIDO LA DIVISION DEL TERRENO | ES9: 22206850 | ET9: 62ca324f-4710-41b1-bef2-add9a128d1e7 | EU9: 46202.789 | EX9: submitted_via_web | EY9: encuestador_adepro | EZ9: vzzpoqrQEmZ8kFXEawwS6F | FB9: uuid:62ca324f-4710-41b1-bef2-add9a128d1e7 | FC9: 3
A10: ="V"&B10&"-R"&FC10 -> V2-R4 | B10: 2 | C10: 46202.562 | D10: 46202.588 | E10: 46202 | G10: Juan | H10: Rigoberto | K10: GERTRUDIS CRUZ CRUZ | L10: 33 | M10: Hombre | O10: San Miguel | P10: San Miguel Oeste | Q10: El Transito | R10: CALLE NUEVA | S10: SAN CARLOS | V10: GERTRUDIS CRUZ CRUZ | W10: Sí | AB10: Sí | AD10: No | AF10: Sí | AG10: 1 | AH10: 1 | AI10: 1 | AJ10: 60 | AK10: 300 | AL10: 50 | AM10: 75 | AN10: 250 | AV10: Sí | AW10: 2025 | AX10: No | AY10: No | BA10: No | BO10: Bomba de agua Equipo de fumigación | BP10: 0 | BQ10: 0 | BR10: 0 | BS10: 0 | BT10: 0 | BU10: 1 | BV10: 0 | BW10: 1 | BX10: 0 | BY10: 0 | BZ10: 0 | CA10: 0 | CB10: 0 | CC10: No sufrió pérdidas de cosecha o animales | CD10: 0 | CE10: 0 | CF10: 0 | CG10: 0 | CH10: 0 | CI10: 0 | CJ10: 0 | CK10: 0 | CL10: 1 | CM10: 6 | CO10: Jornalero agropecuario | CP10: Sí | CQ10: No | CR10: No | CS10: No | CT10: No | CU10: No | CV10: No | CW10: No | CX10: Sí | CY10: No | CZ10: No | DA10: No | DB10: No | DC10: No | DD10: No | DE10: No | DG10: 4 | DH10: 0 | DI10: 4 | DJ10: 2 | DK10: 5 | DL10: 7 | DM10: 7 | DN10: 1 | DO10: Sí | EH10: Sí | EI10: 13.3740134 -88.278169 0.0 0.0;13.3748247 -88.2782237 0.0 0.0;13.3748013 -88.2776332 0.0 0.0;13.374145 -88.2776854 0.0 0.0;13.3740134 -88.278169 0.0 0.0 | EK10: 73127467 | EL10: 73127467 | EN10: NINGUNO | ES10: 22207297 | ET10: 4dc24167-1b02-4ff6-b174-9fd59b2cef2c | EU10: 46202.839 | EX10: submitted_via_web | EY10: encuestador_adepro | EZ10: vzzpoqrQEmZ8kFXEawwS6F | FB10: uuid:4dc24167-1b02-4ff6-b174-9fd59b2cef2c | FC10: 4
A11: ="V"&B11&"-R"&FC11 -> V2-R5 | B11: 2 | C11: 46202.723 | D11: 46202.742 | E11: 46202 | W11: Sí | AB11: Sí | AD11: Sí | AF11: Sí | AV11: Sí | AW11: 2023 | AX11: Sí | AY11: Sí | AZ11: NO SABE | CM11: 4 | CP11: No | CQ11: No | CR11: No | CS11: No | CT11: No | CU11: No | CV11: No | CW11: No | CX11: No | EH11: Sí | EI11: 13.3087066 -88.5708734 0.0 0.0;13.308305945039907 -88.57060186564922 0.0 0.0;13.3080069 -88.5691306 0.0 0.0;13.3077682 -88.569366 0.0 0.0;13.3087066 -88.5708734 0.0 0.0 | EK11: 60259676 | EN11: EMPIEZAN A SEMBRAR PIPIAN Y DESPUES SEMBRARAN MAIZ | ES11: 22208802 | ET11: a5c4ebc3-b10b-4e28-8c95-2fec8cbe7c5f | EU11: 46202.992 | EX11: submitted_via_web | EY11: encuestador_adepro | EZ11: vzzpoqrQEmZ8kFXEawwS6F | FB11: uuid:a5c4ebc3-b10b-4e28-8c95-2fec8cbe7c5f | FC11: 5
A12: ="V"&B12&"-R"&FC12 -> V2-R6 | B12: 2 | C12: 46202.402 | D12: 46203.336 | E12: 46202 | G12: Zaira | H12: Milagro | I12: 46202 | K12: JOSE ESTANISLAO RODRIGUEZ | L12: 69 | M12: Hombre | O12: Usulután | P12: Usulután Oeste | Q12: Jiquilisco | R12: CANTON LA NORIA | S12: LA MARANONERA | V12: WENDY RODRIGUEZ | W12: Sí | Y12: Familiar del productor | AB12: Sí | AD12: No | AF12: Sí | AG12: 1 | AH12: 2 | AI12: 1 | AJ12: 200 | AN12: 500 | AV12: Sí | AW12: 2023 | AX12: Sí | AY12: Sí | AZ12: FRANCISCO | BA12: Sí | BO12: Tractor Arado Rastra Cultivadora Sembradora Podadora Equipo de fumigación | BP12: 1 | BQ12: 1 | BR12: 1 | BS12: 1 | BT12: 1 | BU12: 1 | BV12: 0 | BW12: 0 | BX12: 0 | BY12: 0 | BZ12: 0 | CA12: 0 | CB12: 0 | CC12: Sequías | CD12: 0 | CE12: 1 | CF12: 0 | CG12: 0 | CH12: 0 | CI12: 0 | CJ12: 0 | CK12: 0 | CL12: 0 | CM12: 5 | CO12: Producción agropecuaria | CP12: No | CQ12: No | CR12: No | CS12: No | CT12: No | CU12: No | CV12: No | CW12: No | CX12: Sí | CY12: No | CZ12: No | DA12: No | DB12: No | DC12: No | DD12: No | DE12: No | DG12: 7 | DH12: 7 | DI12: 7 | DJ12: 3 | DK12: 7 | DL12: 7 | DM12: 7 | DN12: 7 | DO12: Sí | DP12: Agua entubada | DR12: Sí | DS12: Sí | DT12: Ene Feb Mar Abr May Jun Jul Ago Sep Oct Nov Dic | DU12: 1 | DV12: 1 | DW12: 1 | DX12: 1 | DY12: 1 | DZ12: 1 | EA12: 1 | EB12: 1 | EC12: 1 | ED12: 1 | EE12: 1 | EF12: 1 | EH12: Sí | EI12: 13.3872594 -88.678072 0.0 0.0; 13.3873038 -88.6779345 0.0 0.0; 13.3876548 -88.6778923 0.0 0.0; 13.3876391 -88.6780116 0.0 0.0; 13.3872594 -88.678072 0.0 0.0 | EK12: 76169140 | EN12: LA HIJA ES BENEFICIARIA | ES12: 22217390 | ET12: 09e653af-0ea9-44a4-b386-4db9c752e2ec | EU12: 46203.586 | EX12: submitted_via_web | EY12: encuestador_adepro | EZ12: vzzpoqrQEmZ8kFXEawwS6F | FB12: uuid:09e653af-0ea9-44a4-b386-4db9c752e2ec | FC12: 6
A13: ="V"&B13&"-R"&FC13 -> V2-R7 | B13: 2 | C13: 46202.42 | D13: 46202.439 | E13: 46202 | G13: Wendy | H13: Rigoberto | I13: 46202 | K13: NHEMY DEL CARMEN GOMEZ CANAS | L13: 50 | M13: Mujer | O13: San Miguel | P13: San Miguel Centro | Q13: San Miguel | R13: CANTON PRIMAVERA EL TRANSITO | S13: PRIMAVERA | V13: NOHEMY GARCIA | W13: Sí | Y13: Productor | AB13: Sí | AD13: No | AF13: Sí | AG13: 2 | AH13: 20 | AI13: 2 | AJ13: 700 | AK13: 18 | AM13: 10 | AN13: 600 | AV13: Sí | AW13: 2021 | AX13: Sí | AY13: Sí | AZ13: LUIS | BA13: Sí | BB13: Regeneración artificial (plantación de árboles) | BC13: No | BD13: Sí | BE13: RECLIMA ONG | BF13: 0 | BG13: 1 | BH13: 0 | BI13: 1 | BJ13: 0 | BK13: 0 | BL13: Aumentó mucho | BM13: Sequías extremas | BO13: Rastra Bomba de agua | BP13: 0 | BQ13: 1 | BR13: 0 | BS13: 0 | BT13: 0 | BU13: 0 | BV13: 0 | BW13: 1 | BX13: 0 | BY13: 0 | BZ13: 0 | CA13: 0 | CB13: 0 | CC13: Sequías | CD13: 0 | CE13: 1 | CF13: 0 | CG13: 0 | CH13: 0 | CI13: 0 | CJ13: 0 | CK13: 0 | CL13: 0 | CM13: 3 | CP13: Sí | CQ13: Sí | CR13: No | CS13: Sí | CT13: No | CU13: Sí | CV13: No | CW13: No | CX13: No | DG13: 4 | DH13: 7 | DI13: 2 | DJ13: 7 | DK13: 7 | DM13: 7 | DO13: Sí | EH13: Sí | EI13: PENDIENTE | EK13: 70901542 | EN13: NINGUNA | ES13: 22218815 | ET13: 9d47a5d0-8b09-4fa9-b01f-233bb0700fa5 | EU13: 46203.626 | EX13: submitted_via_web | EY13: encuestador_adepro | EZ13: vzzpoqrQEmZ8kFXEawwS6F | FB13: uuid:9d47a5d0-8b09-4fa9-b01f-233bb0700fa5 | FC13: 7
A14: ="V"&B14&"-R"&FC14 -> V2-R9 | B14: 2 | C14: 46202.442 | D14: 46202.457 | E14: 46202 | G14: Wendy | K14: NOHEMY HERNANDEZ | L14: 50 | M14: Mujer | O14: San Miguel | P14: San Miguel Centro | W14: Sí | AB14: Sí | AD14: No | AF14: No | EH14: Sí | EI14: 13.3517716 -88.3129451 0.0 0.0;13.366207480874408 -88.30100432038307 0.0 0.0;13.3516734 -88.3126581 0.0 0.0;13.38270582382977 -88.31388127058744 0.0 0.0;13.370796012408158 -88.32492057234049 0.0 0.0;13.360910027285502 -88.33363708108664 0.0 0.0;13.35930315352596 -88.32394257187843 0.0 0.0;13.3516734 -88.3126581 0.0 0.0;13.354877834419723 -88.31916455179453 0.0 0.0;13.344480331347976 -88.32389261573553 0.0 0.0;13.3516734 -88.3126581 0.0 0.0;13.354877834419723 -88.31916455179453 0.0 0.0;13.3516832424863 -88.32698956131935 0.0 0.0;13.3517716 -88.3129451 0.0 0.0 | EK14: 70901542 | EN14: MEDICION NOHEMY | ES14: 22218817 | ET14: acd3087f-99f7-4159-b895-d99fd8954ce0 | EU14: 46203.626 | EX14: submitted_via_web | EY14: encuestador_adepro | EZ14: vzzpoqrQEmZ8kFXEawwS6F | FB14: uuid:acd3087f-99f7-4159-b895-d99fd8954ce0 | FC14: 9
A15: ="V"&B15&"-R"&FC15 -> V2-R10 | B15: 2 | C15: 46202.48 | D15: 46203.376 | E15: 46202 | G15: Wendy | H15: Rigoberto | I15: 46202 | K15: MARIA DE JESUS RIVAS LISAMA | L15: 37 | M15: Mujer | O15: San Miguel | P15: San Miguel Centro | Q15: San Miguel | R15: CANTON PRIMAVERA | S15: CASERIO MI ANGULO | V15: MARIA RIVAS LISAMA | W15: Sí | Y15: Productor | AB15: Sí | AD15: No | AF15: Sí | AG15: 1 | AH15: 1 | AI15: 1 | AJ15: 60 | AK15: 250 | AL15: 50 | AM15: 10 | AN15: 500 | AV15: Sí | AW15: 2022 | AX15: No | AY15: No | BA15: No | BO15: Ningún activo | BP15: 0 | BQ15: 0 | BR15: 0 | BS15: 0 | BT15: 0 | BU15: 0 | BV15: 0 | BW15: 0 | BX15: 0 | BY15: 0 | BZ15: 0 | CA15: 0 | CB15: 1 | CC15: Lluvia o inundaciones | CD15: 0 | CE15: 0 | CF15: 1 | CG15: 0 | CH15: 0 | CI15: 0 | CJ15: 0 | CK15: 0 | CL15: 0 | CM15: 6 | CO15: Oficios varios (artesanías, carpintería, albañilería, etc.) | CP15: Sí | CQ15: No | CR15: No | CS15: No | CT15: No | CU15: No | CV15: No | CW15: No | CX15: Sí | CY15: No | CZ15: No | DA15: No | DB15: No | DC15: No | DD15: No | DE15: No | DG15: 4 | DH15: 2 | DI15: 3 | DJ15: 2 | DK15: 7 | DL15: 2 | DM15: 4 | DN15: 2 | DO15: Sí | EH15: Sí | EI15: 13.357721060704327 -88.33317708224058 0.0 0.0; 13.3581517 -88.3280833 0.0 0.0; 13.36168214491333 -88.32408539950848 0.0 0.0; 13.36489193568014 -88.32735233008862 0.0 0.0; 13.366843232724067 -88.33146013319492 0.0 0.0; 13.362531895508418 -88.33362702280283 0.0 0.0; 13.357721060704327 -88.33317708224058 0.0 0.0; 13.35580100587401 -88.3308569714427 0.0 0.0; 13.35630108278788 -88.32847315818071 0.0 0.0; 13.357887751797747 -88.32608465105295 0.0 0.0; 13.359539977249463 -88.32547713071108 0.0 0.0; 13.36168214491333 -88.32408539950848 0.0 0.0; 13.361389542959886 -88.32656778395176 0.0 0.0; 13.364369042800197 -88.32464531064034 0.0 0.0; 13.357721060704327 -88.33317708224058 0.0 0.0 | EK15: 69554723 | EL15: 76000631 | EN15: NINGUNO | ES15: 22218831 | ET15: 7b9380eb-f042-411a-81cb-3d51ad535f36 | EU15: 46203.627 | EX15: submitted_via_web | EY15: encuestador_adepro | EZ15: vzzpoqrQEmZ8kFXEawwS6F | FB15: uuid:7b9380eb-f042-411a-81cb-3d51ad535f36 | FC15: 10
A16: ="V"&B16&"-R"&FC16 -> V2-R11 | B16: 2 | C16: 46202.443 | D16: 46202.466 | E16: 46202 | G16: Rodrigo | H16: Rigoberto | I16: 46202 | K16: MARCO ANTONIO CALDERON GARCIA | L16: 50 | M16: Hombre | V16: MARCO CALDERON | W16: Sí | Y16: Productor | AB16: Sí | AF16: Sí | AG16: 1 | AH16: 1 | AI16: 1 | AJ16: 65 | AK16: 10 | AM16: 240 | AV16: Sí | AW16: 2024 | AX16: Sí | AY16: No | AZ16: ISELA QUINTANILLA | BA16: Sí | BB16: Regeneración artificial (plantación de árboles) | BC16: No | BD16: Sí | BE16: ONG | BF16: 0 | BG16: 0 | BH16: 0 | BI16: 1 | BJ16: 0 | BK16: 0 | BL16: Sin cambió | BM16: Otra, especificar | BN16: FALTA DE AGUA | BO16: Arado | BP16: 0 | BQ16: 0 | BR16: 0 | BS16: 0 | BT16: 0 | BU16: 0 | BV16: 0 | BW16: 0 | BX16: 0 | BY16: 0 | BZ16: 0 | CA16: 0 | CB16: 0 | CC16: Sequías | CD16: 0 | CE16: 1 | CF16: 0 | CG16: 0 | CH16: 0 | CI16: 0 | CJ16: 0 | CK16: 0 | CL16: 0 | CM16: 5 | CO16: Jornalero agropecuario | CP16: Sí | CQ16: Sí | CR16: Sí | CS16: Sí | CT16: No | CU16: Sí | CV16: Sí | CW16: No | CX16: Sí | CY16: Sí | CZ16: Sí | DA16: No | DB16: No | DC16: No | DD16: No | DE16: No | DG16: 5 | DH16: 4 | DI16: 0 | DJ16: 0 | DK16: 5 | DL16: 1 | DM16: 7 | DN16: 0 | DO16: Sí | DP16: Agua entubada | DR16: Sí | DS16: Sí | DT16: Ene Feb Mar Abr May Jun Jul Ago Sep Oct Nov Dic | DU16: 1 | DV16: 1 | DW16: 1 | DX16: 1 | DY16: 1 | DZ16: 1 | EA16: 1 | EB16: 1 | EC16: 1 | ED16: 1 | EE16: 1 | EF16: 1 | EH16: Sí | EI16: 13.3621856 -88.3216157 0.0 0.0;13.362157 -88.3217061 0.0 0.0;13.361951 -88.3216423 0.0 0.0;13.3620381 -88.3213908 0.0 0.0;13.3622319 -88.32135 0.0 0.0;13.3621856 -88.3216157 0.0 0.0 | EL16: 60163628 | EN16: PERDIO LA COSECHA DE FRIJOL | ES16: 22237409 | ET16: 5abdf5c2-add7-4462-8faf-09ebaf783be9 | EU16: 46204.66 | EX16: submitted_via_web | EY16: encuestador_adepro | EZ16: vzzpoqrQEmZ8kFXEawwS6F | FB16: uuid:5abdf5c2-add7-4462-8faf-09ebaf783be9 | FC16: 11
A17: ="V"&B17&"-R"&FC17 -> V2-R12 | B17: 2 | C17: 46202.471 | D17: 46202.485 | E17: 46202 | G17: Rodrigo | H17: Rigoberto | I17: 46202 | K17: CLAUDIA AZUCENA CAMPOS | L17: 36 | M17: Mujer | O17: San Miguel | P17: San Miguel Oeste | Q17: El Transito | R17: EL LLANO | S17: CASERIO LA CEIBA | V17: CLAUDIA CAMPOS | W17: Sí | Y17: Productor | AB17: Sí | AD17: No | AF17: Sí | AG17: 1 | AH17: 2 | AI17: 1 | AJ17: 100 | AK17: 250 | AL17: 100 | AN17: 600 | AV17: Sí | AW17: 2024 | AX17: Sí | AY17: No | AZ17: ISELA QUINTANILLA | BA17: Sí | BB17: Regeneración artificial (plantación de árboles) | BC17: No | BD17: Sí | BE17: ONG | BF17: 0 | BG17: 0 | BH17: 0 | BI17: 1 | BJ17: 0 | BK17: 0 | BL17: Sin cambió | BM17: Sequías extremas | BO17: Equipo de fumigación | BP17: 0 | BQ17: 0 | BR17: 0 | BS17: 0 | BT17: 0 | BU17: 1 | BV17: 0 | BW17: 0 | BX17: 0 | BY17: 0 | BZ17: 0 | CA17: 0 | CB17: 0 | CC17: No sufrió pérdidas de cosecha o animales | CD17: 0 | CE17: 0 | CF17: 0 | CG17: 0 | CH17: 0 | CI17: 0 | CJ17: 0 | CK17: 0 | CL17: 1 | CM17: 4 | CO17: Trabajo asalariado/permanente (sueldo regular) | CP17: No | CQ17: No | CR17: No | CS17: No | CT17: No | CU17: No | CV17: No | CW17: No | CX17: Sí | CY17: No | CZ17: No | DA17: No | DB17: No | DC17: No | DD17: No | DE17: No | DG17: 7 | DH17: 5 | DI17: 3 | DJ17: 7 | DK17: 7 | DL17: 3 | DM17: 7 | DN17: 7 | DO17: Sí | DP17: Agua entubada | DR17: Sí | DS17: Sí | DT17: Ene Feb Mar Abr May Jun Jul Ago Sep Oct Nov Dic | DU17: 1 | DV17: 1 | DW17: 1 | DX17: 1 | DY17: 1 | DZ17: 1 | EA17: 1 | EB17: 1 | EC17: 1 | ED17: 1 | EE17: 1 | EF17: 1 | EH17: No | EJ17: Lejanía, dentro del distritio | EK17: 71893551 | EN17: PRODUCCION DE AUTOCONSUMO | ES17: 22237410 | ET17: 49b4d306-077b-44ea-b767-d8c8025a9dd0 | EU17: 46204.66 | EX17: submitted_via_web | EY17: encuestador_adepro | EZ17: vzzpoqrQEmZ8kFXEawwS6F | FB17: uuid:49b4d306-077b-44ea-b767-d8c8025a9dd0 | FC17: 12
A18: ="V"&B18&"-R"&FC18 -> V2-R13 | B18: 2 | C18: 46202.38 | D18: 46204.689 | E18: 46202 | G18: Nancy | H18: Milagro | I18: 46202 | K18: JOSE JAVIER LOPEZ RIVERA | L18: 34 | M18: Hombre | O18: Usulután | P18: Usulután Oeste | Q18: Jiquilisco | R18: EL QUINAL | S18: ANDRES CHAVEZ | V18: JAVIER LOPEZ | W18: Sí | Y18: Productor | AB18: Sí | AD18: Sí | AF18: Sí | AG18: 1 | AH18: 2 | AI18: 1 | AJ18: 50 | AK18: 300 | AL18: 100 | AM18: 160 | AN18: 600 | AV18: Sí | AW18: 2023 | AX18: Sí | AY18: No | AZ18: MAIRA FELICITA VIGIL | BA18: No | BO18: Tanque para almacenamiento de agua | BP18: 0 | BQ18: 0 | BR18: 0 | BS18: 0 | BT18: 0 | BU18: 0 | BV18: 1 | BW18: 0 | BX18: 0 | BY18: 0 | BZ18: 0 | CA18: 0 | CB18: 0 | CC18: Sequías | CD18: 0 | CE18: 1 | CF18: 0 | CG18: 0 | CH18: 0 | CI18: 0 | CJ18: 0 | CK18: 0 | CL18: 0 | CM18: 4 | CO18: Trabajo asalariado/permanente (sueldo regular) | CP18: No | CQ18: No | CR18: Sí | CS18: Sí | CT18: No | CU18: Sí | CV18: No | CW18: No | CX18: No | DG18: 2 | DH18: 1 | DI18: 1 | DJ18: 2 | DK18: 7 | DL18: 2 | DM18: 1 | DN18: 1 | DO18: Sí | DP18: Agua entubada | DR18: No | DS18: No | DT18: Ene Feb Mar Abr May Jun Jul Ago Sep Oct Nov Dic | DU18: 1 | DV18: 1 | DW18: 1 | DX18: 1 | DY18: 1 | DZ18: 1 | EA18: 1 | EB18: 1 | EC18: 1 | ED18: 1 | EE18: 1 | EF18: 1 | EH18: Sí | EI18: 13.383103 -88.6711989 0.0 0.0; 13.3829272 -88.6704652 0.0 0.0; 13.3835793 -88.6703437 0.0 0.0; 13.3837088 -88.6711024 0.0 0.0; 13.383103 -88.6711989 0.0 0.0 | EK18: 70993454 | EN18: IDENTIFICA EL PROGRAMA Y LAS CAPACITACIONES QUE RECIBIO EN LA ACTUALIDAD TIENE CULTIVO DE LOROCO | ES18: 22241416 | ET18: 3af9b4dc-3abe-4559-bbd5-4c4cc09ddb0d | EU18: 46204.939 | EX18: submitted_via_web | EY18: encuestador_adepro | EZ18: vzzpoqrQEmZ8kFXEawwS6F | FB18: uuid:3af9b4dc-3abe-4559-bbd5-4c4cc09ddb0d | FC18: 13
A19: ="V"&B19&"-R"&FC19 -> V2-R14 | B19: 2 | C19: 46202.418 | D19: 46204.689 | E19: 46202 | G19: Nancy | H19: Milagro | I19: 46202 | K19: MERCEDES CATALINA CASTANEDA | L19: 71 | M19: Mujer | O19: Usulután | P19: Usulután Oeste | Q19: Jiquilisco | R19: TIERRA BLANCA | S19: TIERRA BLANCA | V19: MERCEDES CATALINA CASTANEDA | W19: Sí | Y19: Productor | AB19: Sí | AD19: Sí | AF19: Sí | AG19: 1 | AH19: 1 | AI19: 1 | AJ19: 50 | AK19: 300 | AL19: 30 | AM19: 300 | AV19: Sí | AW19: 2024 | AX19: Sí | AY19: Sí | AZ19: MAIRA FELICITA VIGIL | BA19: Sí | BB19: Regeneración artificial (plantación de árboles) | BC19: Sí | BD19: Sí | BE19: ONG | BF19: 0 | BG19: 0 | BH19: 0 | BI19: 1 | BJ19: 0 | BK19: 0 | BL19: Aumentó algo | BM19: Sequías extremas | BO19: Ningún activo | BP19: 0 | BQ19: 0 | BR19: 0 | BS19: 0 | BT19: 0 | BU19: 0 | BV19: 0 | BW19: 0 | BX19: 0 | BY19: 0 | BZ19: 0 | CA19: 0 | CB19: 1 | CC19: Sequías | CD19: 0 | CE19: 1 | CF19: 0 | CG19: 0 | CH19: 0 | CI19: 0 | CJ19: 0 | CK19: 0 | CL19: 0 | CM19: 1 | CO19: Remesas familiares | CP19: No | CQ19: No | CR19: No | CS19: No | CT19: No | CU19: No | CV19: No | CW19: No | CX19: No | DG19: 7 | DH19: 7 | DI19: 7 | DJ19: 0 | DK19: 3 | DL19: 7 | DM19: 7 | DN19: 7 | DO19: Sí | DP19: Agua entubada | DR19: Sí | DS19: Sí | DT19: Ene Feb Mar Abr May Jun Jul Ago Sep Oct Nov Dic | DU19: 1 | DV19: 1 | DW19: 1 | DX19: 1 | DY19: 1 | DZ19: 1 | EA19: 1 | EB19: 1 | EC19: 1 | ED19: 1 | EE19: 1 | EF19: 1 | EH19: Sí | EI19: 13.3914827 -88.6721747 0.0 0.0; 13.3917562 -88.6737844 0.0 0.0; 13.3912361 -88.6737714 0.0 0.0; 13.391086 -88.6721066 0.0 0.0; 13.3914827 -88.6721747 0.0 0.0 | EK19: 71918633 | ES19: 22241417 | ET19: 53b6be23-f68c-44be-827f-ae26d0d1b939 | EU19: 46204.939 | EX19: submitted_via_web | EY19: encuestador_adepro | EZ19: vzzpoqrQEmZ8kFXEawwS6F | FB19: uuid:53b6be23-f68c-44be-827f-ae26d0d1b939 | FC19: 14
A20: ="V"&B20&"-R"&FC20 -> V2-R15 | B20: 2 | C20: 46202.374 | D20: 46202.417 | E20: 46202 | G20: Iván | H20: Milagro | I20: 46202 | K20: SANTOS LORENZO DEL CID ZELAYA | L20: 45 | M20: Hombre | O20: Usulután | P20: Usulután Oeste | Q20: Jiquilisco | R20: ZAMORAN | S20: EL CEDRO | V20: SANTOS ZELAYA | W20: Sí | Y20: Productor | AB20: Sí | AF20: Sí | AG20: 1 | AH20: 4 | AI20: 1 | AK20: 200 | AL20: 160 | AM20: 350 | AN20: 1200 | AV20: Sí | AW20: 2024 | AX20: Sí | AY20: Sí | AZ20: SALVADOR | BA20: No | BO20: Bomba de agua Equipo para la cría o engorda de animales Autos particulares Bodega | BP20: 0 | BQ20: 0 | BR20: 0 | BS20: 0 | BT20: 0 | BU20: 0 | BV20: 0 | BW20: 1 | BX20: 1 | BY20: 1 | BZ20: 0 | CA20: 1 | CB20: 0 | CC20: Lluvia o inundaciones Plagas o enfermedades | CD20: 1 | CE20: 0 | CF20: 1 | CG20: 0 | CH20: 0 | CI20: 0 | CJ20: 0 | CK20: 0 | CL20: 0 | CM20: 5 | CO20: Producción agropecuaria | CP20: Sí | CQ20: No | CR20: Sí | CS20: Sí | CT20: No | CU20: No | CV20: Sí | CW20: No | CX20: Sí | CY20: No | CZ20: Sí | DA20: No | DB20: No | DC20: Sí | DD20: No | DE20: No | DG20: 7 | DH20: 3 | DI20: 5 | DJ20: 5 | DK20: 4 | DL20: 7 | DM20: 7 | DN20: 7 | DO20: Sí | DP20: Agua entubada | DR20: Sí | DS20: No | DT20: Ene Feb Mar Abr Jun Jul May Ago Sep Oct Nov Dic | DU20: 1 | DV20: 1 | DW20: 1 | DX20: 1 | DY20: 1 | DZ20: 1 | EA20: 1 | EB20: 1 | EC20: 1 | ED20: 1 | EE20: 1 | EF20: 1 | EH20: Sí | EI20: 13.31827 -88.7063505 0.0 0.0; 13.3179185 -88.7064647 0.0 0.0; 13.3184554 -88.7013528 0.0 0.0; 13.3189528 -88.7014116 0.0 0.0; 13.31827 -88.7063505 0.0 0.0 | EK20: 75747522 | EN20: CUARENTA VARIEDADES DE ARBOLES FRITAS | ES20: 22324081 | ET20: d4910001-71ec-4ff0-8292-9629eda9b27e | EU20: 46211.127 | EX20: submitted_via_web | EY20: encuestador_adepro | EZ20: vzzpoqrQEmZ8kFXEawwS6F | FB20: uuid:d4910001-71ec-4ff0-8292-9629eda9b27e | FC20: 15
A21: ="V"&B21&"-R"&FC21 -> V2-R16 | B21: 2 | C21: 46202.423 | D21: 46202.453 | E21: 46202 | G21: Iván | H21: Milagro | I21: 46202 | K21: CANDIDA ZELAYA DEL CID | L21: 72 | M21: Mujer | O21: Usulután | P21: Usulután Oeste | Q21: Jiquilisco | R21: EL ZAMORANO | S21: EL CEDRO | V21: CANDIDA ZELAYA | W21: Sí | Y21: Productor | AB21: Sí | AD21: Sí | AF21: Sí | AG21: 2 | AH21: 3 | AI21: 2 | AJ21: 40 | AK21: 35 | AL21: 35 | AM21: 100 | AV21: Sí | AW21: 2024 | AX21: Sí | AY21: Sí | AZ21: SALVADOR GOMEZ | BA21: Sí | BB21: Regeneración artificial (plantación de árboles) | BC21: No | BD21: Sí | BE21: RECLIMA | BF21: 0 | BG21: 1 | BH21: 0 | BI21: 0 | BJ21: 0 | BK21: 0 | BL21: Sin cambió | BM21: Sequías extremas | BO21: Equipo de fumigación | BP21: 0 | BQ21: 0 | BR21: 0 | BS21: 0 | BT21: 0 | BU21: 1 | BV21: 0 | BW21: 0 | BX21: 0 | BY21: 0 | BZ21: 0 | CA21: 0 | CB21: 0 | CC21: Sequías | CD21: 0 | CE21: 1 | CF21: 0 | CG21: 0 | CH21: 0 | CI21: 0 | CJ21: 0 | CK21: 0 | CL21: 0 | CM21: 2 | CO21: Jornalero agropecuario | CP21: Sí | CQ21: Sí | CR21: Sí | CS21: Sí | CT21: No | CU21: Sí | CV21: No | CW21: No | CX21: No | DG21: 4 | DH21: 7 | DI21: 2 | DJ21: 7 | DK21: 7 | DL21: 7 | DM21: 7 | DN21: 7 | DO21: Sí | DP21: Agua entubada | DR21: Sí | DS21: No | DT21: Ene Feb Mar Abr May Jun Jul Ago Sep Oct Nov Dic | DU21: 1 | DV21: 1 | DW21: 1 | DX21: 1 | DY21: 1 | DZ21: 1 | EA21: 1 | EB21: 1 | EC21: 1 | ED21: 1 | EE21: 1 | EF21: 1 | EH21: Sí | EI21: 13.317562 -88.6994162 0.0 0.0;13.317079 -88.6993005 0.0 0.0;13.3167429 -88.699978 0.0 0.0;13.317251 -88.7001076 0.0 0.0;13.317562 -88.6994162 0.0 0.0 | EK21: 73422704 | ES21: 22324202 | ET21: 4e002817-e8cf-41fb-b6bf-63dd4c5f272d | EU21: 46211.13 | EX21: submitted_via_web | EY21: encuestador_adepro | EZ21: vzzpoqrQEmZ8kFXEawwS6F | FB21: uuid:4e002817-e8cf-41fb-b6bf-63dd4c5f272d | FC21: 16
A22: ="V"&B22&"-R"&FC22 -> V2-R17 | B22: 2 | C22: 46202.468 | D22: 46210.627 | E22: 46202 | G22: Iván | H22: Milagro | I22: 46202 | K22: NOE ABRAHAN MARTINEZ GALVEZ | L22: 37 | M22: Hombre | O22: Usulután | P22: Usulután Oeste | Q22: Jiquilisco | R22: ZAMORANO | S22: LOS ZAMORANOS | T22: NK-574-0 | V22: NOE MARTINEZ | W22: Sí | Y22: Productor | AB22: Sí | AD22: No | AF22: Sí | AG22: 1 | AH22: 1 | AI22: 1 | AJ22: 60 | AK22: 40 | AL22: 17 | AM22: 100 | AV22: Sí | AW22: 2021 | AX22: No | AY22: No | BA22: No | BO22: Ningún activo | BP22: 0 | BQ22: 0 | BR22: 0 | BS22: 0 | BT22: 0 | BU22: 0 | BV22: 0 | BW22: 0 | BX22: 0 | BY22: 0 | BZ22: 0 | CA22: 0 | CB22: 1 | CC22: Sequías | CD22: 0 | CE22: 1 | CF22: 0 | CG22: 0 | CH22: 0 | CI22: 0 | CJ22: 0 | CK22: 0 | CL22: 0 | CM22: 3 | CO22: Jornalero agropecuario | CP22: Sí | CQ22: No | CR22: Sí | CS22: Sí | CT22: Sí | CU22: Sí | CV22: Sí | CW22: No | CX22: Sí | CY22: Sí | CZ22: Sí | DA22: No | DB22: Sí | DC22: Sí | DD22: No | DE22: No | DG22: 7 | DH22: 0 | DI22: 3 | DJ22: 6 | DK22: 7 | DL22: 6 | DM22: 7 | DN22: 2 | DO22: Sí | EH22: No | EJ22: Otra | EK22: 72502406 | EN22: NO SE PUDO MEDIR LA PARCELA POR QUE NO EL PRODUCTOR YA NO TIENE ACCESO | ES22: 22324888 | ET22: 142ea5f0-fe95-45c7-b4b6-897f9ccd4532 | EU22: 46211.152 | EX22: submitted_via_web | EY22: encuestador_adepro | EZ22: vzzpoqrQEmZ8kFXEawwS6F | FB22: uuid:142ea5f0-fe95-45c7-b4b6-897f9ccd4532 | FC22: 17
A23: ="V"&B23&"-R"&FC23 -> V2-R18 | B23: 2 | C23: 46202.547 | D23: 46202.57 | E23: 46202 | G23: Iván | H23: Milagro | I23: 46202 | K23: DUGLAS TURCIO ESCOBAR | L23: 62 | M23: Hombre | O23: Usulután | P23: Usulután Oeste | Q23: San Francisco Javier | R23: JOBALHORNOS | V23: DOUGLAS TURCIOS | W23: Sí | Y23: Productor | AB23: Sí | AF23: Sí | AG23: 1 | AH23: 2 | AI23: 1 | AJ23: 150 | AK23: 100 | AL23: 42 | AM23: 50 | AV23: Sí | AW23: 2023 | AX23: No | AY23: No | BA23: No | BO23: Ningún activo | BP23: 0 | BQ23: 0 | BR23: 0 | BS23: 0 | BT23: 0 | BU23: 0 | BV23: 0 | BW23: 0 | BX23: 0 | BY23: 0 | BZ23: 0 | CA23: 0 | CB23: 1 | CC23: Plagas o enfermedades Sequías Lluvia o inundaciones | CD23: 1 | CE23: 1 | CF23: 1 | CG23: 0 | CH23: 0 | CI23: 0 | CJ23: 0 | CK23: 0 | CL23: 0 | CM23: 4 | CO23: Oficios varios (artesanías, carpintería, albañilería, etc.) | CP23: No | CQ23: No | CR23: No | CS23: Sí | CT23: No | CU23: No | CV23: No | CW23: No | CX23: Sí | CY23: Sí | CZ23: Sí | DA23: No | DB23: No | DC23: No | DD23: No | DE23: No | DG23: 7 | DH23: 5 | DI23: 4 | DJ23: 5 | DK23: 0 | DL23: 7 | DM23: 7 | DN23: 7 | DO23: Sí | EH23: Sí | EI23: 13.3956902 -88.600342 0.0 0.0;13.3954745 -88.6005548 0.0 0.0;13.3953811 -88.6007926 0.0 0.0;13.3945143 -88.6007487 0.0 0.0;13.3944814 -88.600552 0.0 0.0;13.3945455 -88.6005437 0.0 0.0;13.3944554 -88.600416 0.0 0.0;13.394423 -88.6002722 0.0 0.0;13.3956902 -88.600342 0.0 0.0 | EK23: 61010116 | EL23: 71590170 | ES23: 22325160 | ET23: 866a0396-2c78-4616-ba19-d82f102f58c3 | EU23: 46211.167 | EX23: submitted_via_web | EY23: encuestador_adepro | EZ23: vzzpoqrQEmZ8kFXEawwS6F | FB23: uuid:866a0396-2c78-4616-ba19-d82f102f58c3 | FC23: 18
A24: ="V"&B24&"-R"&FC24 -> V3-R3 | B24: 3 | C24: 46202.496 | D24: 46202.557 | E24: 46201 | G24: Javier | H24: Milagro | I24: 46202 | K24: OLIVAR BATRES JOVITO NELSON | L24: 50 | M24: Hombre | O24: Usulután | P24: Usulután Oeste | Q24: Jiquilisco | R24: NUEVO TABLON | V24: OLIVER BATRES JOVITO NELSON | W24: Sí | Y24: Productor | AB24: Sí | AD24: Sí | AF24: Sí | AG24: 1 | AH24: 2 | AI24: 1 | AJ24: 100 | AK24: 180 | AL24: 50 | AM24: 70 | AN24: 1000 | AO24: Bovinos (vacas, terneros, novillos, bueyes, toros) | AP24: 1 | AQ24: 0 | AR24: 0 | AS24: 0 | AT24: 0 | AV24: Sí | AW24: 2025 | AX24: Sí | AY24: No | AZ24: JENNIFER AREVALO | BA24: Sí | BB24: Regeneración artificial (plantación de árboles) | BC24: No | BD24: No | BL24: Aumentó algo | BM24: Falta de mantenimiento | BO24: Ningún activo | BP24: 0 | BQ24: 0 | BR24: 0 | BS24: 0 | BT24: 0 | BU24: 0 | BV24: 0 | BW24: 0 | BX24: 0 | BY24: 0 | BZ24: 0 | CA24: 0 | CB24: 1 | CC24: No sufrió pérdidas de cosecha o animales | CD24: 0 | CE24: 0 | CF24: 0 | CG24: 0 | CH24: 0 | CI24: 0 | CJ24: 0 | CK24: 0 | CL24: 1 | CM24: 2 | CO24: Oficios varios (artesanías, carpintería, albañilería, etc.) | CP24: Sí | CQ24: Sí | CR24: Sí | CS24: Sí | CT24: No | CU24: No | CV24: Sí | CW24: No | CX24: No | DG24: 7 | DH24: 6 | DI24: 2 | DJ24: 1 | DK24: 7 | DL24: 7 | DM24: 7 | DN24: 3 | DO24: Sí | DP24: Agua entubada | DR24: Sí | DS24: Sí | DT24: May | DU24: 0 | DV24: 0 | DW24: 0 | DX24: 0 | DY24: 1 | DZ24: 0 | EA24: 0 | EB24: 0 | EC24: 0 | ED24: 0 | EE24: 0 | EF24: 0 | EH24: No | EJ24: Lejanía, dentro del distritio | EK24: 60100928 | EN24: EL GANADO ERA DEL VECINO COMO TAL | ES24: 22207036 | ET24: fb77112e-6433-483e-a69a-9b6dbd6b1ff2 | EU24: 46202.807 | EX24: submitted_via_web | EZ24: vmzueHpYT9juc6BY6BECkZ | FB24: uuid:fb77112e-6433-483e-a69a-9b6dbd6b1ff2 | FC24: 3
A25: ="V"&B25&"-R"&FC25 -> V3-R4 | B25: 3 | C25: 46202.619 | D25: 46202.638 | E25: 46201 | G25: Zaira | H25: Milagro | I25: 46202 | K25: MANUEL DE JESUS URQUILLA HENRIQUE | L25: 39 | M25: Hombre | O25: Usulután | P25: Usulután Oeste | Q25: San Francisco Javier | R25: BARRIO EL CALVARIO | S25: SAN FRANCISCO JAVIER | V25: REYNA ISABEL HERNANDEZ | W25: Sí | Y25: Familiar del productor | AB25: Sí | AD25: No | AF25: Sí | AG25: 1 | AH25: 2 | AI25: 1 | AJ25: 150 | AK25: 0 | AL25: 40 | AM25: 0 | AN25: 0 | AV25: Sí | AW25: 2020 | AX25: Sí | AY25: No | AZ25: NO SE ACUERDA | BA25: No | BO25: Ningún activo | BP25: 0 | BQ25: 0 | BR25: 0 | BS25: 0 | BT25: 0 | BU25: 0 | BV25: 0 | BW25: 0 | BX25: 0 | BY25: 0 | BZ25: 0 | CA25: 0 | CB25: 1 | CC25: No sufrió pérdidas de cosecha o animales | CD25: 0 | CE25: 0 | CF25: 0 | CG25: 0 | CH25: 0 | CI25: 0 | CJ25: 0 | CK25: 0 | CL25: 1 | CM25: 4 | CO25: Producción agropecuaria | CP25: Sí | CQ25: Sí | CR25: Sí | CS25: No | CT25: No | CU25: No | CV25: No | CW25: No | CX25: Sí | CY25: No | CZ25: No | DA25: No | DB25: No | DC25: No | DD25: No | DE25: No | DG25: 7 | DH25: 2 | DI25: 3 | DJ25: 5 | DK25: 3 | DL25: 7 | DM25: 7 | DN25: 3 | DO25: No | EH25: No | EJ25: Lejanía, dentro del distritio | EK25: 61974206 | EN25: LA PARCELA ESTA LEJOS | ES25: 22207591 | ET25: 7f2ef08c-9fe8-45ad-b693-114c17f3ec14 | EU25: 46202.888 | EX25: submitted_via_web | EZ25: vmzueHpYT9juc6BY6BECkZ | FB25: uuid:7f2ef08c-9fe8-45ad-b693-114c17f3ec14 | FC25: 4
A26: ="V"&B26&"-R"&FC26 -> V3-R5 | B26: 3 | C26: 46202.762 | D26: 46202.779 | E26: 46201 | G26: Milagro | H26: Milagro | I26: 46202 | K26: NUMAS MENA | L26: 51 | M26: Hombre | O26: Usulután | P26: Usulután Oeste | Q26: Jiquilisco | R26: CABOS NEGROS | S26: MARANON | V26: NUMAS | W26: Sí | Y26: Productor | AB26: Sí | AD26: No | AF26: Sí | AG26: 3 | AH26: 3 | AI26: 2 | AJ26: 1400 | AK26: 9999 | AL26: 9999 | AM26: 200 | AN26: 9999 | AV26: Sí | AW26: 2024 | AX26: No | AY26: No | AZ26: NO SABE | BA26: No | BO26: Rastra Equipo de fumigación | BP26: 0 | BQ26: 1 | BR26: 0 | BS26: 0 | BT26: 0 | BU26: 1 | BV26: 0 | BW26: 0 | BX26: 0 | BY26: 0 | BZ26: 0 | CA26: 0 | CB26: 0 | CC26: No sufrió pérdidas de cosecha o animales | CD26: 0 | CE26: 0 | CF26: 0 | CG26: 0 | CH26: 0 | CI26: 0 | CJ26: 0 | CK26: 0 | CL26: 1 | CM26: 3 | CO26: Producción agropecuaria | CP26: No | CQ26: No | CR26: No | CS26: No | CT26: No | CU26: No | CV26: No | CW26: No | CX26: No | DG26: 7 | DH26: 7 | DI26: 0 | DJ26: 2 | DK26: 2 | DL26: 2 | DM26: 7 | DN26: 7 | DO26: Sí | DP26: Agua entubada | DR26: Sí | DS26: Sí | DT26: Ene Feb Mar Abr May Jun Jul Ago Sep Oct Nov Dic | DU26: 1 | DV26: 1 | DW26: 1 | DX26: 1 | DY26: 1 | DZ26: 1 | EA26: 1 | EB26: 1 | EC26: 1 | ED26: 1 | EE26: 1 | EF26: 1 | EH26: No | EJ26: Otra | EK26: 76533675 | EN26: NO VIVE EN LA ZONA CABOS | ES26: 22208921 | ET26: 707cc38e-80e9-48ee-bfc3-e898e8180638 | EU26: 46203.029 | EX26: submitted_via_web | EZ26: vmzueHpYT9juc6BY6BECkZ | FB26: uuid:707cc38e-80e9-48ee-bfc3-e898e8180638 | FC26: 5
A27: ="V"&B27&"-R"&FC27 -> V3-R6 | B27: 3 | C27: 46202.638 | D27: 46203.33 | E27: 46201 | G27: Zaira | H27: Milagro | I27: 46202 | K27: MAGDALENA LISBETH AYALA GOMEZ | L27: 32 | M27: Mujer | O27: Usulután | P27: Usulután Oeste | Q27: San Francisco Javier | R27: BARRIO EL CALVARIO | S27: VISTA AL MAR | V27: MAGDALENA | W27: Sí | Y27: Productor | AB27: Sí | AD27: No | AF27: Sí | AG27: 1 | AH27: 1 | AI27: 1 | AJ27: 0 | AK27: 0 | AL27: 0 | AM27: 0 | AN27: 0 | AV27: Sí | AW27: 2021 | AX27: No | AY27: No | AZ27: NO SE ACUERDA | BA27: No | BO27: Tanque para almacenamiento de agua Bomba de agua | BP27: 0 | BQ27: 0 | BR27: 0 | BS27: 0 | BT27: 0 | BU27: 0 | BV27: 1 | BW27: 1 | BX27: 0 | BY27: 0 | BZ27: 0 | CA27: 0 | CB27: 0 | CC27: Lluvia o inundaciones | CD27: 0 | CE27: 0 | CF27: 1 | CG27: 0 | CH27: 0 | CI27: 0 | CJ27: 0 | CK27: 0 | CL27: 0 | CM27: 3 | CO27: Producción agropecuaria | CP27: Sí | CQ27: Sí | CR27: Sí | CS27: No | CT27: No | CU27: No | CV27: No | CW27: No | CX27: Sí | CY27: No | CZ27: No | DA27: No | DB27: No | DC27: No | DD27: No | DE27: No | DG27: 3 | DH27: 1 | DI27: 0 | DJ27: 4 | DK27: 7 | DL27: 7 | DM27: 7 | DN27: 3 | DO27: Sí | DP27: Agua entubada | DR27: Sí | DS27: Sí | DT27: Ene Feb Mar Abr May Jun Jul Ago Sep Oct Nov Dic | DU27: 1 | DV27: 1 | DW27: 1 | DX27: 1 | DY27: 1 | DZ27: 1 | EA27: 1 | EB27: 1 | EC27: 1 | ED27: 1 | EE27: 1 | EF27: 1 | EH27: No | EJ27: Lejanía, dentro del distritio | EK27: 61689446 | ES27: 22217314 | ET27: aee77320-39e5-4b9b-8a2d-4be8ceb4db83 | EU27: 46203.58 | EX27: submitted_via_web | EZ27: vmzueHpYT9juc6BY6BECkZ | FB27: uuid:aee77320-39e5-4b9b-8a2d-4be8ceb4db83 | FC27: 6
A28: ="V"&B28&"-R"&FC28 -> V3-R7 | B28: 3 | C28: 46203.398 | D28: 46203.441 | E28: 46202 | G28: Juan | H28: Rigoberto | I28: 46203 | K28: JAVIER ALVAREZ BONILLA | L28: 52 | M28: Hombre | O28: La Unión | P28: La Unión Norte | Q28: Concepción de Oriente | R28: HUERIPE | S28: EL NANCE | V28: JAVIER ALVAREZ | W28: Sí | Y28: Productor | AB28: Sí | AD28: No | AF28: Sí | AG28: 1 | AH28: 1 | AI28: 1 | AJ28: 110 | AK28: 400 | AL28: 100 | AM28: 500 | AN28: 0 | AV28: Sí | AW28: 2025 | AX28: No | AY28: No | AZ28: NO DIO NOMBRE | BA28: No | BO28: Equipo de fumigación Camioneta o camión | BP28: 0 | BQ28: 0 | BR28: 0 | BS28: 0 | BT28: 0 | BU28: 1 | BV28: 0 | BW28: 0 | BX28: 0 | BY28: 0 | BZ28: 1 | CA28: 0 | CB28: 0 | CC28: Lluvia o inundaciones | CD28: 0 | CE28: 0 | CF28: 1 | CG28: 0 | CH28: 0 | CI28: 0 | CJ28: 0 | CK28: 0 | CL28: 0 | CM28: 4 | CO28: Jornalero agropecuario | CP28: Sí | CQ28: Sí | CR28: Sí | CS28: Sí | CT28: No | CU28: No | CV28: No | CW28: No | CX28: Sí | CY28: No | CZ28: No | DA28: No | DB28: No | DC28: No | DD28: No | DE28: No | DG28: 7 | DH28: 7 | DI28: 7 | DJ28: 0 | DK28: 0 | DL28: 2 | DM28: 7 | DN28: 7 | DO28: Sí | DP28: Pozo | DR28: Sí | DS28: Sí | DT28: Ene Feb Mar Abr May Jun Jul Ago Sep Oct Nov Dic | DU28: 1 | DV28: 1 | DW28: 1 | DX28: 1 | DY28: 1 | DZ28: 1 | EA28: 1 | EB28: 1 | EC28: 1 | ED28: 1 | EE28: 1 | EF28: 1 | EH28: No | EJ28: Otra | EK28: 75185431 | EN28: NO SE REALIZO LA MEDICION PORQUE LOS DUENOS DEL TERRENO NO AUTORIZARON LA MEDICION | ES28: 22220024 | ET28: 2b6a8abe-6438-43fe-8b62-e98d396db932 | EU28: 46203.691 | EX28: submitted_via_web | EZ28: vmzueHpYT9juc6BY6BECkZ | FB28: uuid:2b6a8abe-6438-43fe-8b62-e98d396db932 | FC28: 7
A29: ="V"&B29&"-R"&FC29 -> V3-R8 | B29: 3 | C29: 46203.33 | D29: 46203.455 | E29: 46202 | G29: Zaira | H29: Milagro | I29: 46203 | K29: ROSELIA SALAZAR HERNANDEZ | L29: 48 | M29: Mujer | O29: La Unión | P29: La Unión Norte | Q29: Bolivar | R29: EL TRANSITO | S29: LOS AMAYA | V29: ROSELIA | W29: Sí | Y29: Productor | AB29: Sí | AD29: No | AF29: Sí | AG29: 1 | AH29: 2 | AI29: 1 | AJ29: 0 | AK29: 0 | AL29: 0 | AM29: 300 | AN29: 0 | AV29: Sí | AW29: 2022 | AX29: Sí | AY29: Sí | AZ29: NO SE ACUERDA | BA29: Sí | BB29: Regeneración artificial (plantación de árboles) | BC29: No | BD29: No | BL29: Sin cambió | BM29: Sequías extremas | BO29: Bomba de agua | BP29: 0 | BQ29: 0 | BR29: 0 | BS29: 0 | BT29: 0 | BU29: 0 | BV29: 0 | BW29: 1 | BX29: 0 | BY29: 0 | BZ29: 0 | CA29: 0 | CB29: 0 | CC29: Lluvia o inundaciones | CD29: 0 | CE29: 0 | CF29: 1 | CG29: 0 | CH29: 0 | CI29: 0 | CJ29: 0 | CK29: 0 | CL29: 0 | CM29: 4 | CO29: Producción agropecuaria | CP29: Sí | CQ29: Sí | CR29: Sí | CS29: Sí | CT29: Sí | CU29: Sí | CV29: Sí | CW29: Sí | CX29: Sí | CY29: Sí | CZ29: Sí | DA29: Sí | DB29: Sí | DC29: Sí | DD29: Sí | DE29: Sí | DG29: 7 | DH29: 7 | DI29: 1 | DJ29: 1 | DK29: 7 | DL29: 7 | DM29: 7 | DN29: 7 | DO29: No | EH29: No | EJ29: Otra | EK29: 74324865 | EN29: NO SE PUDO MEDIR ERA ALQUILADA | ES29: 22220467 | ET29: bacb573c-c4a7-41ad-8f2d-09bab7f29ffd | EU29: 46203.705 | EX29: submitted_via_web | EZ29: vmzueHpYT9juc6BY6BECkZ | FB29: uuid:bacb573c-c4a7-41ad-8f2d-09bab7f29ffd | FC29: 8
A30: ="V"&B30&"-R"&FC30 -> V3-R9 | B30: 3 | C30: 46203.466 | D30: 46203.466 | E30: 46202 | ES30: 22220746 | ET30: 2bc835ee-ab70-428c-b585-55e9410f7ef6 | EU30: 46203.716 | EX30: submitted_via_web | EZ30: vmzueHpYT9juc6BY6BECkZ | FB30: uuid:2bc835ee-ab70-428c-b585-55e9410f7ef6 | FC30: 9
A31: ="V"&B31&"-R"&FC31 -> V3-R10 | B31: 3 | C31: 46203.402 | D31: 46203.466 | E31: 46202 | G31: Iván | H31: Milagro | I31: 46203 | K31: JOSE NELSON SARAVIA | L31: 60 | M31: Hombre | O31: La Unión | P31: La Unión Norte | Q31: Bolivar | R31: LA RINCONADA | S31: LOS CRUZES | V31: JOSE NELSON | W31: Sí | Y31: Productor | AB31: Sí | AD31: No | AF31: Sí | AG31: 1 | AH31: 1 | AI31: 1 | AJ31: 5 | AK31: 50 | AL31: 15 | AM31: 300 | AN31: 0 | AO31: Aves (gallinas, pollos, gallos) | AP31: 0 | AQ31: 0 | AR31: 1 | AS31: 0 | AT31: 0 | AV31: Sí | AW31: 2023 | AX31: No | AY31: No | AZ31: NO SE ACUERDA | BA31: No | BO31: Bomba de agua | BP31: 0 | BQ31: 0 | BR31: 0 | BS31: 0 | BT31: 0 | BU31: 0 | BV31: 0 | BW31: 1 | BX31: 0 | BY31: 0 | BZ31: 0 | CA31: 0 | CB31: 0 | CC31: Plagas o enfermedades Lluvia o inundaciones | CD31: 1 | CE31: 0 | CF31: 1 | CG31: 0 | CH31: 0 | CI31: 0 | CJ31: 0 | CK31: 0 | CL31: 0 | CM31: 2 | CO31: Servicios domésticos | CP31: Sí | CQ31: Sí | CR31: Sí | CS31: Sí | CT31: No | CU31: Sí | CV31: Sí | CW31: Sí | CX31: No | DG31: 7 | DH31: 7 | DI31: 7 | DJ31: 7 | DK31: 7 | DL31: 1 | DM31: 7 | DN31: 7 | DO31: No | EH31: No | EJ31: Productor se rehuso | EK31: 60254778 | EN31: NO SE REALIZO LA MEDICION POR LA CONDICION DEL PRODUCTOR | ES31: 22220750 | ET31: 77385b8d-5e61-4aab-84f0-f5af8dd301cf | EU31: 46203.716 | EX31: submitted_via_web | EZ31: vmzueHpYT9juc6BY6BECkZ | FB31: uuid:77385b8d-5e61-4aab-84f0-f5af8dd301cf | FC31: 10
A32: ="V"&B32&"-R"&FC32 -> V3-R11 | B32: 3 | C32: 46202.741 | D32: 46203.469 | E32: 46201 | G32: Nancy | H32: Milagro | I32: 46203 | K32: FABIO MOLINA AMAYA | L32: 75 | M32: Hombre | O32: La Unión | P32: La Unión Norte | Q32: Bolivar | R32: EL TRANSITO | S32: LOS AMAYA | V32: FABIO MOLINA AMAYA | W32: Sí | Y32: Productor | AB32: Sí | AD32: No | AF32: Sí | AG32: 1 | AH32: 2 | AI32: 1 | AJ32: 15 | AK32: 45 | AL32: 25 | AM32: 40 | AN32: 0 | AV32: Sí | AW32: 2023 | AX32: No | AY32: No | AZ32: NO SABE | BA32: No | BO32: Tanque para almacenamiento de agua | BP32: 0 | BQ32: 0 | BR32: 0 | BS32: 0 | BT32: 0 | BU32: 0 | BV32: 1 | BW32: 0 | BX32: 0 | BY32: 0 | BZ32: 0 | CA32: 0 | CB32: 0 | CC32: Plagas o enfermedades Sequías | CD32: 1 | CE32: 1 | CF32: 0 | CG32: 0 | CH32: 0 | CI32: 0 | CJ32: 0 | CK32: 0 | CL32: 0 | CM32: 4 | CO32: Trabajo asalariado/permanente (sueldo regular) | CP32: Sí | CQ32: Sí | CR32: Sí | CS32: Sí | CT32: Sí | CU32: Sí | CV32: Sí | CW32: Sí | CX32: No | DG32: 1 | DH32: 1 | DI32: 0 | DJ32: 0 | DK32: 5 | DL32: 1 | DM32: 7 | DN32: 0 | DO32: Sí | DP32: Nacimiento de agua | DR32: Sí | DS32: Sí | DT32: Jun Jul Ago Sep | DU32: 0 | DV32: 0 | DW32: 0 | DX32: 0 | DY32: 0 | DZ32: 1 | EA32: 1 | EB32: 1 | EC32: 1 | ED32: 0 | EE32: 0 | EF32: 0 | EH32: Sí | EI32: 13.535933 -87.97096 248.20001220703125 5.48199987411499;13.535916 -87.970949 248.20001220703125 4.724999904632568;13.535916 -87.970949 248.20001220703125 4.724999904632568;13.535916 -87.970949 248.20001220703125 4.724999904632568;13.535916 -87.970949 248.20001220703125 4.724999904632568;13.536364 -87.970806 248.20001220703125 5.98199987411499;13.536364 -87.970806 248.20001220703125 5.98199987411499;13.536364 -87.970806 248.20001220703125 5.98199987411499;13.536364 -87.970806 248.20001220703125 5.98199987411499;13.536345 -87.970997 248.20001220703125 7.943999767303467;13.536345 -87.970997 248.20001220703125 7.943999767303467;13.536345 -87.970997 248.20001220703125 7.943999767303467;13.536345 -87.970997 248.20001220703125 7.943999767303467;13.535933 -87.97096 248.20001220703125 5.48199987411499 | EK32: 73701648 | EN32: NINGUNA | ES32: 22220820 | ET32: 7a282532-3970-4fa5-8ccc-8ef090b05443 | EU32: 46203.719 | EX32: submitted_via_web | EZ32: vmzueHpYT9juc6BY6BECkZ | FB32: uuid:7a282532-3970-4fa5-8ccc-8ef090b05443 | FC32: 11
A33: ="V"&B33&"-R"&FC33 -> V3-R12 | B33: 3 | C33: 46203.455 | D33: 46203.497 | E33: 46202 | G33: Zaira | H33: Milagro | I33: 46203 | K33: MARTHA LIDIA SORTO | L33: 38 | M33: Mujer | O33: La Unión | P33: La Unión Norte | Q33: Bolivar | R33: EL TRANSITO | S33: ASIENIGA | V33: MARTHA | W33: Sí | Y33: Productor | AB33: Sí | AD33: No | AF33: Sí | AG33: 1 | AH33: 1 | AI33: 1 | AJ33: 0 | AK33: 0 | AL33: 0 | AM33: 0 | AN33: 0 | AV33: Sí | AW33: 2024 | AX33: No | AY33: No | AZ33: ERNESTO CONTRERAS | BA33: Sí | BB33: Regeneración artificial (plantación de árboles) | BC33: No | BD33: Sí | BE33: RECLIMA | BF33: 0 | BG33: 1 | BH33: 0 | BI33: 0 | BJ33: 0 | BK33: 0 | BL33: Aumentó algo | BM33: Sequías extremas | CC33: No sufrió pérdidas de cosecha o animales | CD33: 0 | CE33: 0 | CF33: 0 | CG33: 0 | CH33: 0 | CI33: 0 | CJ33: 0 | CK33: 0 | CL33: 1 | CM33: 4 | CO33: Producción agropecuaria | CP33: Sí | CQ33: Sí | CR33: Sí | CS33: Sí | CT33: No | CU33: No | CV33: No | CW33: No | CX33: Sí | CY33: No | CZ33: Sí | DA33: No | DB33: No | DC33: Sí | DD33: No | DE33: No | DG33: 2 | DH33: 7 | DI33: 0 | DJ33: 1 | DK33: 0 | DL33: 0 | DM33: 2 | DN33: 1 | DO33: Sí | DP33: Nacimiento de agua | DR33: Sí | DS33: Sí | DT33: Ene Feb Mar Abr May Jun Jul Ago Sep Oct Nov Dic | DU33: 1 | DV33: 1 | DW33: 1 | DX33: 1 | DY33: 1 | DZ33: 1 | EA33: 1 | EB33: 1 | EC33: 1 | ED33: 1 | EE33: 1 | EF33: 1 | EH33: No | EJ33: Otra | EK33: 78909175 | EN33: LA PARCELA NO ES PROPIA | ES33: 22221813 | ET33: 231e1282-f423-4c8e-ad5b-8be9f5da6709 | EU33: 46203.749 | EX33: submitted_via_web | EZ33: vmzueHpYT9juc6BY6BECkZ | FB33: uuid:231e1282-f423-4c8e-ad5b-8be9f5da6709 | FC33: 12
A34: ="V"&B34&"-R"&FC34 -> V3-R13 | B34: 3 | C34: 46203.497 | D34: 46203.551 | E34: 46202 | G34: Zaira | H34: Milagro | I34: 46203 | K34: ENRIQUE ANTONIO GUEVARA | L34: 35 | M34: Hombre | O34: La Unión | P34: La Unión Norte | Q34: Bolivar | R34: CANTON SANTA LUCIA | S34: EL LIMON | V34: ENRIQUE | W34: Sí | Y34: Productor | AB34: Sí | AD34: No | AF34: Sí | AG34: 1 | AH34: 2 | AI34: 1 | AJ34: 0 | AK34: 0 | AL34: 0 | AM34: 0 | AN34: 0 | AV34: Sí | AW34: 2024 | AX34: No | AY34: No | AZ34: JOSE MARCELINO | BA34: No | CC34: No sufrió pérdidas de cosecha o animales | CD34: 0 | CE34: 0 | CF34: 0 | CG34: 0 | CH34: 0 | CI34: 0 | CJ34: 0 | CK34: 0 | CL34: 1 | CM34: 4 | CO34: Producción agropecuaria | CP34: Sí | CQ34: Sí | CR34: Sí | CS34: Sí | CT34: Sí | CU34: Sí | CV34: Sí | CW34: Sí | CX34: Sí | CY34: Sí | CZ34: Sí | DA34: Sí | DB34: Sí | DC34: Sí | DD34: Sí | DE34: Sí | DG34: 1 | DH34: 7 | DI34: 2 | DJ34: 3 | DK34: 1 | DL34: 1 | DM34: 0 | DN34: 1 | DO34: No | EH34: Sí | EI34: 13.516534 -87.9441 152.40000915527344 50.37699890136719;13.516603 -87.944106 152.40000915527344 10.744000434875488;13.516598 -87.944154 152.40000915527344 12.92199993133545;13.516575 -87.944224 152.40000915527344 22.325000762939453;13.516534 -87.9441 152.40000915527344 50.37699890136719 | EK34: 73009632 | EN34: TERRENO DENTRO DE LA CASA | ES34: 22223847 | ET34: 3246a932-b6f5-432b-b992-5f4c6b36a69e | EU34: 46203.857 | EX34: submitted_via_web | EZ34: vmzueHpYT9juc6BY6BECkZ | FB34: uuid:3246a932-b6f5-432b-b992-5f4c6b36a69e | FC34: 13
A35: ="V"&B35&"-R"&FC35 -> V3-R14 | B35: 3 | C35: 46203.557 | D35: 46203.612 | E35: 46202 | G35: Nancy | H35: Milagro | I35: 46203 | K35: FERMIN ALVAREZ MANCIA | L35: 82 | M35: Hombre | O35: La Unión | P35: La Unión Norte | Q35: Bolivar | R35: CANTON LA PAZ | S35: LA PAZ | T35: RCCUATROOCHONUEVEOCHO | V35: FERMIN ALVAREZ MANCIA | W35: Sí | Y35: Productor | AB35: Sí | AD35: No | AF35: Sí | AG35: 1 | AH35: 1 | AI35: 1 | AJ35: 60 | AK35: 0 | AL35: 0 | AM35: 0 | AN35: 0 | AV35: Sí | AW35: 2024 | AX35: Sí | AY35: No | AZ35: NO SABE | BA35: No | BO35: Ningún activo | BP35: 0 | BQ35: 0 | BR35: 0 | BS35: 0 | BT35: 0 | BU35: 0 | BV35: 0 | BW35: 0 | BX35: 0 | BY35: 0 | BZ35: 0 | CA35: 0 | CB35: 1 | CC35: Sequías | CD35: 0 | CE35: 1 | CF35: 0 | CG35: 0 | CH35: 0 | CI35: 0 | CJ35: 0 | CK35: 0 | CL35: 0 | CM35: 4 | CO35: Otra | CP35: Sí | CQ35: No | CR35: No | CS35: Sí | CT35: No | CU35: No | CV35: No | CW35: No | CX35: No | DG35: 7 | DH35: 7 | DI35: 3 | DJ35: 0 | DK35: 2 | DL35: 1 | DM35: 2 | DN35: 2 | DO35: Sí | DP35: Pozo | DR35: Sí | DS35: No | DT35: Ene Feb Mar Abr May Jun Jul Ago Sep Oct Nov Dic | DU35: 1 | DV35: 1 | DW35: 1 | DX35: 1 | DY35: 1 | DZ35: 1 | EA35: 1 | EB35: 1 | EC35: 1 | ED35: 1 | EE35: 1 | EF35: 1 | EH35: No | EJ35: Otra | EK35: 73075417 | EN35: LA PARCELA NO ES DE EL Y TODAVIA NO LA HA ALQUILADO | ES35: 22223877 | ET35: cb747487-0e87-4943-96df-4d2d37bc9b9f | EU35: 46203.862 | EX35: submitted_via_web | EZ35: vmzueHpYT9juc6BY6BECkZ | FB35: uuid:cb747487-0e87-4943-96df-4d2d37bc9b9f | FC35: 14
A36: ="V"&B36&"-R"&FC36 -> V3-R15 | B36: 3 | C36: 46203.469 | D36: 46203.613 | E36: 46202 | G36: Nancy | H36: Milagro | I36: 46203 | K36: HECTOR SAMUEL PEREIRA VILLATORO | L36: 24 | M36: Hombre | O36: La Unión | P36: La Unión Norte | Q36: Bolivar | R36: CANTON SANTA LUCIA | S36: LOS PEREIRA | T36: VJNUEVECINCOCEROSIETE | V36: HECTOR SAMUEL PEREIRA VILLATORO | W36: Sí | Y36: Productor | AB36: Sí | AD36: No | AF36: Sí | AG36: 1 | AH36: 1 | AI36: 1 | AJ36: 80 | AK36: 0 | AL36: 30 | AM36: 200 | AN36: 0 | AV36: Sí | AW36: 2024 | AX36: Sí | AY36: No | AZ36: JESSY JOAN FUENTES | BA36: Sí | BB36: Regeneración artificial (plantación de árboles) | BC36: No | BD36: No | BL36: Disminuyó algo | BM36: Sequías extremas | BO36: Ningún activo | BP36: 0 | BQ36: 0 | BR36: 0 | BS36: 0 | BT36: 0 | BU36: 0 | BV36: 0 | BW36: 0 | BX36: 0 | BY36: 0 | BZ36: 0 | CA36: 0 | CB36: 1 | CC36: Sequías | CD36: 0 | CE36: 1 | CF36: 0 | CG36: 0 | CH36: 0 | CI36: 0 | CJ36: 0 | CK36: 0 | CL36: 0 | CM36: 3 | CO36: Jornalero agropecuario | CP36: Sí | CQ36: Sí | CR36: No | CS36: No | CT36: Sí | CU36: Sí | CV36: Sí | CW36: No | CX36: Sí | CY36: No | CZ36: No | DA36: No | DB36: No | DC36: Sí | DD36: No | DE36: No | DG36: 3 | DH36: 2 | DI36: 1 | DJ36: 2 | DK36: 4 | DL36: 4 | DM36: 7 | DN36: 3 | DO36: Sí | DP36: Pozo | DR36: Sí | DS36: Sí | DT36: Ene Feb Mar Abr May Jun Jul Ago Sep Oct Nov Dic | DU36: 1 | DV36: 1 | DW36: 1 | DX36: 1 | DY36: 1 | DZ36: 1 | EA36: 1 | EB36: 1 | EC36: 1 | ED36: 1 | EE36: 1 | EF36: 1 | EH36: No | EJ36: Productor se rehuso | EK36: 79047232 | EN36: NO SE PUEDO IR A CONOCER LA PARCELA POR FALTA DE TIEMPO DEL PRODUCTOR | ES36: 22223883 | ET36: 84213a62-7ade-4d06-bfd8-9d69ccf84473 | EU36: 46203.863 | EX36: submitted_via_web | EZ36: vmzueHpYT9juc6BY6BECkZ | FB36: uuid:84213a62-7ade-4d06-bfd8-9d69ccf84473 | FC36: 15
A37: ="V"&B37&"-R"&FC37 -> V3-R16 | B37: 3 | C37: 46203.551 | D37: 46203.628 | E37: 46202 | G37: Zaira | H37: Milagro | I37: 46203 | K37: FELIX LOPEZ ALVAREZ | L37: 70 | M37: Hombre | O37: La Unión | P37: La Unión Norte | Q37: Bolivar | R37: CANTON LA PAZ | S37: LA PAZ | V37: FELIX | W37: Sí | Y37: Productor | AB37: Sí | AD37: No | AF37: Sí | AG37: 1 | AH37: 2 | AI37: 1 | AJ37: 0 | AK37: 100 | AL37: 100 | AM37: 0 | AN37: 400 | AV37: Sí | AW37: 2024 | AX37: Sí | AY37: No | AZ37: JOSE EBER | BA37: Sí | BB37: Regeneración artificial (plantación de árboles) | BC37: No | BD37: No | BL37: Aumentó algo | BM37: Sequías extremas | BO37: Tanque para almacenamiento de agua | BP37: 0 | BQ37: 0 | BR37: 0 | BS37: 0 | BT37: 0 | BU37: 0 | BV37: 1 | BW37: 0 | BX37: 0 | BY37: 0 | BZ37: 0 | CA37: 0 | CB37: 0 | CC37: Sequías | CD37: 0 | CE37: 1 | CF37: 0 | CG37: 0 | CH37: 0 | CI37: 0 | CJ37: 0 | CK37: 0 | CL37: 0 | CM37: 2 | CO37: Producción agropecuaria | CP37: No | CQ37: No | CR37: No | CS37: No | CT37: No | CU37: No | CV37: No | CW37: No | CX37: No | DG37: 5 | DH37: 1 | DI37: 7 | DJ37: 7 | DK37: 7 | DL37: 7 | DM37: 4 | DN37: 7 | DO37: Sí | DP37: Nacimiento de agua | DR37: Sí | DS37: Sí | DT37: Ene Feb Mar Abr May Jun Jul Ago Sep Oct Nov Dic | DU37: 1 | DV37: 1 | DW37: 1 | DX37: 1 | DY37: 1 | DZ37: 1 | EA37: 1 | EB37: 1 | EC37: 1 | ED37: 1 | EE37: 1 | EF37: 1 | EH37: No | EJ37: Otra | EK37: 79145228 | ES37: 22223993 | ET37: 00eedc57-25ba-46f8-8679-0ca094ef2b81 | EU37: 46203.878 | EX37: submitted_via_web | EZ37: vmzueHpYT9juc6BY6BECkZ | FB37: uuid:00eedc57-25ba-46f8-8679-0ca094ef2b81 | FC37: 16
A38: ="V"&B38&"-R"&FC38 -> V3-R17 | B38: 3 | C38: 46202.586 | D38: 46204.688 | E38: 46201 | G38: Nancy | H38: Milagro | I38: 46202 | K38: MARIA JOSEFA FLORES DE MUNOS | L38: 57 | M38: Mujer | O38: Usulután | P38: Usulután Oeste | Q38: San Francisco Javier | R38: LA PENA | S38: LA PENA | V38: MARIA JOSEFA FLORES DE MUNOZ | W38: Sí | Y38: Productor | AB38: Sí | AD38: No | AF38: Sí | AG38: 1 | AH38: 2 | AI38: 1 | AJ38: 300 | AK38: 700 | AL38: 125 | AM38: 300 | AN38: 275 | AO38: Bovinos (vacas, terneros, novillos, bueyes, toros) | AP38: 1 | AQ38: 0 | AR38: 0 | AS38: 0 | AT38: 0 | AV38: Sí | AW38: 2025 | AX38: No | AY38: No | AZ38: JOSE OSCAR CARRANZA | BA38: No | BO38: Ningún activo | BP38: 0 | BQ38: 0 | BR38: 0 | BS38: 0 | BT38: 0 | BU38: 0 | BV38: 0 | BW38: 0 | BX38: 0 | BY38: 0 | BZ38: 0 | CA38: 0 | CB38: 1 | CC38: Sequías | CD38: 0 | CE38: 1 | CF38: 0 | CG38: 0 | CH38: 0 | CI38: 0 | CJ38: 0 | CK38: 0 | CL38: 0 | CM38: 1 | CO38: Producción agropecuaria | CP38: No | CQ38: No | CR38: No | CS38: No | CT38: No | CU38: No | CV38: No | CW38: No | CX38: No | DG38: 7 | DH38: 7 | DI38: 7 | DJ38: 0 | DK38: 7 | DL38: 7 | DM38: 7 | DN38: 0 | DO38: Sí | DP38: Agua entubada | DR38: Sí | DS38: Sí | DT38: Ene Feb Mar Abr May Jun Jul Ago Sep Oct Nov Dic | DU38: 1 | DV38: 1 | DW38: 1 | DX38: 1 | DY38: 1 | DZ38: 1 | EA38: 1 | EB38: 1 | EC38: 1 | ED38: 1 | EE38: 1 | EF38: 1 | EH38: Sí | EK38: 63144699 | EN38: NO SE PUDO MEDIR LA PARCELA PORQUE ESTA RETIRADA DE LA VIVIENDA Y ASUNTOS PERSONALES DE LA PRODUCTORA FALTA DE TIEMPO | ES38: 22241414 | ET38: c49d573c-86fb-4307-8532-f60ee2529475 | EU38: 46204.938 | EX38: submitted_via_web | EZ38: vBf6xt5iWdkTjghTeBLtbw | FB38: uuid:c49d573c-86fb-4307-8532-f60ee2529475 | FC38: 17
A39: ="V"&B39&"-R"&FC39 -> V3-R18 | B39: 3 | C39: 46204.652 | D39: 46204.822 | E39: 46203 | G39: Nancy | H39: Milagro | I39: 46204 | K39: FELIPE CARLOS BONILLA | L39: 61 | M39: Hombre | O39: Morazán | P39: Morazán Sur | Q39: El Divisadero | R39: BARRIO EL CENTRO | S39: LOMA LARGA ABAJO | T39: ERCUATROCUATROOCHOUNO | V39: ELIZABETH MIRANDA | W39: Sí | Y39: Familiar del productor | AB39: Sí | AD39: No | AF39: Sí | AG39: 1 | AH39: 2 | AI39: 1 | AJ39: 0 | AK39: 9999 | AL39: 9999 | AM39: 0 | AN39: 9999 | AV39: Sí | AW39: 2024 | AX39: Sí | AY39: No | AZ39: NO SABE | BA39: No | BO39: Ningún activo | BP39: 0 | BQ39: 0 | BR39: 0 | BS39: 0 | BT39: 0 | BU39: 0 | BV39: 0 | BW39: 0 | BX39: 0 | BY39: 0 | BZ39: 0 | CA39: 0 | CB39: 1 | CC39: Lluvia o inundaciones | CD39: 0 | CE39: 0 | CF39: 1 | CG39: 0 | CH39: 0 | CI39: 0 | CJ39: 0 | CK39: 0 | CL39: 0 | CM39: 3 | CO39: Oficios varios (artesanías, carpintería, albañilería, etc.) | CP39: Sí | CQ39: No | CR39: No | CS39: Sí | CT39: No | CU39: No | CV39: No | CW39: No | CX39: No | DG39: 7 | DH39: 7 | DI39: 6 | DJ39: 1 | DK39: 7 | DL39: 2 | DM39: 7 | DN39: 7 | DO39: Sí | DP39: Agua entubada | DR39: No | DS39: No | DT39: Ene Feb Mar Abr May Jun Jul Ago Sep Oct Nov Dic | DU39: 1 | DV39: 1 | DW39: 1 | DX39: 1 | DY39: 1 | DZ39: 1 | EA39: 1 | EB39: 1 | EC39: 1 | ED39: 1 | EE39: 1 | EF39: 1 | EH39: No | EJ39: Lejanía, dentro del distritio | EK39: 70311015 | EN39: PARCELA LEJOS DEL DISTRITO Y LA ESPOSA NO TIENE TIEMPO PORQUE DEBE TRABAJAR VENDIDO PUPUSAS | ES39: 22256251 | ET39: 93d3ce9f-5fed-4cb1-abae-cbd82ee7bab6 | EU39: 46205.764 | EX39: submitted_via_web | EZ39: vBf6xt5iWdkTjghTeBLtbw | FB39: uuid:93d3ce9f-5fed-4cb1-abae-cbd82ee7bab6 | FC39: 18
A40: ="V"&B40&"-R"&FC40 -> V3-R19 | B40: 3 | C40: 46204.887 | D40: 46205.518 | E40: 46203 | G40: Zaira | H40: Milagro | I40: 46205 | K40: BLANCA SONIA AMAYA | L40: 50 | M40: Mujer | O40: Morazán | P40: Morazán Sur | Q40: Gualococti | R40: SAN LUCAS | S40: LOS GRAMALES | V40: SONIA | W40: Sí | Y40: Productor | AB40: Sí | AD40: No | AF40: Sí | AG40: 1 | AH40: 2 | AI40: 1 | AJ40: 0 | AK40: 0 | AL40: 0 | AM40: 300 | AN40: 0 | AO40: Bovinos (vacas, terneros, novillos, bueyes, toros) | AP40: 1 | AQ40: 0 | AR40: 0 | AS40: 0 | AT40: 0 | AV40: Sí | AW40: 2024 | AX40: Sí | AY40: Sí | AZ40: FLOR | BA40: Sí | BB40: Regeneración artificial (plantación de árboles) | BC40: No | BD40: Sí | BE40: RECLIMA | BF40: 0 | BG40: 1 | BH40: 0 | BI40: 0 | BJ40: 0 | BK40: 0 | BL40: Sin cambió | BM40: Sequías extremas | BO40: Ningún activo | BP40: 0 | BQ40: 0 | BR40: 0 | BS40: 0 | BT40: 0 | BU40: 0 | BV40: 0 | BW40: 0 | BX40: 0 | BY40: 0 | BZ40: 0 | CA40: 0 | CB40: 1 | CC40: No sufrió pérdidas de cosecha o animales | CD40: 0 | CE40: 0 | CF40: 0 | CG40: 0 | CH40: 0 | CI40: 0 | CJ40: 0 | CK40: 0 | CL40: 1 | CM40: 5 | CO40: Comercio informal | CP40: Sí | CQ40: No | CR40: Sí | CS40: Sí | CT40: No | CU40: Sí | CV40: Sí | CW40: No | CX40: Sí | CY40: Sí | CZ40: Sí | DA40: No | DB40: Sí | DC40: Sí | DD40: Sí | DE40: No | DG40: 7 | DH40: 7 | DI40: 3 | DJ40: 3 | DK40: 4 | DL40: 7 | DM40: 7 | DN40: 0 | DO40: Sí | DP40: Agua entubada | DR40: Sí | DS40: Sí | DT40: Ene Feb Mar Abr May Jun Jul Ago Sep Oct Nov Dic | DU40: 1 | DV40: 1 | DW40: 1 | DX40: 1 | DY40: 1 | DZ40: 1 | EA40: 1 | EB40: 1 | EC40: 1 | ED40: 1 | EE40: 1 | EF40: 1 | EH40: No | EJ40: Lejanía, dentro del distritio | EK40: 72623119 | EN40: PARCELA ALQUILADA | ES40: 22256284 | ET40: fa87f83a-b79d-4820-96cd-a8383b0a1f9e | EU40: 46205.768 | EX40: submitted_via_web | EZ40: vBf6xt5iWdkTjghTeBLtbw | FB40: uuid:fa87f83a-b79d-4820-96cd-a8383b0a1f9e | FC40: 19
A41: ="V"&B41&"-R"&FC41 -> V3-R20 | B41: 3 | C41: 46205.519 | D41: 46205.645 | E41: 46204 | G41: Nancy | H41: Milagro | I41: 46205 | K41: MARIA ALICIA SAEN MARQUEZ | L41: 55 | M41: Mujer | O41: Morazán | P41: Morazán Sur | Q41: Gualococti | R41: SAN LUCAS | S41: LOS GRAMALES | T41: TMCINCOCUATROSIETEOCHO | V41: MARIA ALICIA SAEN MARQUEZ | W41: Sí | Y41: Productor | AB41: Sí | AD41: Sí | AF41: Sí | AG41: 1 | AH41: 2 | AI41: 1 | AJ41: 0 | AK41: 0 | AL41: 0 | AM41: 100 | AN41: 0 | AV41: Sí | AW41: 2024 | AX41: Sí | AY41: Sí | AZ41: NO SABE | BA41: Sí | BB41: Regeneración artificial (plantación de árboles) | BC41: No | BD41: Sí | BE41: RECLIMA | BF41: 0 | BG41: 1 | BH41: 0 | BI41: 0 | BJ41: 0 | BK41: 0 | BL41: Disminuyó mucho | BM41: Sequías extremas | BO41: Ningún activo | BP41: 0 | BQ41: 0 | BR41: 0 | BS41: 0 | BT41: 0 | BU41: 0 | BV41: 0 | BW41: 0 | BX41: 0 | BY41: 0 | BZ41: 0 | CA41: 0 | CB41: 1 | CC41: Sequías Vientos fuertes | CD41: 0 | CE41: 1 | CF41: 0 | CG41: 0 | CH41: 1 | CI41: 0 | CJ41: 0 | CK41: 0 | CL41: 0 | CM41: 2 | CO41: Servicios domésticos | CP41: Sí | CQ41: Sí | CR41: Sí | CS41: Sí | CT41: Sí | CU41: Sí | CV41: Sí | CW41: No | CX41: No | DG41: 3 | DH41: 3 | DI41: 3 | DJ41: 0 | DK41: 7 | DL41: 7 | DM41: 7 | DN41: 3 | DO41: Sí | DP41: Agua entubada | DR41: Sí | DS41: Sí | DT41: Ene Feb Mar Abr May Jun Jul Ago Sep Oct Nov Dic | DU41: 1 | DV41: 1 | DW41: 1 | DX41: 1 | DY41: 1 | DZ41: 1 | EA41: 1 | EB41: 1 | EC41: 1 | ED41: 1 | EE41: 1 | EF41: 1 | EH41: Sí | EK41: 77478312 | EN41: ESTE ANO SEMBRO MAIZ Y CHILIPUCAS EN SU PARCELA | ES41: 22257651 | ET41: e6c4cb69-52fb-475e-a5c6-399e837537d9 | EU41: 46205.895 | EX41: submitted_via_web | EZ41: vBf6xt5iWdkTjghTeBLtbw | FB41: uuid:e6c4cb69-52fb-475e-a5c6-399e837537d9 | FC41: 20
A42: ="V"&B42&"-R"&FC42 -> V3-R21 | B42: 3 | C42: 46205.727 | D42: 46205.747 | E42: 46204 | G42: Nancy | H42: Milagro | I42: 46205 | K42: MARIA EDITH ALVAREZ VIGIL | L42: 30 | M42: Hombre | O42: Morazán | P42: Morazán Sur | Q42: Chilanga | R42: PIEDRA PARADA | S42: LOS PEREZ | T42: TYCUATRONUEVESIETECINCO | V42: MARIA EDITH VIGIL ALVAREZ | W42: Sí | Y42: Productor | AB42: Sí | AD42: No sabe / no responde | AF42: Sí | AG42: 1 | AH42: 1 | AI42: 1 | AJ42: 0 | AK42: 9999 | AL42: 20 | AM42: 50 | AN42: 0 | AV42: Sí | AW42: 2023 | AX42: No | AY42: No | AZ42: WILLIAM CRUZ | BA42: Sí | BB42: Regeneración artificial (plantación de árboles) | BC42: No | BD42: No | BL42: Sin cambió | BM42: Sequías extremas | BO42: Ningún activo | BP42: 0 | BQ42: 0 | BR42: 0 | BS42: 0 | BT42: 0 | BU42: 0 | BV42: 0 | BW42: 0 | BX42: 0 | BY42: 0 | BZ42: 0 | CA42: 0 | CB42: 1 | CC42: Lluvia o inundaciones | CD42: 0 | CE42: 0 | CF42: 1 | CG42: 0 | CH42: 0 | CI42: 0 | CJ42: 0 | CK42: 0 | CL42: 0 | CM42: 6 | CO42: Producción agropecuaria | CP42: No | CQ42: No | CR42: No | CS42: No | CT42: No | CU42: No | CV42: No | CW42: No | CX42: Sí | CY42: No | CZ42: No | DA42: No | DB42: No | DC42: No | DD42: No | DE42: No | DG42: 7 | DH42: 7 | DI42: 2 | DJ42: 1 | DK42: 3 | DL42: 2 | DM42: 7 | DN42: 2 | DO42: Sí | DP42: Nacimiento de agua | DR42: Sí | DS42: Sí | DT42: May Jun Jul Ago | DU42: 0 | DV42: 0 | DW42: 0 | DX42: 0 | DY42: 1 | DZ42: 1 | EA42: 1 | EB42: 1 | EC42: 0 | ED42: 0 | EE42: 0 | EF42: 0 | EH42: Sí | EK42: 74015432 | EN42: NO SE PUDO CONOCER Y MEDIR LA PARCELA PORQUE ESTA LEJOS EN EL MISMO DISTRITO | ES42: 22257888 | ET42: a6693653-d8e8-4e04-a214-f6a0648b01c0 | EU42: 46205.997 | EX42: submitted_via_web | EZ42: vBf6xt5iWdkTjghTeBLtbw | FB42: uuid:a6693653-d8e8-4e04-a214-f6a0648b01c0 | FC42: 21
A43: ="V"&B43&"-R"&FC43 -> V3-R22 | B43: 3 | C43: 46203.441 | D43: 46205.865 | E43: 46202 | G43: Juan | H43: Rigoberto | I43: 46205 | K43: EULISES ANTONIO DIAZ CHICAS | L43: 27 | M43: Hombre | O43: Morazán | P43: Morazán Sur | Q43: Gualococti | R43: LA JOYA | S43: CHUPADERO | V43: EULISES DIAZ | W43: Sí | Y43: Productor | AB43: Sí | AD43: Sí | AF43: Sí | AG43: 1 | AH43: 2 | AI43: 1 | AJ43: 75 | AK43: 160 | AL43: 0 | AM43: 0 | AN43: 0 | AV43: Sí | AW43: 2025 | AX43: No | AY43: No | AZ43: NO SE RECUERDA | BA43: Sí | BB43: Regeneración natural asistida | BC43: No | BD43: Sí | BE43: RECLIMA | BF43: 0 | BG43: 1 | BH43: 0 | BI43: 0 | BJ43: 0 | BK43: 0 | BL43: Aumentó mucho | BM43: Falta de mantenimiento | BO43: Tanque para almacenamiento de agua | BP43: 0 | BQ43: 0 | BR43: 0 | BS43: 0 | BT43: 0 | BU43: 0 | BV43: 1 | BW43: 0 | BX43: 0 | BY43: 0 | BZ43: 0 | CA43: 0 | CB43: 0 | CC43: Sequías | CD43: 0 | CE43: 1 | CF43: 0 | CG43: 0 | CH43: 0 | CI43: 0 | CJ43: 0 | CK43: 0 | CL43: 0 | CM43: 4 | CO43: Jornalero agropecuario | CP43: Sí | CQ43: Sí | CR43: Sí | CS43: Sí | CT43: Sí | CU43: Sí | CV43: Sí | CW43: Sí | CX43: Sí | CY43: Sí | CZ43: Sí | DA43: Sí | DB43: Sí | DC43: Sí | DD43: Sí | DE43: Sí | DG43: 7 | DH43: 2 | DI43: 4 | DJ43: 3 | DK43: 5 | DL43: 5 | DM43: 7 | DN43: 7 | DO43: Sí | DP43: Agua entubada | DR43: Sí | DS43: Sí | DT43: Ene Feb Mar Abr May Jun Jul Ago Sep Oct Nov Dic | DU43: 1 | DV43: 1 | DW43: 1 | DX43: 1 | DY43: 1 | DZ43: 1 | EA43: 1 | EB43: 1 | EC43: 1 | ED43: 1 | EE43: 1 | EF43: 1 | EH43: No | EJ43: Otra | EK43: 70454439 | EN43: POR MOTIVOS DE TRABAJO Y DE LEJANIA DE LA PARCELA NO SE REALIZO LA MEDICION | ES43: 22258062 | ET43: 3e155801-a3b2-491f-948e-e6f0cde0a2ce | EU43: 46206.115 | EX43: submitted_via_web | EZ43: vBf6xt5iWdkTjghTeBLtbw | FB43: uuid:3e155801-a3b2-491f-948e-e6f0cde0a2ce | FC43: 22
A44: ="V"&B44&"-R"&FC44 -> V3-R23 | B44: 3 | C44: 46205.555 | D44: 46205.867 | E44: 46204 | G44: Juan | H44: Rigoberto | I44: 46205 | K44: CARLOS RAMON CHICAS ARANDA | L44: 38 | M44: Hombre | O44: Morazán | P44: Morazán Sur | Q44: Gualococti | R44: PENA BLANCA | S44: PENA BLANCA | V44: YESENIA BEATRIZ ARGUETA CHICAS | W44: Sí | Y44: Familiar del productor | AB44: Sí | AD44: Sí | AF44: Sí | AG44: 2 | AH44: 1 | AI44: 2 | AJ44: 70 | AK44: 25 | AL44: 25 | AM44: 120 | AN44: 0 | AV44: Sí | AW44: 2025 | AX44: Sí | AY44: Sí | AZ44: NO SABE | BA44: Sí | BB44: Regeneración artificial (plantación de árboles) | BC44: No | BD44: Sí | BE44: RECLIMA | BF44: 0 | BG44: 1 | BH44: 0 | BI44: 0 | BJ44: 0 | BK44: 0 | BL44: Disminuyó algo | BM44: Sequías extremas | BO44: Sembradora Podadora Equipo de fumigación | BP44: 0 | BQ44: 0 | BR44: 0 | BS44: 1 | BT44: 1 | BU44: 1 | BV44: 0 | BW44: 0 | BX44: 0 | BY44: 0 | BZ44: 0 | CA44: 0 | CB44: 0 | CC44: Sequías Lluvia o inundaciones | CD44: 0 | CE44: 1 | CF44: 1 | CG44: 0 | CH44: 0 | CI44: 0 | CJ44: 0 | CK44: 0 | CL44: 0 | CM44: 5 | CO44: Jornalero agropecuario | CP44: Sí | CQ44: No | CR44: Sí | CS44: Sí | CT44: No | CU44: Sí | CV44: Sí | CW44: Sí | CX44: Sí | CY44: Sí | CZ44: No | DA44: No | DB44: No | DC44: No | DD44: No | DE44: No | DG44: 7 | DH44: 7 | DI44: 3 | DJ44: 7 | DK44: 3 | DL44: 3 | DM44: 7 | DN44: 7 | DO44: Sí | DP44: Nacimiento de agua | DR44: Sí | DS44: Sí | DT44: Ene Feb Mar Abr May Jun Jul Ago Sep Oct Nov Dic | DU44: 1 | DV44: 1 | DW44: 1 | DX44: 1 | DY44: 1 | DZ44: 1 | EA44: 1 | EB44: 1 | EC44: 1 | ED44: 1 | EE44: 1 | EF44: 1 | EH44: No | EJ44: Productor se rehuso | EK44: 77513059 | EN44: EL PRODUCTOR SE REHUSO A REALIZAR LA MEDICION POR MOTIVOS FAMILIARES | ES44: 22258077 | ET44: 126318c2-8ca8-48e9-8e58-ea8c806513e4 | EU44: 46206.117 | EX44: submitted_via_web | EZ44: vBf6xt5iWdkTjghTeBLtbw | FB44: uuid:126318c2-8ca8-48e9-8e58-ea8c806513e4 | FC44: 23
A45: ="V"&B45&"-R"&FC45 -> V3-R24 | B45: 3 | C45: 46205.559 | D45: 46205.731 | E45: 46204 | G45: Zaira | H45: Milagro | I45: 46205 | K45: JOSE ELIJIO MARQUEZ MORAL | L45: 36 | M45: Hombre | O45: Morazán | P45: Morazán Sur | Q45: Chilanga | R45: PIEDRA PARADA | S45: LOS MORALES | V45: FELIPE MARQUEZ | W45: Sí | Y45: Familiar del productor | AB45: Sí | AD45: No | AF45: Sí | AG45: 1 | AH45: 3 | AI45: 1 | AJ45: 800 | AK45: 100 | AL45: 100 | AM45: 0 | AN45: 900 | AV45: Sí | AW45: 2024 | AX45: Sí | AY45: No | AZ45: TANIA | BA45: Sí | BB45: Regeneración artificial (plantación de árboles) | BC45: No | BD45: Sí | BE45: RECLIMA | BF45: 0 | BG45: 1 | BH45: 0 | BI45: 0 | BJ45: 0 | BK45: 0 | BL45: Disminuyó algo | BM45: Sequías extremas | BO45: Tanque para almacenamiento de agua Bomba de agua | BP45: 0 | BQ45: 0 | BR45: 0 | BS45: 0 | BT45: 0 | BU45: 0 | BV45: 1 | BW45: 1 | BX45: 0 | BY45: 0 | BZ45: 0 | CA45: 0 | CB45: 0 | CC45: No sufrió pérdidas de cosecha o animales | CD45: 0 | CE45: 0 | CF45: 0 | CG45: 0 | CH45: 0 | CI45: 0 | CJ45: 0 | CK45: 0 | CL45: 1 | CM45: 4 | CO45: Producción agropecuaria | CP45: Sí | CQ45: No | CR45: Sí | CS45: Sí | CT45: No | CU45: No | CV45: No | CW45: No | CX45: No | DG45: 7 | DH45: 6 | DI45: 3 | DJ45: 3 | DK45: 5 | DL45: 7 | DM45: 7 | DN45: 2 | DO45: Sí | DP45: Nacimiento de agua | DR45: Sí | DS45: Sí | DT45: Ene Feb Mar Abr May Jun Jul Ago Sep Oct Nov Dic | DU45: 1 | DV45: 1 | DW45: 1 | DX45: 1 | DY45: 1 | DZ45: 1 | EA45: 1 | EB45: 1 | EC45: 1 | ED45: 1 | EE45: 1 | EF45: 1 | EH45: No | EJ45: Lejanía, dentro del distritio | EK45: 0 | EN45: NO TIENE EL NUMERO | ES45: 22263518 | ET45: 203e8184-6314-4d7d-8a00-fb342473d7f7 | EU45: 46206.625 | EX45: submitted_via_web | EZ45: vBf6xt5iWdkTjghTeBLtbw | FB45: uuid:203e8184-6314-4d7d-8a00-fb342473d7f7 | FC45: 24
A46: ="V"&B46&"-R"&FC46 -> V3-R25 | B46: 3 | C46: 46206.441 | D46: 46206.566 | E46: 46205 | G46: Iván | H46: Milagro | I46: 46206 | K46: JOSE DE JESUS ORELLANA CHICAS | L46: 35 | M46: Hombre | O46: Morazán | P46: Morazán Norte | Q46: Perquín | R46: VOLCANCILLO | S46: VOLCANCILLO | V46: JOSE MARIO CHICAS | W46: Sí | Y46: Familiar del productor | AB46: Sí | AD46: No | AF46: Sí | AG46: 1 | AH46: 1 | AI46: 1 | AJ46: 0 | AK46: 0 | AL46: 0 | AM46: 50 | AN46: 0 | AV46: Sí | AW46: 2025 | AX46: Sí | AY46: No | AZ46: LUIS HERNANDEZ | BA46: Sí | BB46: Regeneración artificial (plantación de árboles) | BC46: No | BD46: Sí | BE46: RECLIMA | BF46: 0 | BG46: 1 | BH46: 0 | BI46: 0 | BJ46: 0 | BK46: 0 | BL46: Sin cambió | BM46: Sequías extremas | BO46: Ningún activo | BP46: 0 | BQ46: 0 | BR46: 0 | BS46: 0 | BT46: 0 | BU46: 0 | BV46: 0 | BW46: 0 | BX46: 0 | BY46: 0 | BZ46: 0 | CA46: 0 | CB46: 1 | CC46: Plagas o enfermedades Sequías | CD46: 1 | CE46: 1 | CF46: 0 | CG46: 0 | CH46: 0 | CI46: 0 | CJ46: 0 | CK46: 0 | CL46: 0 | CM46: 4 | CO46: Jornalero agropecuario | CP46: Sí | CQ46: No | CR46: Sí | CS46: Sí | CT46: No | CU46: Sí | CV46: Sí | CW46: No | CX46: No | DG46: 7 | DH46: 7 | DI46: 0 | DJ46: 7 | DK46: 6 | DL46: 4 | DM46: 4 | DN46: 2 | DO46: Sí | DP46: Agua entubada | DR46: Sí | DS46: Sí | DT46: Ene Feb Mar Abr May Jun Jul Ago Sep Oct Nov Dic | DU46: 1 | DV46: 1 | DW46: 1 | DX46: 1 | DY46: 1 | DZ46: 1 | EA46: 1 | EB46: 1 | EC46: 1 | ED46: 1 | EE46: 1 | EF46: 1 | EH46: No | EJ46: Otra | EK46: 74155485 | ES46: 22265706 | ET46: fbbdbcab-fac1-401a-8deb-9ba9f65456cb | EU46: 46206.816 | EX46: submitted_via_web | EZ46: vBf6xt5iWdkTjghTeBLtbw | FB46: uuid:fbbdbcab-fac1-401a-8deb-9ba9f65456cb | FC46: 25
A47: ="V"&B47&"-R"&FC47 -> V3-R26 | B47: 3 | C47: 46202.632 | D47: 46207.249 | E47: 46201 | G47: Nancy | H47: Milagro | I47: 46202 | K47: RICARDO ANTONIO JUAREZ | L47: 37 | M47: Hombre | O47: Usulután | P47: Usulután Oeste | Q47: Jiquilisco | R47: CABOS NEGROS | S47: EL MARANON | V47: EVELYN VANESSA URQUIA QUINTANILLA | W47: Sí | Y47: Familiar del productor | AB47: Sí | AD47: Sí | AF47: Sí | AG47: 1 | AH47: 2 | AI47: 1 | AJ47: 9999 | AK47: 300 | AL47: 9999 | AM47: 0 | AN47: 700 | AV47: Sí | AW47: 2024 | AX47: Sí | AY47: Sí | AZ47: NO SABE | BA47: Sí | BB47: Regeneración artificial (plantación de árboles) | BC47: No | BD47: Sí | BE47: RECLIMA | BF47: 0 | BG47: 1 | BH47: 0 | BI47: 0 | BJ47: 0 | BK47: 0 | BL47: Sin cambió | BM47: Sequías extremas | BO47: Equipo de fumigación | BP47: 0 | BQ47: 0 | BR47: 0 | BS47: 0 | BT47: 0 | BU47: 1 | BV47: 0 | BW47: 0 | BX47: 0 | BY47: 0 | BZ47: 0 | CA47: 0 | CB47: 0 | CC47: No sufrió pérdidas de cosecha o animales | CD47: 0 | CE47: 0 | CF47: 0 | CG47: 0 | CH47: 0 | CI47: 0 | CJ47: 0 | CK47: 0 | CL47: 1 | CM47: 4 | CO47: Producción agropecuaria | CP47: Sí | CQ47: No | CR47: Sí | CS47: No | CT47: No | CU47: No | CV47: No | CW47: No | CX47: Sí | CY47: No | CZ47: No | DA47: No | DB47: No | DC47: No | DD47: No | DE47: No | DG47: 7 | DH47: 7 | DI47: 3 | DJ47: 4 | DK47: 7 | DL47: 7 | DM47: 7 | DN47: 3 | DO47: Sí | DP47: Agua entubada | DR47: Sí | DS47: Sí | DT47: Ene Feb Mar Abr May Jun Jul Ago Sep Oct Nov Dic | DU47: 1 | DV47: 1 | DW47: 1 | DX47: 1 | DY47: 1 | DZ47: 1 | EA47: 1 | EB47: 1 | EC47: 1 | ED47: 1 | EE47: 1 | EF47: 1 | EH47: Sí | EI47: 13.308441 -88.569832 25.600000381469727 4.570000171661377;13.308097 -88.569165 25.600000381469727 6.757999897003174;13.308097 -88.569165 25.600000381469727 6.757999897003174;13.308097 -88.569164 25.600000381469727 74.38700103759766;13.307734 -88.569298 25.600000381469727 7.520999908447266;13.307734 -88.569298 25.600000381469727 7.520999908447266;13.307734 -88.569298 25.600000381469727 7.520999908447266;13.308441 -88.569832 25.600000381469727 4.570000171661377 | ES47: 22273895 | ET47: 9551ceb0-ff11-4efe-a903-0414bbccaf0c | EU47: 46207.499 | EX47: submitted_via_web | EZ47: vBf6xt5iWdkTjghTeBLtbw | FB47: uuid:9551ceb0-ff11-4efe-a903-0414bbccaf0c | FC47: 26
A48: ="V"&B48&"-R"&FC48 -> V3-R27 | B48: 3 | C48: 46206.579 | D48: 46207.251 | E48: 46205 | G48: Nancy | H48: Milagro | I48: 46206 | K48: ANA NOLASCO VIUDA DE AMAYA | L48: 52 | M48: Mujer | O48: Morazán | P48: Morazán Norte | Q48: Perquín | R48: CHANGUITON | S48: CASA BLANCA | T48: NCSEISOCHOCEROUNO | V48: NOE ANTONIO AMAYA NOLASCO | W48: Sí | Y48: Familiar del productor | AB48: Sí | AD48: No sabe / no responde | AF48: Sí | AG48: 1 | AH48: 2 | AI48: 1 | AJ48: 0 | AK48: 9999 | AL48: 9999 | AM48: 210 | AN48: 9999 | AV48: Sí | AW48: 2023 | AX48: No | AY48: No | AZ48: NO SABE | BA48: Sí | BB48: Regeneración artificial (plantación de árboles) | BC48: No | BD48: No | BL48: Aumentó algo | BM48: Sequías extremas | BO48: Ningún activo | BP48: 0 | BQ48: 0 | BR48: 0 | BS48: 0 | BT48: 0 | BU48: 0 | BV48: 0 | BW48: 0 | BX48: 0 | BY48: 0 | BZ48: 0 | CA48: 0 | CB48: 1 | CC48: Plagas o enfermedades Sequías | CD48: 1 | CE48: 1 | CF48: 0 | CG48: 0 | CH48: 0 | CI48: 0 | CJ48: 0 | CK48: 0 | CL48: 0 | CM48: 3 | CO48: Producción agropecuaria | CP48: Sí | CQ48: No | CR48: No | CS48: No | CT48: No | CU48: No | CV48: No | CW48: No | CX48: Sí | CY48: No | CZ48: No | DA48: No | DB48: No | DC48: No | DD48: No | DE48: No | DG48: 7 | DH48: 7 | DI48: 3 | DJ48: 0 | DK48: 7 | DL48: 7 | DM48: 7 | DN48: 7 | DO48: Sí | DP48: Nacimiento de agua | DR48: Sí | DS48: Sí | DT48: Ene Feb Mar Abr May Jun Jul Ago Sep Oct Nov Dic | DU48: 1 | DV48: 1 | DW48: 1 | DX48: 1 | DY48: 1 | DZ48: 1 | EA48: 1 | EB48: 1 | EC48: 1 | ED48: 1 | EE48: 1 | EF48: 1 | EH48: No | EJ48: Lejanía, fuera del distritio | EK48: 75503549 | EN48: NO SE PUEDE IR A CONOCER LA PARCELA PORQUE ESTA A DOS HORAS EN CARRO | ES48: 22273902 | ET48: cdab55c0-90ee-4ac1-98fe-4f83dc604146 | EU48: 46207.501 | EX48: submitted_via_web | EZ48: vBf6xt5iWdkTjghTeBLtbw | FB48: uuid:cdab55c0-90ee-4ac1-98fe-4f83dc604146 | FC48: 27
A49: ="V"&B49&"-R"&FC49 -> V3-R28 | B49: 3 | C49: 46206.597 | D49: 46207.252 | E49: 46205 | G49: Nancy | H49: Milagro | I49: 46206 | K49: CRUZ ROLANDO ARGUETA PEREZ | L49: 35 | M49: Hombre | O49: Morazán | P49: Morazán Norte | Q49: Perquín | R49: CASA BLANCA | S49: CHANGUITON | T49: AHUNOSIETENUEVETRES | V49: LUIS SANTOS FRANCISCO ARGUETA FERNANDEZ | W49: Sí | Y49: Familiar del productor | AB49: Sí | AD49: Sí | AF49: Sí | AG49: 1 | AH49: 2 | AI49: 1 | AJ49: 50 | AK49: 100 | AL49: 100 | AM49: 0 | AN49: 600 | AV49: Sí | AW49: 2024 | AX49: Sí | AY49: Sí | AZ49: DANIEL TORRES | BA49: Sí | BB49: Regeneración artificial (plantación de árboles) | BC49: No | BD49: No | BL49: Sin cambió | BM49: Sequías extremas | BO49: Ningún activo | BP49: 0 | BQ49: 0 | BR49: 0 | BS49: 0 | BT49: 0 | BU49: 0 | BV49: 0 | BW49: 0 | BX49: 0 | BY49: 0 | BZ49: 0 | CA49: 0 | CB49: 1 | CC49: No sufrió pérdidas de cosecha o animales | CD49: 0 | CE49: 0 | CF49: 0 | CG49: 0 | CH49: 0 | CI49: 0 | CJ49: 0 | CK49: 0 | CL49: 1 | CM49: 3 | CO49: Jornalero agropecuario | CP49: Sí | CQ49: Sí | CR49: No | CS49: No | CT49: No | CU49: No | CV49: No | CW49: No | CX49: No | DG49: 5 | DH49: 7 | DI49: 0 | DJ49: 0 | DK49: 7 | DL49: 7 | DM49: 7 | DN49: 7 | DO49: Sí | DP49: Nacimiento de agua | DR49: Sí | DS49: Sí | DT49: Ene Feb Mar Abr May Jun Jul Ago Sep Oct Nov Dic | DU49: 1 | DV49: 1 | DW49: 1 | DX49: 1 | DY49: 1 | DZ49: 1 | EA49: 1 | EB49: 1 | EC49: 1 | ED49: 1 | EE49: 1 | EF49: 1 | EH49: No | EJ49: Lejanía, dentro del distritio | EK49: 68496996 | EN49: NO SE PUDO CONOCER LA PARCELA PORQUE ESTA LEJOS DE LA CASA DEL PRODUCTOR | ES49: 22273904 | ET49: 214dd877-b950-4f78-82f6-78a3c61eff16 | EU49: 46207.502 | EX49: submitted_via_web | EZ49: vBf6xt5iWdkTjghTeBLtbw | FB49: uuid:214dd877-b950-4f78-82f6-78a3c61eff16 | FC49: 28
A50: ="V"&B50&"-R"&FC50 -> V3-R29 | B50: 3 | C50: 46206.667 | D50: 46207.252 | E50: 46205 | G50: Nancy | H50: Milagro | I50: 46206 | K50: ABNER OSORIS HERNANDEZ HERRERA | L50: 39 | M50: Hombre | O50: Morazán | P50: Morazán Norte | Q50: Perquín | R50: CHANGUITON | S50: CASA BLANCA | T50: TTSEISUNOSIETECINCO | V50: ABNER OSORIS HERNANDEZ HERRERA | W50: Sí | Y50: Productor | AB50: Sí | AD50: No sabe / no responde | AF50: Sí | AG50: 1 | AH50: 4 | AI50: 1 | AJ50: 0 | AK50: 240 | AL50: 9999 | AM50: 60 | AN50: 0 | AV50: Sí | AW50: 2024 | AX50: No | AY50: No | AZ50: DAVID ENOT PEREZ | BA50: No | BO50: Equipo de fumigación | BP50: 0 | BQ50: 0 | BR50: 0 | BS50: 0 | BT50: 0 | BU50: 1 | BV50: 0 | BW50: 0 | BX50: 0 | BY50: 0 | BZ50: 0 | CA50: 0 | CB50: 0 | CC50: No sufrió pérdidas de cosecha o animales | CD50: 0 | CE50: 0 | CF50: 0 | CG50: 0 | CH50: 0 | CI50: 0 | CJ50: 0 | CK50: 0 | CL50: 1 | CM50: 4 | CO50: Jornalero agropecuario | CP50: Sí | CQ50: No | CR50: No | CS50: Sí | CT50: No | CU50: No | CV50: No | CW50: No | CX50: Sí | CY50: Sí | CZ50: No | DA50: No | DB50: No | DC50: No | DD50: No | DE50: No | DG50: 7 | DH50: 7 | DI50: 7 | DJ50: 1 | DK50: 7 | DL50: 7 | DM50: 7 | DN50: 7 | DO50: Sí | DP50: Agua entubada | DR50: Sí | DS50: Sí | DT50: Ene Feb Mar Abr May Jun Jul Ago Sep Oct Nov Dic | DU50: 1 | DV50: 1 | DW50: 1 | DX50: 1 | DY50: 1 | DZ50: 1 | EA50: 1 | EB50: 1 | EC50: 1 | ED50: 1 | EE50: 1 | EF50: 1 | EH50: No | EJ50: Lejanía, dentro del distritio | EK50: 72399569 | EN50: NO SE MIDIO LA PARCELA POR LA DISTANCIA A PIE Y LA HORA DE LA TARDE EL PRODUCTOR DIJO QUE EL PROMOTOR FALSIFICABA FIRMAS Y NO ENTREGABA LOS INSUMOS QUE LOS DONANTES ENTREGABAN O ENTREGRABA SOLO A AMIGOS DE EL O SU FAMILIA | ES50: 22273913 | ET50: 7148e373-6a93-4242-abe6-d31cf8070bd9 | EU50: 46207.502 | EX50: submitted_via_web | EZ50: vBf6xt5iWdkTjghTeBLtbw | FB50: uuid:7148e373-6a93-4242-abe6-d31cf8070bd9 | FC50: 29
A51: ="V"&B51&"-R"&FC51 -> V3-R30 | B51: 3 | C51: 46205.416 | D51: 46205.569 | E51: 46204 | G51: Wendy | H51: Rigoberto | I51: 46205 | K51: CANDIDA AZUCENA MARTINEZ GOMEZ | L51: 30 | M51: Mujer | O51: Morazán | P51: Morazán Sur | Q51: Gualococti | R51: LA JOYA | S51: PENA BLANCA | V51: CANDIDA GOMEZ | W51: Sí | Y51: Productor | AB51: Sí | AD51: No | AF51: Sí | AG51: 1 | AH51: 1 | AI51: 1 | AJ51: 100 | AK51: 2 | AL51: 100 | AM51: 100 | AN51: 0 | AV51: Sí | AW51: 2025 | AX51: Sí | AY51: Sí | AZ51: NUBIA | BA51: Sí | BB51: Regeneración artificial (plantación de árboles) | BC51: Sí | BD51: Sí | BE51: RECLIMA | BF51: 0 | BG51: 1 | BH51: 0 | BI51: 0 | BJ51: 0 | BK51: 0 | BL51: Aumentó algo | BM51: Pastoreo | BO51: Podadora | BP51: 0 | BQ51: 0 | BR51: 0 | BS51: 0 | BT51: 1 | BU51: 0 | BV51: 0 | BW51: 0 | BX51: 0 | BY51: 0 | BZ51: 0 | CA51: 0 | CB51: 0 | CC51: Sequías | CD51: 0 | CE51: 1 | CF51: 0 | CG51: 0 | CH51: 0 | CI51: 0 | CJ51: 0 | CK51: 0 | CL51: 0 | CM51: 4 | CO51: Trabajo asalariado/permanente (sueldo regular) | CP51: Sí | CQ51: No | CR51: No | CS51: No | CT51: No | CU51: No | CV51: Sí | CW51: No | CX51: Sí | CY51: No | CZ51: No | DA51: No | DB51: No | DC51: No | DD51: No | DE51: No | DG51: 7 | DH51: 3 | DI51: 2 | DJ51: 3 | DK51: 7 | DL51: 2 | DM51: 3 | DN51: 7 | DO51: No | EH51: Sí | EI51: 13.837918 -88.216814 0 0;13.83795 -88.21793 0 0;13.838288 -88.217704 0 0;13.838564 -88.217919 0 0;13.838715 -88.218257 0 0;13.838395 -88.218667 0 0;13.837596 -88.218648 0 0;13.836983 -88.218296 0 0;13.837067 -88.217554 0 0;13.837644 -88.21682 0 0;13.838507 -88.216771 0 0;13.839559 -88.216299 0 0;13.83977 -88.217365 0 0;13.839674 -88.217887 0 0;13.838809 -88.218766 0 0;13.838049 -88.218981 0 0;13.836314 -88.219002 0 0;13.835572 -88.217688 0 0;13.835736 -88.216825 0 0;13.836817 -88.215711 0 0;13.837926 -88.215256 0 0;13.839158 -88.215687 0 0;13.83984 -88.215923 0 0;13.839928 -88.216278 0 0;13.837918 -88.216814 0 0 | EK51: 78903078 | EN51: NO | ES51: 22277737 | ET51: d56a51ff-421e-4ab1-b324-2338e58a5e8e | EU51: 46207.698 | EX51: submitted_via_web | EZ51: vmzueHpYT9juc6BY6BECkZ | FB51: uuid:d56a51ff-421e-4ab1-b324-2338e58a5e8e | FC51: 30
A52: ="V"&B52&"-R"&FC52 -> V3-R31 | B52: 3 | C52: 46205.732 | D52: 46207.456 | E52: 46204 | G52: Rodrigo | H52: Rigoberto | I52: 46207 | K52: SANTOS MARITZA HERNANDEZ DE MONTEAGUDO | L52: 28 | M52: Mujer | O52: Morazán | P52: Morazán Norte | Q52: El Rosario_M | S52: COLONIA VISTA AL RIO | T52: HA3380 | V52: MARITZA HERNANDEZ | W52: Sí | Y52: Productor | AB52: Sí | AD52: Sí | AF52: Sí | AG52: 1 | AH52: 3 | AI52: 1 | AJ52: 0 | AK52: 30 | AL52: 8 | AM52: 160 | AN52: 0 | AV52: Sí | AW52: 2024 | AX52: Sí | AY52: Sí | AZ52: NO SABE | BA52: Sí | BB52: Regeneración artificial (plantación de árboles) | BC52: No | BD52: Sí | BE52: ONG | BF52: 0 | BG52: 0 | BH52: 0 | BI52: 1 | BJ52: 0 | BK52: 0 | BL52: Disminuyó algo | BM52: Sequías extremas | BO52: Ningún activo | BP52: 0 | BQ52: 0 | BR52: 0 | BS52: 0 | BT52: 0 | BU52: 0 | BV52: 0 | BW52: 0 | BX52: 0 | BY52: 0 | BZ52: 0 | CA52: 0 | CB52: 1 | CC52: Sequías | CD52: 0 | CE52: 1 | CF52: 0 | CG52: 0 | CH52: 0 | CI52: 0 | CJ52: 0 | CK52: 0 | CL52: 0 | CM52: 3 | CO52: Trabajo asalariado/permanente (sueldo regular) | CP52: No | CQ52: No | CR52: No | CS52: No | CT52: No | CU52: No | CV52: No | CW52: No | CX52: Sí | CY52: No | CZ52: No | DA52: No | DB52: No | DC52: No | DD52: No | DE52: No | DG52: 7 | DH52: 5 | DI52: 5 | DJ52: 7 | DK52: 5 | DL52: 2 | DM52: 7 | DN52: 7 | DO52: Sí | DP52: Agua entubada | DR52: Sí | DS52: Sí | DT52: Ene Feb Mar Abr May Ago Sep Oct Nov Dic | DU52: 1 | DV52: 1 | DW52: 1 | DX52: 1 | DY52: 1 | DZ52: 0 | EA52: 0 | EB52: 1 | EC52: 1 | ED52: 1 | EE52: 1 | EF52: 1 | EH52: No | EJ52: Lejanía, dentro del distritio | EK52: 69953758 | EN52: EL SOLAR SOLO ES ACCESIBLD CON VEHICULO DE DOBLE TRACCION | ES52: 22278044 | ET52: eec57285-4d7a-46c9-a1fc-535fec6bf11f | EU52: 46207.709 | EX52: submitted_via_web | EZ52: vBf6xt5iWdkTjghTeBLtbw | FB52: uuid:eec57285-4d7a-46c9-a1fc-535fec6bf11f | FC52: 31
A53: ="V"&B53&"-R"&FC53 -> V3-R32 | B53: 3 | C53: 46207.366 | D53: 46207.568 | E53: 46206 | G53: Zaira | H53: Milagro | I53: 46207 | K53: BLANCA OLIVIA AVILES ESPINAL | L53: 48 | M53: Mujer | O53: La Unión | P53: La Unión Sur | Q53: Yucuaiquín | R53: LAS MARIAS | S53: SAN LUCAS | V53: BLANCA OLIVIA | W53: Sí | Y53: Productor | AB53: Sí | AD53: No | AF53: Sí | AG53: 1 | AH53: 1 | AI53: 1 | AJ53: 5 | AK53: 12 | AL53: 20 | AM53: 200 | AN53: 0 | AV53: Sí | AW53: 2025 | AX53: Sí | AY53: Sí | AZ53: YOALMO | BA53: Sí | BB53: Regeneración artificial (plantación de árboles) | BC53: No | BD53: Sí | BE53: RECLIMA | BF53: 0 | BG53: 1 | BH53: 0 | BI53: 0 | BJ53: 0 | BK53: 0 | BL53: Aumentó algo | BM53: Sequías extremas | BO53: Ningún activo | BP53: 0 | BQ53: 0 | BR53: 0 | BS53: 0 | BT53: 0 | BU53: 0 | BV53: 0 | BW53: 0 | BX53: 0 | BY53: 0 | BZ53: 0 | CA53: 0 | CB53: 1 | CC53: Plagas o enfermedades Lluvia o inundaciones | CD53: 1 | CE53: 0 | CF53: 1 | CG53: 0 | CH53: 0 | CI53: 0 | CJ53: 0 | CK53: 0 | CL53: 0 | CM53: 7 | CO53: Servicios domésticos | CP53: Sí | CQ53: Sí | CR53: Sí | CS53: Sí | CT53: Sí | CU53: Sí | CV53: Sí | CW53: Sí | CX53: Sí | CY53: Sí | CZ53: Sí | DA53: Sí | DB53: Sí | DC53: Sí | DD53: Sí | DE53: Sí | DG53: 1 | DH53: 4 | DI53: 0 | DJ53: 2 | DK53: 4 | DL53: 3 | DM53: 4 | DN53: 0 | DO53: Sí | DP53: Agua entubada | DR53: Sí | DS53: Sí | DT53: Ene Feb Mar Abr May Jun Jul Ago Sep Oct Nov Dic | DU53: 1 | DV53: 1 | DW53: 1 | DX53: 1 | DY53: 1 | DZ53: 1 | EA53: 1 | EB53: 1 | EC53: 1 | ED53: 1 | EE53: 1 | EF53: 1 | EH53: No | EJ53: Lejanía, dentro del distritio | EK53: 70153004 | EN53: NO SE MIDIO ESTABA OCUPADA | ES53: 22279088 | ET53: 847ec7f4-983d-4eca-ab6b-8abf248054d2 | EU53: 46207.818 | EX53: submitted_via_web | EZ53: vBf6xt5iWdkTjghTeBLtbw | FB53: uuid:847ec7f4-983d-4eca-ab6b-8abf248054d2 | FC53: 32
A54: ="V"&B54&"-R"&FC54 -> V3-R33 | B54: 3 | C54: 46207.41 | D54: 46207.572 | E54: 46206 | G54: Juan | H54: Rigoberto | I54: 46207 | K54: XENIA LILIANA ORELLANA DE VENTURA | L54: 39 | M54: Mujer | O54: Morazán | P54: Morazán Norte | Q54: El Rosario_M | R54: BARRIO EL CENTRO | T54: DW1968 | V54: XENIA ORELLANA | W54: Sí | Y54: Productor | AB54: Sí | AD54: No | AF54: No | EH54: No | EJ54: Lejanía, dentro del distritio | EK54: 72703741 | EN54: NO TIENEN TERRENO PARA CULTIVAR Y LOS ARBOLES LOS REGALARON A UN FAMILIAR Y EL TERRENO ESTA LEJOS | ES54: 22279098 | ET54: f63b489a-4a75-4c02-b4e6-1482c2179bd0 | EU54: 46207.822 | EX54: submitted_via_web | EZ54: vBf6xt5iWdkTjghTeBLtbw | FB54: uuid:f63b489a-4a75-4c02-b4e6-1482c2179bd0 | FC54: 33
A55: ="V"&B55&"-R"&FC55 -> V3-R34 | B55: 3 | C55: 46207.377 | D55: 46207.637 | E55: 46206 | G55: Milagro | H55: Milagro | I55: 46207 | K55: JOSE SANTOS PEREZ CONSTANCIA | L55: 37 | M55: Hombre | O55: La Unión | P55: La Unión Sur | Q55: Yucuaiquín | R55: SIRICUARIO | S55: SIRICUARIO | T55: VPNUEVEOCHODOSCERO | V55: SANTOS | W55: Sí | Y55: Productor | AB55: Sí | AD55: Sí | AF55: Sí | AG55: 1 | AH55: 1 | AI55: 1 | AJ55: 9999 | AK55: 9999 | AL55: 20 | AM55: 9999 | AN55: 9999 | AV55: Sí | AW55: 2025 | AX55: Sí | AY55: No | AZ55: KEVIN MAURICIO | BA55: Sí | BB55: Regeneración natural asistida | BC55: No | BD55: Sí | BE55: RECLIMA | BF55: 0 | BG55: 1 | BH55: 0 | BI55: 0 | BJ55: 0 | BK55: 0 | BL55: Sin cambió | BM55: Sequías extremas | BO55: Equipo de fumigación | BP55: 0 | BQ55: 0 | BR55: 0 | BS55: 0 | BT55: 0 | BU55: 1 | BV55: 0 | BW55: 0 | BX55: 0 | BY55: 0 | BZ55: 0 | CA55: 0 | CB55: 0 | CC55: Sequías | CD55: 0 | CE55: 1 | CF55: 0 | CG55: 0 | CH55: 0 | CI55: 0 | CJ55: 0 | CK55: 0 | CL55: 0 | CM55: 3 | CO55: Jornalero agropecuario | CP55: Sí | CQ55: Sí | CR55: Sí | CS55: Sí | CT55: No | CU55: Sí | CV55: No | CW55: No | CX55: No | DG55: 7 | DH55: 7 | DI55: 4 | DJ55: 3 | DK55: 5 | DL55: 7 | DM55: 7 | DN55: 7 | DO55: Sí | DP55: Agua entubada | DR55: Sí | DS55: Sí | DT55: Ene Feb Mar Abr May Jun Jul Ago Sep Oct Nov Dic | DU55: 1 | DV55: 1 | DW55: 1 | DX55: 1 | DY55: 1 | DZ55: 1 | EA55: 1 | EB55: 1 | EC55: 1 | ED55: 1 | EE55: 1 | EF55: 1 | EH55: No | EJ55: Lejanía, dentro del distritio | EK55: 73876326 | EN55: TERRENO EN TAMBORONES | ES55: 22279676 | ET55: 229a556d-aa23-4dc4-9214-0c913379cd57 | EU55: 46207.887 | EX55: submitted_via_web | EZ55: vBf6xt5iWdkTjghTeBLtbw | FB55: uuid:229a556d-aa23-4dc4-9214-0c913379cd57 | FC55: 34
A56: ="V"&B56&"-R"&FC56 -> V3-R35 | B56: 3 | C56: 46205.398 | D56: 46207.655 | E56: 46204 | G56: Rodrigo | H56: Rigoberto | I56: 46205 | K56: ALEJANDRA ORELLANA | L56: 62 | M56: Mujer | O56: Morazán | P56: Morazán Sur | Q56: Gualococti | R56: LA JOYA | S56: PENA BLANCA | T56: FL7589 | V56: ALEJANDRA ORELLANA | W56: Sí | Y56: Productor | AB56: Sí | AD56: No | AF56: Sí | AG56: 1 | AH56: 2 | AI56: 1 | AJ56: 100 | AK56: 0 | AL56: 0 | AM56: 0 | AN56: 0 | AV56: Sí | AW56: 2024 | AX56: Sí | AY56: Sí | AZ56: NUBIA LISSETH FUENTES | BA56: Sí | BB56: Regeneración artificial (plantación de árboles) | BC56: No | BD56: Sí | BE56: RECLIMA | BF56: 0 | BG56: 1 | BH56: 0 | BI56: 0 | BJ56: 0 | BK56: 0 | BL56: Sin cambió | BM56: Sequías extremas | BO56: Ningún activo | BP56: 0 | BQ56: 0 | BR56: 0 | BS56: 0 | BT56: 0 | BU56: 0 | BV56: 0 | BW56: 0 | BX56: 0 | BY56: 0 | BZ56: 0 | CA56: 0 | CB56: 1 | CC56: Sequías | CD56: 0 | CE56: 1 | CF56: 0 | CG56: 0 | CH56: 0 | CI56: 0 | CJ56: 0 | CK56: 0 | CL56: 0 | CM56: 6 | CO56: Remesas familiares | CP56: No | CQ56: No | CR56: No | CS56: Sí | CT56: No | CU56: No | CV56: No | CW56: No | CX56: Sí | CY56: No | CZ56: No | DA56: No | DB56: No | DC56: No | DD56: No | DE56: No | DG56: 7 | DH56: 7 | DI56: 3 | DJ56: 5 | DK56: 5 | DL56: 5 | DM56: 5 | DN56: 7 | DO56: Sí | DP56: Agua entubada | DR56: Sí | DS56: Sí | DT56: Ene Feb Mar Abr May Jun Jul Ago Sep Oct Nov Dic | DU56: 1 | DV56: 1 | DW56: 1 | DX56: 1 | DY56: 1 | DZ56: 1 | EA56: 1 | EB56: 1 | EC56: 1 | ED56: 1 | EE56: 1 | EF56: 1 | EH56: No | EJ56: Otra | EK56: 61344651 | EN56: EL ESPOSO MURIO Y HAY PLEITO POR EL TERRENO | ES56: 22279791 | ET56: 99734839-35af-449a-80a4-9fcd94e8f84e | EU56: 46207.905 | EX56: submitted_via_web | EZ56: vBf6xt5iWdkTjghTeBLtbw | FB56: uuid:99734839-35af-449a-80a4-9fcd94e8f84e | FC56: 35
A57: ="V"&B57&"-R"&FC57 -> V3-R36 | B57: 3 | C57: 46205.361 | D57: 46207.655 | E57: 46204 | G57: Rodrigo | H57: Rigoberto | I57: 46205 | K57: MARIA GUZMAN | L57: 57 | M57: Mujer | O57: Morazán | P57: Morazán Sur | Q57: Gualococti | R57: LA JOYA | S57: CHUPADERO | T57: CC4959 | V57: PETRONILA GUZMAN | W57: Sí | Y57: Productor | AB57: Sí | AD57: Sí | AF57: Sí | AG57: 5 | AH57: 2 | AI57: 2 | AJ57: 20 | AK57: 0 | AL57: 0 | AM57: 0 | AN57: 0 | AV57: Sí | AW57: 2025 | AX57: Sí | AY57: No | AZ57: VENTURA CHICAS | BA57: Sí | BB57: Regeneración artificial (plantación de árboles) | BC57: No | BD57: No | BL57: Sin cambió | BM57: Sequías extremas | BO57: Ningún activo | BP57: 0 | BQ57: 0 | BR57: 0 | BS57: 0 | BT57: 0 | BU57: 0 | BV57: 0 | BW57: 0 | BX57: 0 | BY57: 0 | BZ57: 0 | CA57: 0 | CB57: 1 | CC57: Sequías | CD57: 0 | CE57: 1 | CF57: 0 | CG57: 0 | CH57: 0 | CI57: 0 | CJ57: 0 | CK57: 0 | CL57: 0 | CM57: 2 | CO57: Trabajo eventual en actividades no agrícolas | CP57: Sí | CQ57: Sí | CR57: Sí | CS57: Sí | CT57: No | CU57: Sí | CV57: Sí | CW57: Sí | CX57: No | DG57: 7 | DH57: 5 | DI57: 0 | DJ57: 7 | DK57: 3 | DL57: 5 | DM57: 7 | DN57: 3 | DO57: Sí | DP57: Agua entubada | DR57: No | DS57: Sí | DT57: Ene Feb Mar Abr May Jun Jul Ago Sep Oct Nov Dic | DU57: 1 | DV57: 1 | DW57: 1 | DX57: 1 | DY57: 1 | DZ57: 1 | EA57: 1 | EB57: 1 | EC57: 1 | ED57: 1 | EE57: 1 | EF57: 1 | EH57: No | EJ57: Otra | EK57: 69911698 | EN57: PERSONA MAYOR ILETRADA | ES57: 22279795 | ET57: a70a1278-59d4-4e8c-9312-e37bbe74430a | EU57: 46207.905 | EX57: submitted_via_web | EZ57: vBf6xt5iWdkTjghTeBLtbw | FB57: uuid:a70a1278-59d4-4e8c-9312-e37bbe74430a | FC57: 36
A58: ="V"&B58&"-R"&FC58 -> V3-R37 | B58: 3 | C58: 46205.517 | D58: 46207.658 | E58: 46204 | G58: Rodrigo | H58: Rigoberto | I58: 46205 | K58: EDWIN SAUL PINEDA | L58: 36 | M58: Hombre | O58: Morazán | P58: Morazán Sur | Q58: Chilanga | R58: CHAPARAL | S58: PINEDA | T58: RH0465 | V58: EDWIN PINEDA | W58: Sí | Y58: Productor | AB58: Sí | AD58: Sí | AF58: Sí | AG58: 1 | AH58: 2 | AI58: 1 | AJ58: 50 | AK58: 150 | AL58: 20 | AM58: 300 | AN58: 0 | AO58: Cabras | AP58: 0 | AQ58: 0 | AR58: 0 | AS58: 1 | AT58: 0 | AV58: Sí | AW58: 2024 | AX58: Sí | AY58: No | AZ58: CRISPIN VASQUEZ | BA58: Sí | BB58: Regeneración artificial (plantación de árboles) | BC58: No | BD58: No | BL58: Sin cambió | BM58: Sequías extremas | BO58: Ningún activo | BP58: 0 | BQ58: 0 | BR58: 0 | BS58: 0 | BT58: 0 | BU58: 0 | BV58: 0 | BW58: 0 | BX58: 0 | BY58: 0 | BZ58: 0 | CA58: 0 | CB58: 1 | CC58: Sequías | CD58: 0 | CE58: 1 | CF58: 0 | CG58: 0 | CH58: 0 | CI58: 0 | CJ58: 0 | CK58: 0 | CL58: 0 | CM58: 4 | CO58: Jornalero agropecuario | CP58: Sí | CQ58: No | CR58: No | CS58: No | CT58: No | CU58: No | CV58: No | CW58: No | CX58: Sí | CY58: No | CZ58: No | DA58: No | DB58: No | DC58: No | DD58: No | DE58: No | DG58: 7 | DH58: 7 | DI58: 5 | DJ58: 4 | DK58: 7 | DL58: 1 | DM58: 7 | DN58: 7 | DO58: Sí | DP58: Pozo | DR58: Sí | DS58: Sí | DT58: Ene Feb Mar Abr May Jun Jul Ago Sep Oct Nov Dic | DU58: 1 | DV58: 1 | DW58: 1 | DX58: 1 | DY58: 1 | DZ58: 1 | EA58: 1 | EB58: 1 | EC58: 1 | ED58: 1 | EE58: 1 | EF58: 1 | EH58: No | EJ58: Lejanía, dentro del distritio | EK58: 78963086 | ES58: 22279813 | ET58: 5e65bcdf-97ed-43c0-bdee-990a03919f43 | EU58: 46207.908 | EX58: submitted_via_web | EZ58: vBf6xt5iWdkTjghTeBLtbw | FB58: uuid:5e65bcdf-97ed-43c0-bdee-990a03919f43 | FC58: 37
A59: ="V"&B59&"-R"&FC59 -> V3-R38 | B59: 3 | C59: 46207.654 | D59: 46207.715 | E59: 46206 | G59: Nancy | H59: Milagro | I59: 46207 | K59: JOSE MARGARITO YANES MENDOZA | L59: 38 | M59: Hombre | O59: La Unión | P59: La Unión Sur | Q59: Yucuaiquín | R59: LAS CRUCES | S59: CENTRO | T59: EVCUATROSIETENUEVEOCHO | V59: JOSE MARGARITO YANES MENDOZA | W59: Sí | Y59: Productor | AB59: Sí | AD59: No | AF59: Sí | AG59: 1 | AH59: 1 | AI59: 1 | AJ59: 28 | AK59: 64 | AL59: 28 | AM59: 300 | AN59: 0 | AV59: Sí | AW59: 2025 | AX59: No | AY59: No | AZ59: JAIME PEREZ | BA59: No | BO59: Ningún activo | BP59: 0 | BQ59: 0 | BR59: 0 | BS59: 0 | BT59: 0 | BU59: 0 | BV59: 0 | BW59: 0 | BX59: 0 | BY59: 0 | BZ59: 0 | CA59: 0 | CB59: 1 | CC59: Lluvia o inundaciones | CD59: 0 | CE59: 0 | CF59: 1 | CG59: 0 | CH59: 0 | CI59: 0 | CJ59: 0 | CK59: 0 | CL59: 0 | CM59: 4 | CO59: Trabajo asalariado/permanente (sueldo regular) | CP59: Sí | CQ59: No | CR59: No | CS59: Sí | CT59: No | CU59: No | CV59: No | CW59: No | CX59: Sí | CY59: No | CZ59: No | DA59: No | DB59: No | DC59: No | DD59: No | DE59: No | DG59: 7 | DH59: 7 | DI59: 3 | DJ59: 3 | DK59: 7 | DL59: 7 | DM59: 7 | DN59: 7 | DO59: Sí | DP59: Nacimiento de agua | DR59: No | DS59: Sí | DT59: Sep Nov Dic | DU59: 0 | DV59: 0 | DW59: 0 | DX59: 0 | DY59: 0 | DZ59: 0 | EA59: 0 | EB59: 0 | EC59: 1 | ED59: 0 | EE59: 1 | EF59: 1 | EH59: Sí | EK59: 74341913 | ES59: 22279856 | ET59: bd6d012c-c5ce-4e18-b4d6-39954325b97f | EU59: 46207.965 | EX59: submitted_via_web | EZ59: vBf6xt5iWdkTjghTeBLtbw | FB59: uuid:bd6d012c-c5ce-4e18-b4d6-39954325b97f | FC59: 38
A60: ="V"&B60&"-R"&FC60 -> V3-R39 | B60: 3 | C60: 46207.568 | D60: 46207.64 | E60: 46206 | G60: Zaira | H60: Milagro | I60: 46207 | K60: DELMI ARELY PINEDA DE MAJANO | L60: 25 | M60: Mujer | O60: La Unión | P60: La Unión Sur | Q60: Yucuaiquín | R60: EL CARMEN | V60: DELMI PINEDA | W60: Sí | Y60: Productor | AB60: Sí | AD60: No | AF60: Sí | AG60: 1 | AH60: 3 | AI60: 1 | AJ60: 0 | AK60: 0 | AL60: 2 | AM60: 0 | AN60: 0 | AV60: Sí | AW60: 2025 | AX60: Sí | AY60: No | AZ60: ERODITA | BA60: Sí | BB60: Regeneración artificial (plantación de árboles) | BC60: No | BD60: Sí | BE60: RECLIMA | BF60: 0 | BG60: 1 | BH60: 0 | BI60: 0 | BJ60: 0 | BK60: 0 | BL60: Aumentó algo | BM60: Sequías extremas | BO60: Ningún activo | BP60: 0 | BQ60: 0 | BR60: 0 | BS60: 0 | BT60: 0 | BU60: 0 | BV60: 0 | BW60: 0 | BX60: 0 | BY60: 0 | BZ60: 0 | CA60: 0 | CB60: 1 | CC60: Plagas o enfermedades Sequías | CD60: 1 | CE60: 1 | CF60: 0 | CG60: 0 | CH60: 0 | CI60: 0 | CJ60: 0 | CK60: 0 | CL60: 0 | CM60: 7 | CO60: Trabajo asalariado/permanente (sueldo regular) | CP60: Sí | CQ60: Sí | CR60: Sí | CS60: Sí | CT60: No | CU60: No | CV60: No | CW60: No | CX60: Sí | CY60: No | CZ60: No | DA60: No | DB60: Sí | DC60: No | DD60: No | DE60: No | DG60: 7 | DH60: 3 | DI60: 3 | DJ60: 1 | DK60: 3 | DL60: 7 | DM60: 7 | DN60: 7 | DO60: Sí | DP60: Pozo | DR60: Sí | DS60: Sí | DT60: Ene Feb Mar Sep Oct Nov Dic | DU60: 1 | DV60: 1 | DW60: 1 | DX60: 0 | DY60: 0 | DZ60: 0 | EA60: 0 | EB60: 0 | EC60: 1 | ED60: 1 | EE60: 1 | EF60: 1 | EH60: No | EJ60: Otra | EK60: 73022507 | ES60: 22279979 | ET60: 0c318b1c-ed3f-440d-ab3e-7d0c3248a13a | EU60: 46208.038 | EX60: submitted_via_web | EZ60: vBf6xt5iWdkTjghTeBLtbw | FB60: uuid:0c318b1c-ed3f-440d-ab3e-7d0c3248a13a | FC60: 39
A61: ="V"&B61&"-R"&FC61 -> V3-R40 | B61: 3 | C61: 46208.314 | D61: 46208.355 | E61: 46207 | G61: Nancy | H61: Milagro | I61: 46208 | K61: JOSE SALOMON CLAROS CRUZ | L61: 63 | M61: Hombre | O61: Usulután | P61: Usulután Norte | Q61: Jucuapa | R61: EL AMATON | S61: LOS SANTOS | T61: HNSEISCEROTRESOCHO | V61: ROXANA PINEDA | W61: Sí | Y61: Familiar del productor | AB61: Sí | AD61: Sí | AF61: Sí | AG61: 1 | AH61: 2 | AI61: 1 | AJ61: 300 | AK61: 9999 | AL61: 9999 | AM61: 70 | AN61: 200 | AV61: Sí | AW61: 2023 | AX61: Sí | AY61: No | AZ61: ROLA DO MEJILLA | BA61: Sí | BB61: Regeneración artificial (plantación de árboles) | BC61: No | BD61: No | BL61: Disminuyó mucho | BM61: Sequías extremas | BO61: Ningún activo | BP61: 0 | BQ61: 0 | BR61: 0 | BS61: 0 | BT61: 0 | BU61: 0 | BV61: 0 | BW61: 0 | BX61: 0 | BY61: 0 | BZ61: 0 | CA61: 0 | CB61: 1 | CC61: Sequías | CD61: 0 | CE61: 1 | CF61: 0 | CG61: 0 | CH61: 0 | CI61: 0 | CJ61: 0 | CK61: 0 | CL61: 0 | CM61: 5 | CO61: Servicios domésticos | CP61: Sí | CQ61: Sí | CR61: Sí | CS61: Sí | CT61: Sí | CU61: Sí | CV61: Sí | CW61: No | CX61: Sí | CY61: Sí | CZ61: Sí | DA61: Sí | DB61: Sí | DC61: Sí | DD61: Sí | DE61: Sí | DG61: 7 | DH61: 7 | DI61: 1 | DJ61: 0 | DK61: 3 | DL61: 7 | DM61: 0 | DN61: 7 | DO61: Sí | DP61: Pozo | DR61: No | DS61: Sí | DT61: Jul Ago Sep Oct | DU61: 0 | DV61: 0 | DW61: 0 | DX61: 0 | DY61: 0 | DZ61: 0 | EA61: 1 | EB61: 1 | EC61: 1 | ED61: 1 | EE61: 0 | EF61: 0 | EH61: No | EJ61: Lejanía, dentro del distritio | EK61: 79969625 | EN61: LA ESPOSA DEL PRODUCTOR NO TUVO TIEMPO PARA IR A MEDIR LA PARCELA PORQUE DEBIA SALIR | ES61: 22290134 | ET61: 44899382-ced4-48cb-9fe7-be8b3e09a8b5 | EU61: 46208.606 | EX61: submitted_via_web | EZ61: vBf6xt5iWdkTjghTeBLtbw | FB61: uuid:44899382-ced4-48cb-9fe7-be8b3e09a8b5 | FC61: 40
A62: ="V"&B62&"-R"&FC62 -> V3-R41 | B62: 3 | C62: 46207.64 | D62: 46208.394 | E62: 46206 | G62: Zaira | H62: Milagro | I62: 46208 | K62: OSCAR RAFAEL SANTOS | L62: 69 | M62: Hombre | O62: Usulután | P62: Usulután Norte | Q62: Jucuapa | R62: EL AMATON | S62: LOS SANTOS | T62: RVCEROTRESCINCOSIETE | V62: OSCAR | W62: Sí | Y62: Productor | AB62: Sí | AD62: No | AF62: Sí | AG62: 1 | AH62: 2 | AI62: 1 | AJ62: 125 | AK62: 0 | AL62: 360 | AM62: 100 | AN62: 1500 | AO62: Bovinos (vacas, terneros, novillos, bueyes, toros) | AP62: 1 | AQ62: 0 | AR62: 0 | AS62: 0 | AT62: 0 | AV62: Sí | AW62: 2025 | AX62: Sí | AY62: Sí | AZ62: NO SE ACUERDA | BA62: Sí | BB62: Regeneración natural asistida | BC62: No | BD62: Sí | BE62: RECLIMA | BF62: 0 | BG62: 1 | BH62: 0 | BI62: 0 | BJ62: 0 | BK62: 0 | BL62: Aumentó algo | BM62: Incendios forestales | BO62: Ningún activo | BP62: 0 | BQ62: 0 | BR62: 0 | BS62: 0 | BT62: 0 | BU62: 0 | BV62: 0 | BW62: 0 | BX62: 0 | BY62: 0 | BZ62: 0 | CA62: 0 | CB62: 1 | CC62: Sequías Lluvia o inundaciones | CD62: 0 | CE62: 1 | CF62: 1 | CG62: 0 | CH62: 0 | CI62: 0 | CJ62: 0 | CK62: 0 | CL62: 0 | CM62: 7 | CO62: Producción agropecuaria | CP62: Sí | CQ62: No | CR62: No | CS62: No | CT62: No | CU62: No | CV62: Sí | CW62: No | CX62: No | DG62: 3 | DH62: 7 | DI62: 3 | DJ62: 6 | DK62: 7 | DL62: 7 | DM62: 7 | DN62: 1 | DO62: Sí | DP62: Agua entubada | DR62: Sí | DS62: Sí | DT62: Ene Feb Mar Abr May Jun Jul Ago Sep Oct Nov Dic | DU62: 1 | DV62: 1 | DW62: 1 | DX62: 1 | DY62: 1 | DZ62: 1 | EA62: 1 | EB62: 1 | EC62: 1 | ED62: 1 | EE62: 1 | EF62: 1 | EH62: Sí | EK62: 61372763 | ES62: 22291401 | ET62: 1eec7806-dc61-4a20-94ff-ed86719da285 | EU62: 46208.644 | EX62: submitted_via_web | EZ62: vBf6xt5iWdkTjghTeBLtbw | FB62: uuid:1eec7806-dc61-4a20-94ff-ed86719da285 | FC62: 41
A63: ="V"&B63&"-R"&FC63 -> V3-R42 | B63: 3 | C63: 46206.546 | D63: 46208.395 | E63: 46205 | G63: Zaira | H63: Milagro | I63: 46206 | K63: POMPEO AMAYA CHICAS | L63: 70 | M63: Hombre | O63: Morazán | P63: Morazán Norte | Q63: Perquín | R63: CASA BLANCA | S63: ACHIOTE | T63: KRSEISOCHOTRESOCHO | V63: APOMPEO | W63: Sí | Y63: Productor | AB63: Sí | AD63: No | AF63: Sí | AG63: 2 | AH63: 3 | AI63: 2 | AJ63: 0 | AK63: 0 | AL63: 50 | AM63: 220 | AN63: 0 | AV63: Sí | AW63: 2023 | AX63: No | AY63: No | AZ63: FRANCIS BALMORE | BA63: Sí | BB63: Regeneración artificial (plantación de árboles) | BC63: No | BD63: No | BL63: Disminuyó algo | BM63: Incendios forestales | BO63: Ningún activo | BP63: 0 | BQ63: 0 | BR63: 0 | BS63: 0 | BT63: 0 | BU63: 0 | BV63: 0 | BW63: 0 | BX63: 0 | BY63: 0 | BZ63: 0 | CA63: 0 | CB63: 1 | CC63: No sufrió pérdidas de cosecha o animales | CD63: 0 | CE63: 0 | CF63: 0 | CG63: 0 | CH63: 0 | CI63: 0 | CJ63: 0 | CK63: 0 | CL63: 1 | CM63: 5 | CO63: Trabajo asalariado/permanente (sueldo regular) | CP63: Sí | CQ63: No | CR63: No | CS63: No | CT63: No | CU63: No | CV63: No | CW63: No | CX63: Sí | CY63: No | CZ63: No | DA63: No | DB63: No | DC63: No | DD63: No | DE63: No | DG63: 6 | DH63: 3 | DI63: 4 | DJ63: 5 | DK63: 7 | DL63: 7 | DM63: 5 | DN63: 2 | DO63: Sí | DP63: Agua entubada | DR63: Sí | DS63: Sí | DT63: Ene Feb Mar Abr May Jun Jul Ago Sep Oct Nov Dic | DU63: 1 | DV63: 1 | DW63: 1 | DX63: 1 | DY63: 1 | DZ63: 1 | EA63: 1 | EB63: 1 | EC63: 1 | ED63: 1 | EE63: 1 | EF63: 1 | EH63: No | EJ63: Productor se rehuso | EK63: 79884971 | ES63: 22291543 | ET63: a300ee44-d712-4b33-b1b5-68a247a72d92 | EU63: 46208.645 | EX63: submitted_via_web | EZ63: vBf6xt5iWdkTjghTeBLtbw | FB63: uuid:a300ee44-d712-4b33-b1b5-68a247a72d92 | FC63: 42
A64: ="V"&B64&"-R"&FC64 -> V3-R43 | B64: 3 | C64: 46205.731 | D64: 46208.397 | E64: 46204 | G64: Zaira | H64: Milagro | I64: 46206 | K64: JOSE ASENCION RAMOS SAENZ | L64: 71 | M64: Hombre | O64: Morazán | P64: Morazán Norte | Q64: Perquín | R64: CASA BLANCA | S64: CASA BLANCA | T64: VKCUATROCEROUNOOCHO | V64: REINA MARGARITA RAMOS | W64: Sí | Y64: Familiar del productor | AB64: Sí | AD64: No | AF64: Sí | AG64: 4 | AH64: 5 | AI64: 2 | AJ64: 200 | AK64: 26.6 | AL64: 40 | AM64: 30 | AN64: 0 | AV64: Sí | AW64: 2024 | AX64: Sí | AY64: No | AZ64: JOSE LUIS | BA64: Sí | BB64: Regeneración artificial (plantación de árboles) | BC64: No | BD64: No | BL64: Aumentó algo | BM64: Incendios forestales | BO64: Sembradora Equipo de fumigación | BP64: 0 | BQ64: 0 | BR64: 0 | BS64: 1 | BT64: 0 | BU64: 1 | BV64: 0 | BW64: 0 | BX64: 0 | BY64: 0 | BZ64: 0 | CA64: 0 | CB64: 0 | CC64: Plagas o enfermedades | CD64: 1 | CE64: 0 | CF64: 0 | CG64: 0 | CH64: 0 | CI64: 0 | CJ64: 0 | CK64: 0 | CL64: 0 | CM64: 5 | CO64: Producción agropecuaria | CP64: No | CQ64: No | CR64: Sí | CS64: Sí | CT64: No | CU64: No | CV64: No | CW64: No | CX64: Sí | CY64: No | CZ64: Sí | DA64: No | DB64: No | DC64: No | DD64: No | DE64: No | DG64: 7 | DH64: 2 | DI64: 7 | DJ64: 3 | DK64: 3 | DL64: 2 | DM64: 7 | DN64: 7 | DO64: Sí | DP64: Nacimiento de agua | DR64: Sí | DS64: Sí | DT64: Ene Feb Mar Abr May Jun Jul Ago Sep Oct Nov Dic | DU64: 1 | DV64: 1 | DW64: 1 | DX64: 1 | DY64: 1 | DZ64: 1 | EA64: 1 | EB64: 1 | EC64: 1 | ED64: 1 | EE64: 1 | EF64: 1 | EH64: Sí | EI64: 13.97198 -88.159995 1073.2847554741472 13.904000282287598;13.971873 -88.15979 1073.6876931616991 23.600000381469727;13.971873 -88.15979 1073.292954599385 26.399999618530273;13.971875 -88.159789 1073.1945656124353 45.599998474121094;13.97198 -88.159995 1073.2847554741472 13.904000282287598 | EK64: 75563535 | ES64: 22291582 | ET64: 8b38c7a3-139f-4f00-903c-a3688ea5375f | EU64: 46208.647 | EX64: submitted_via_web | EZ64: vBf6xt5iWdkTjghTeBLtbw | FB64: uuid:8b38c7a3-139f-4f00-903c-a3688ea5375f | FC64: 43
A65: ="V"&B65&"-R"&FC65 -> V3-R44 | B65: 3 | C65: 46208.355 | D65: 46208.394 | E65: 46207 | G65: Nancy | H65: Milagro | I65: 46208 | K65: DIEGO ALEJANDRO AYALA CAMPOS | L65: 27 | M65: Hombre | O65: Usulután | P65: Usulután Norte | Q65: Jucuapa | R65: EL AMATON | S65: LOS SANTOS | T65: XNSIETETRESCEROUNO | V65: JUAN CARLOS AYALA BERRIO | W65: Sí | Y65: Familiar del productor | AB65: Sí | AD65: Sí | AF65: Sí | AG65: 1 | AH65: 2 | AI65: 1 | AJ65: 40 | AK65: 55 | AL65: 8 | AM65: 30 | AN65: 0 | AV65: Sí | AW65: 2024 | AX65: Sí | AY65: No | AZ65: NO SABE | BA65: No | BO65: Ningún activo | BP65: 0 | BQ65: 0 | BR65: 0 | BS65: 0 | BT65: 0 | BU65: 0 | BV65: 0 | BW65: 0 | BX65: 0 | BY65: 0 | BZ65: 0 | CA65: 0 | CB65: 1 | CC65: Vientos fuertes | CD65: 0 | CE65: 0 | CF65: 0 | CG65: 0 | CH65: 1 | CI65: 0 | CJ65: 0 | CK65: 0 | CL65: 0 | CM65: 4 | CO65: Producción agropecuaria | CP65: Sí | CQ65: Sí | CR65: Sí | CS65: Sí | CT65: No | CU65: Sí | CV65: Sí | CW65: No | CX65: No | DG65: 4 | DH65: 7 | DI65: 0 | DJ65: 0 | DK65: 5 | DL65: 5 | DM65: 7 | DN65: 3 | DO65: Sí | DP65: Pozo | DR65: No | DS65: Sí | DT65: Jul Ago Sep | DU65: 0 | DV65: 0 | DW65: 0 | DX65: 0 | DY65: 0 | DZ65: 0 | EA65: 1 | EB65: 1 | EC65: 1 | ED65: 0 | EE65: 0 | EF65: 0 | EH65: No | EJ65: Lejanía, dentro del distritio | EK65: 64532946 | EN65: SE ENCUESTO AL PAPA DEL PRODUCTOR PORQUE AMBOS TRABAJAN JUNTOS NO SE MIDIO LA PARCELA POR LA DISTANCIA | ES65: 22293850 | ET65: f0f3042a-9370-42c1-a781-77e72e093b19 | EU65: 46208.749 | EX65: submitted_via_web | EZ65: vBf6xt5iWdkTjghTeBLtbw | FB65: uuid:f0f3042a-9370-42c1-a781-77e72e093b19 | FC65: 44
A66: ="V"&B66&"-R"&FC66 -> V3-R45 | B66: 3 | C66: 46208.394 | D66: 46208.514 | E66: 46207 | G66: Nancy | H66: Milagro | I66: 46208 | K66: LUZ MARINA JIMENEZ RAMOZ | L66: 50 | M66: Mujer | O66: Usulután | P66: Usulután Este | Q66: Jucuarán | R66: LLANO EL CHILAMATE | S66: CENTRO | T66: CWCUATROSEISTRESUNO | V66: RAFAEL ANTONIO JIMENEZ | W66: Sí | Y66: Familiar del productor | AB66: Sí | AD66: No sabe / no responde | AF66: Sí | AG66: 1 | AH66: 2 | AI66: 1 | AJ66: 100 | AK66: 80 | AL66: 60 | AM66: 40 | AN66: 9999 | AV66: Sí | AW66: 2023 | AX66: No | AY66: No | AZ66: NO SABE | BA66: Sí | BB66: Regeneración artificial (plantación de árboles) | BC66: No | BD66: No | BL66: Sin cambió | BM66: Falta de mantenimiento | BO66: Bomba de agua | BP66: 0 | BQ66: 0 | BR66: 0 | BS66: 0 | BT66: 0 | BU66: 0 | BV66: 0 | BW66: 1 | BX66: 0 | BY66: 0 | BZ66: 0 | CA66: 0 | CB66: 0 | CC66: No sufrió pérdidas de cosecha o animales | CD66: 0 | CE66: 0 | CF66: 0 | CG66: 0 | CH66: 0 | CI66: 0 | CJ66: 0 | CK66: 0 | CL66: 1 | CM66: 2 | CO66: Producción agropecuaria | CP66: Sí | CQ66: No | CR66: No | CS66: Sí | CT66: No | CU66: No | CV66: No | CW66: No | CX66: No | DG66: 7 | DH66: 7 | DI66: 5 | DJ66: 3 | DK66: 7 | DL66: 3 | DM66: 7 | DN66: 3 | DO66: Sí | DP66: Agua entubada | DR66: Sí | DS66: Sí | DT66: Ene Feb Mar Abr May Jun Jul Ago Sep Oct Nov Dic | DU66: 1 | DV66: 1 | DW66: 1 | DX66: 1 | DY66: 1 | DZ66: 1 | EA66: 1 | EB66: 1 | EC66: 1 | ED66: 1 | EE66: 1 | EF66: 1 | EH66: No | EJ66: Productor se rehuso | EK66: 73868448 | EN66: NO SE PUDO MEDIR LA PARCELA PORQUE DEBIA SALIR EL PRODUCTOR | ES66: 22293974 | ET66: 9f336b3d-42a6-435b-b534-eb00682920e0 | EU66: 46208.765 | EX66: submitted_via_web | EZ66: vBf6xt5iWdkTjghTeBLtbw | FB66: uuid:9f336b3d-42a6-435b-b534-eb00682920e0 | FC66: 45
A67: ="V"&B67&"-R"&FC67 -> V3-R46 | B67: 3 | C67: 46208.345 | D67: 46208.548 | E67: 46207 | G67: Milagro | H67: Milagro | I67: 46208 | K67: JUAN ANTONIO CRUZ SANTOS | L67: 40 | M67: Mujer | O67: Usulután | P67: Usulután Norte | Q67: Jucuapa | R67: EL AMATON | S67: LOS SANTOS | T67: YCCEROOCHOCERODOS | V67: JUAN | W67: Sí | Y67: Productor | AB67: Sí | AD67: No | AF67: Sí | AG67: 2 | AH67: 3 | AI67: 2 | AJ67: 150 | AK67: 600 | AL67: 50 | AM67: 900 | AN67: 5000 | AO67: Bovinos (vacas, terneros, novillos, bueyes, toros) | AP67: 1 | AQ67: 0 | AR67: 0 | AS67: 0 | AT67: 0 | AV67: Sí | AW67: 2025 | AX67: Sí | AY67: Sí | AZ67: RAUL MONCHI | BA67: Sí | BB67: Regeneración artificial (plantación de árboles) | BC67: No | BD67: Sí | BE67: RECLIMA | BF67: 0 | BG67: 1 | BH67: 0 | BI67: 0 | BJ67: 0 | BK67: 0 | BL67: Sin cambió | BM67: Sequías extremas | BO67: Ningún activo | BP67: 0 | BQ67: 0 | BR67: 0 | BS67: 0 | BT67: 0 | BU67: 0 | BV67: 0 | BW67: 0 | BX67: 0 | BY67: 0 | BZ67: 0 | CA67: 0 | CB67: 1 | CC67: No sufrió pérdidas de cosecha o animales | CD67: 0 | CE67: 0 | CF67: 0 | CG67: 0 | CH67: 0 | CI67: 0 | CJ67: 0 | CK67: 0 | CL67: 1 | CM67: 2 | CO67: Producción agropecuaria | CP67: No | CQ67: No | CR67: No | CS67: No | CT67: No | CU67: No | CV67: No | CW67: No | CX67: No | DG67: 7 | DH67: 7 | DI67: 3 | DJ67: 2 | DK67: 3 | DL67: 7 | DM67: 7 | DN67: 7 | DO67: Sí | DP67: Agua entubada | DR67: Sí | DS67: Sí | DT67: Ene Feb Mar Abr May Jun Jul Ago Sep Oct Nov Dic | DU67: 1 | DV67: 1 | DW67: 1 | DX67: 1 | DY67: 1 | DZ67: 1 | EA67: 1 | EB67: 1 | EC67: 1 | ED67: 1 | EE67: 1 | EF67: 1 | EH67: No | EJ67: Lejanía, fuera del distritio | EK67: 64262348 | ES67: 22294270 | ET67: 3fb6e8ee-d339-4928-9777-268dd751c0f7 | EU67: 46208.798 | EX67: submitted_via_web | EZ67: vBf6xt5iWdkTjghTeBLtbw | FB67: uuid:3fb6e8ee-d339-4928-9777-268dd751c0f7 | FC67: 46
A68: ="V"&B68&"-R"&FC68 -> V3-R47 | B68: 3 | C68: 46208.514 | D68: 46208.793 | E68: 46207 | G68: Nancy | H68: Milagro | I68: 46208 | K68: SUSANA GRANILLO DE CRUZ | L68: 46 | M68: Hombre | O68: Usulután | P68: Usulután Norte | Q68: Jucuapa | R68: LLANO CHILAMATE | S68: CIENTODIEZ | T68: DEDOSSIETECINCOSEIS | V68: SUSANA GRANILLO DE CRUZ | W68: Sí | Y68: Productor | AB68: Sí | AD68: No | AF68: Sí | AG68: 1 | AH68: 3 | AI68: 1 | AJ68: 50 | AK68: 100 | AL68: 35 | AM68: 0 | AN68: 0 | AO68: Bovinos (vacas, terneros, novillos, bueyes, toros) Aves (gallinas, pollos, gallos) | AP68: 1 | AQ68: 0 | AR68: 1 | AS68: 0 | AT68: 0 | AV68: Sí | AW68: 2023 | AX68: Sí | AY68: Sí | AZ68: SONIA MARGARITA GOMEZ | BA68: Sí | BB68: Regeneración artificial (plantación de árboles) | BC68: No | BD68: Sí | BE68: RECLIMA | BF68: 0 | BG68: 1 | BH68: 0 | BI68: 0 | BJ68: 0 | BK68: 0 | BL68: Sin cambió | BM68: Sequías extremas | BO68: Ningún activo | BP68: 0 | BQ68: 0 | BR68: 0 | BS68: 0 | BT68: 0 | BU68: 0 | BV68: 0 | BW68: 0 | BX68: 0 | BY68: 0 | BZ68: 0 | CA68: 0 | CB68: 1 | CC68: Sequías | CD68: 0 | CE68: 1 | CF68: 0 | CG68: 0 | CH68: 0 | CI68: 0 | CJ68: 0 | CK68: 0 | CL68: 0 | CM68: 7 | CO68: Oficios varios (artesanías, carpintería, albañilería, etc.) | CP68: No | CQ68: No | CR68: No | CS68: No | CT68: No | CU68: No | CV68: No | CW68: No | CX68: Sí | CY68: No | CZ68: No | DA68: No | DB68: No | DC68: No | DD68: No | DE68: No | DG68: 7 | DH68: 7 | DI68: 3 | DJ68: 2 | DK68: 7 | DL68: 2 | DM68: 7 | DN68: 2 | DO68: Sí | DP68: Agua entubada | DR68: Sí | DS68: Sí | DT68: Ene Feb Mar Abr May Jun Jul Ago Sep Oct Nov Dic | DU68: 1 | DV68: 1 | DW68: 1 | DX68: 1 | DY68: 1 | DZ68: 1 | EA68: 1 | EB68: 1 | EC68: 1 | ED68: 1 | EE68: 1 | EF68: 1 | EH68: No | EJ68: Productor se rehuso | EK68: 77642384 | EN68: NO SE MIDIO LA PARCELA PORQUE ELLA ESTABA EN LA IGLESIA Y NO QUISO IR | ES68: 22294823 | ET68: 2333626f-d3af-4a7c-b8fd-826273935275 | EU68: 46209.043 | EX68: submitted_via_web | EZ68: vBf6xt5iWdkTjghTeBLtbw | FB68: uuid:2333626f-d3af-4a7c-b8fd-826273935275 | FC68: 47
A69: ="V"&B69&"-R"&FC69 -> V3-R48 | B69: 3 | C69: 46209.538 | D69: 46209.559 | E69: 46208 | G69: Juan | H69: Rigoberto | I69: 46200 | K69: OSCAR ANTONIO OSEGUEDA | L69: 50 | M69: Hombre | O69: La Paz | P69: La Paz Oeste | Q69: San Luis Talpa | R69: HERBEDOR | S69: HERBEDOR | V69: CELINA MOJARAS | W69: Sí | Y69: Familiar del productor | AB69: Sí | AD69: No | AF69: Sí | AG69: 1 | AH69: 1 | AI69: 1 | AJ69: 80 | AK69: 30 | AL69: 15 | AM69: 120 | AN69: 0 | AV69: Sí | AW69: 2025 | AX69: Sí | AY69: No | AZ69: NO SABE | BA69: No | BO69: Tractor Rastra Equipo de fumigación Bomba de agua | BP69: 1 | BQ69: 1 | BR69: 0 | BS69: 0 | BT69: 0 | BU69: 1 | BV69: 0 | BW69: 1 | BX69: 0 | BY69: 0 | BZ69: 0 | CA69: 0 | CB69: 0 | CC69: No sufrió pérdidas de cosecha o animales | CD69: 0 | CE69: 0 | CF69: 0 | CG69: 0 | CH69: 0 | CI69: 0 | CJ69: 0 | CK69: 0 | CL69: 1 | CM69: 2 | CO69: Comercio informal | CP69: Sí | CQ69: Sí | CR69: Sí | CS69: Sí | CT69: Sí | CU69: Sí | CV69: Sí | CW69: Sí | CX69: No | DG69: 5 | DH69: 0 | DI69: 3 | DJ69: 4 | DK69: 0 | DL69: 7 | DM69: 3 | DN69: 7 | DO69: Sí | DP69: Pozo | DR69: Sí | DS69: Sí | DT69: May Jun Jul Ago Sep Oct | DU69: 0 | DV69: 0 | DW69: 0 | DX69: 0 | DY69: 1 | DZ69: 1 | EA69: 1 | EB69: 1 | EC69: 1 | ED69: 1 | EE69: 0 | EF69: 0 | EH69: No | EJ69: Lejanía, dentro del distritio | EK69: 64221131 | EN69: LA PERSONA ENCUESTADA NO DIO EL PERMISO PARA MEDIR LA PARCELA Y LA PARCELA QUEDA A VEINTE MINUTOS DE LA VIVIENDA | ES69: 22308786 | ET69: 3dc275db-1a74-4423-a7f6-d77549d42752 | EU69: 46209.809 | EX69: submitted_via_web | EZ69: vBf6xt5iWdkTjghTeBLtbw | FB69: uuid:3dc275db-1a74-4423-a7f6-d77549d42752 | FC69: 48
A70: ="V"&B70&"-R"&FC70 -> V3-R49 | B70: 3 | C70: 46209.559 | D70: 46209.648 | E70: 46208 | G70: Juan | H70: Milagro | I70: 46200 | K70: JOSELIN BRISEIDA DE LA ROSA GUERRERO | L70: 28 | M70: Mujer | O70: La Paz | P70: La Paz Oeste | Q70: San Luis Talpa | R70: EL PORVENIR | S70: EL PORVENIR | V70: MANUEL DE JESUS AGUIRRE ORTIZ | W70: Sí | Y70: Familiar del productor | AB70: Sí | AD70: No | AF70: Sí | AG70: 1 | AH70: 3 | AI70: 1 | AJ70: 400 | AK70: 300 | AL70: 0 | AM70: 200 | AN70: 600 | AV70: Sí | AW70: 2025 | AX70: Sí | AY70: Sí | AZ70: NO SABE | BA70: No | BO70: Tractor Rastra Equipo de fumigación Bomba de agua | BP70: 1 | BQ70: 1 | BR70: 0 | BS70: 0 | BT70: 0 | BU70: 1 | BV70: 0 | BW70: 1 | BX70: 0 | BY70: 0 | BZ70: 0 | CA70: 0 | CB70: 0 | CC70: Lluvia o inundaciones | CD70: 0 | CE70: 0 | CF70: 1 | CG70: 0 | CH70: 0 | CI70: 0 | CJ70: 0 | CK70: 0 | CL70: 0 | CM70: 3 | CO70: Jornalero agropecuario | CP70: Sí | CQ70: Sí | CR70: No | CS70: Sí | CT70: No | CU70: Sí | CV70: Sí | CW70: No | CX70: Sí | CY70: Sí | CZ70: No | DA70: No | DB70: No | DC70: Sí | DD70: Sí | DE70: No | DG70: 7 | DH70: 2 | DI70: 0 | DJ70: 1 | DK70: 1 | DL70: 7 | DM70: 7 | DN70: 7 | DO70: Sí | DP70: Pozo | DR70: Sí | DS70: Sí | DT70: May Jun Jul Ago Sep Oct | DU70: 0 | DV70: 0 | DW70: 0 | DX70: 0 | DY70: 1 | DZ70: 1 | EA70: 1 | EB70: 1 | EC70: 1 | ED70: 1 | EE70: 0 | EF70: 0 | EH70: No | EJ70: Lejanía, dentro del distritio | EK70: 76592246 | EN70: NO SE MIDIO LA PARCELA POR DIFICIL ACCESO QUEDA A TREITA MINUTOS DE LA VIVIENDA Y EL TERRENO SE ENCUENTRA EMPANTANADO | ES70: 22309109 | ET70: 12d0dc27-ae5b-4c88-9720-532da2f077ed | EU70: 46209.898 | EX70: submitted_via_web | EZ70: vBf6xt5iWdkTjghTeBLtbw | FB70: uuid:12d0dc27-ae5b-4c88-9720-532da2f077ed | FC70: 49
A71: ="V"&B71&"-R"&FC71 -> V3-R50 | B71: 3 | C71: 46209.413 | D71: 46209.432 | E71: 46208 | G71: Nancy | H71: Milagro | I71: 46209 | K71: AQUILEO FLORES MARTINEZ | L71: 48 | M71: Hombre | O71: San Miguel | P71: San Miguel Norte | Q71: San Gerardo | R71: SAN ANDRES | S71: LA VEGA | V71: GUADALUPE CASTRO REMOS | W71: Sí | Y71: Familiar del productor | AB71: Sí | AD71: Sí | AF71: Sí | AG71: 1 | AH71: 2 | AI71: 1 | AJ71: 40 | AK71: 0 | AL71: 20 | AM71: 0 | AN71: 0 | AV71: Sí | AW71: 2023 | AX71: No | AY71: No | AZ71: NO SABE | BA71: Sí | BB71: Regeneración artificial (plantación de árboles) | BC71: No | BD71: Sí | BE71: RECLIMA | BF71: 0 | BG71: 1 | BH71: 0 | BI71: 0 | BJ71: 0 | BK71: 0 | BL71: Aumentó algo | BM71: Sequías extremas | BO71: Ningún activo | BP71: 0 | BQ71: 0 | BR71: 0 | BS71: 0 | BT71: 0 | BU71: 0 | BV71: 0 | BW71: 0 | BX71: 0 | BY71: 0 | BZ71: 0 | CA71: 0 | CB71: 1 | CC71: Plagas o enfermedades Sequías | CD71: 1 | CE71: 1 | CF71: 0 | CG71: 0 | CH71: 0 | CI71: 0 | CJ71: 0 | CK71: 0 | CL71: 0 | CM71: 4 | CO71: Jornalero agropecuario | CP71: Sí | CQ71: Sí | CR71: Sí | CS71: Sí | CT71: No | CU71: No | CV71: No | CW71: No | CX71: Sí | CY71: No | CZ71: No | DA71: No | DB71: Sí | DC71: No | DD71: No | DE71: No | DG71: 1 | DH71: 7 | DI71: 2 | DJ71: 0 | DK71: 5 | DL71: 5 | DM71: 7 | DN71: 3 | DO71: No | EH71: No | EJ71: Lejanía, fuera del distritio | EK71: 77647613 | EN71: LA PARCELA ESTE ANO NO FUE ALQUILADA | ES71: 22309120 | ET71: 51688234-58e4-4e64-bf0a-a5493193b88d | EU71: 46209.917 | EX71: submitted_via_web | EZ71: vBf6xt5iWdkTjghTeBLtbw | FB71: uuid:51688234-58e4-4e64-bf0a-a5493193b88d | FC71: 50
A72: ="V"&B72&"-R"&FC72 -> V3-R51 | B72: 3 | C72: 46209.648 | D72: 46209.675 | E72: 46208 | G72: Juan | H72: Rigoberto | I72: 46208 | K72: JOSE TOMAS ZELAYA RIVAS | L72: 32 | M72: Hombre | O72: San Miguel | P72: San Miguel Norte | Q72: Ciudad Barrios | R72: GUANASTE | S72: SAN RAFAEL | T72: XL5929 | V72: JOSE ZELAYA | W72: Sí | Y72: Productor | AB72: Sí | AD72: No | AF72: Sí | AG72: 2 | AH72: 3 | AI72: 2 | AJ72: 56 | AK72: 24 | AL72: 7 | AM72: 120 | AN72: 0 | AV72: Sí | AW72: 2022 | AX72: No | AY72: No | AZ72: NO RECUERDA | BA72: No | BO72: Equipo de fumigación Bomba de agua | BP72: 0 | BQ72: 0 | BR72: 0 | BS72: 0 | BT72: 0 | BU72: 1 | BV72: 0 | BW72: 1 | BX72: 0 | BY72: 0 | BZ72: 0 | CA72: 0 | CB72: 0 | CC72: Lluvia o inundaciones | CD72: 0 | CE72: 0 | CF72: 1 | CG72: 0 | CH72: 0 | CI72: 0 | CJ72: 0 | CK72: 0 | CL72: 0 | CM72: 3 | CO72: Oficios varios (artesanías, carpintería, albañilería, etc.) | CP72: Sí | CQ72: No | CR72: Sí | CS72: Sí | CT72: No | CU72: No | CV72: No | CW72: No | CX72: Sí | CY72: No | CZ72: No | DA72: No | DB72: No | DC72: No | DD72: No | DE72: No | DG72: 7 | DH72: 7 | DI72: 0 | DJ72: 7 | DK72: 2 | DL72: 4 | DM72: 7 | DN72: 3 | DO72: Sí | DP72: Agua entubada | DR72: No | DS72: No | DT72: May Jun Jul Ago Sep Oct | DU72: 0 | DV72: 0 | DW72: 0 | DX72: 0 | DY72: 1 | DZ72: 1 | EA72: 1 | EB72: 1 | EC72: 1 | ED72: 1 | EE72: 0 | EF72: 0 | EH72: No | EJ72: Otra | EK72: 68564269 | EN72: NO SE MIDIO LA PARCELA PORQUE EL DUENO VENDIO EL TERRENO | ES72: 22309128 | ET72: 13b4cf16-a731-4cde-9363-c90360d3f627 | EU72: 46209.925 | EX72: submitted_via_web | EZ72: vBf6xt5iWdkTjghTeBLtbw | FB72: uuid:13b4cf16-a731-4cde-9363-c90360d3f627 | FC72: 51
A73: ="V"&B73&"-R"&FC73 -> V3-R52 | B73: 3 | C73: 46209.675 | D73: 46209.702 | E73: 46208 | G73: Juan | H73: Milagro | I73: 46200 | K73: RENE OTMARO RODAS BARRAZA | L73: 50 | M73: Hombre | O73: La Paz | P73: La Paz Oeste | Q73: San Luis Talpa | R73: SAN MARCOS JIBOA | S73: SAN MARCOS JIBOA | V73: RENE RODAS | W73: Sí | Y73: Productor | AB73: Sí | AD73: Sí | AF73: Sí | AG73: 2 | AH73: 5 | AI73: 2 | AJ73: 0 | AK73: 1000 | AL73: 1000 | AM73: 1600 | AN73: 1000 | AV73: Sí | AW73: 2025 | AX73: Sí | AY73: Sí | AZ73: NO RECUERDA | BA73: No | BO73: Rastra Bomba de agua | BP73: 0 | BQ73: 1 | BR73: 0 | BS73: 0 | BT73: 0 | BU73: 0 | BV73: 0 | BW73: 1 | BX73: 0 | BY73: 0 | BZ73: 0 | CA73: 0 | CB73: 0 | CC73: Plagas o enfermedades | CD73: 1 | CE73: 0 | CF73: 0 | CG73: 0 | CH73: 0 | CI73: 0 | CJ73: 0 | CK73: 0 | CL73: 0 | CM73: 4 | CO73: Producción agropecuaria | CP73: No | CQ73: No | CR73: No | CS73: No | CT73: No | CU73: No | CV73: No | CW73: No | CX73: Sí | CY73: No | CZ73: No | DA73: No | DB73: No | DC73: No | DD73: No | DE73: No | DG73: 7 | DH73: 6 | DI73: 7 | DJ73: 4 | DK73: 4 | DL73: 3 | DM73: 7 | DN73: 3 | DO73: Sí | DP73: Pozo | DR73: Sí | DS73: Sí | DT73: May Jun Jul Ago Sep Oct | DU73: 0 | DV73: 0 | DW73: 0 | DX73: 0 | DY73: 1 | DZ73: 1 | EA73: 1 | EB73: 1 | EC73: 1 | ED73: 1 | EE73: 0 | EF73: 0 | EH73: No | EJ73: Otra | EK73: 70959931 | EN73: EL DUENO DEL TERRENO NO AUTORIZO REALIZAR LAS MEDIDAS | ES73: 22309190 | ET73: 28468273-3388-409c-82df-bd56ac300c63 | EU73: 46209.952 | EX73: submitted_via_web | EZ73: vBf6xt5iWdkTjghTeBLtbw | FB73: uuid:28468273-3388-409c-82df-bd56ac300c63 | FC73: 52
A74: ="V"&B74&"-R"&FC74 -> V3-R53 | B74: 3 | C74: 46209.432 | D74: 46210.247 | E74: 46208 | G74: Nancy | H74: Milagro | I74: 46209 | K74: ROSA ANGELICA CEDILLOS | L74: 56 | M74: Mujer | O74: San Miguel | P74: San Miguel Norte | Q74: San Gerardo | R74: LA JOYA | S74: COLORADO | T74: VAOCHODOSTRESUNO | V74: MARCOS ANTONIO VILLANUEVA CEDILLA | W74: Sí | Y74: Familiar del productor | AB74: Sí | AD74: Sí | AF74: Sí | AG74: 1 | AH74: 1 | AI74: 1 | AJ74: 0 | AK74: 0 | AL74: 0 | AM74: 20 | AN74: 0 | AV74: Sí | AW74: 2023 | AX74: Sí | AY74: No | AZ74: NO SABE | BA74: No | BO74: Ningún activo | BP74: 0 | BQ74: 0 | BR74: 0 | BS74: 0 | BT74: 0 | BU74: 0 | BV74: 0 | BW74: 0 | BX74: 0 | BY74: 0 | BZ74: 0 | CA74: 0 | CB74: 1 | CC74: Plagas o enfermedades Sequías | CD74: 1 | CE74: 1 | CF74: 0 | CG74: 0 | CH74: 0 | CI74: 0 | CJ74: 0 | CK74: 0 | CL74: 0 | CM74: 5 | CO74: Servicios domésticos | CP74: Sí | CQ74: Sí | CR74: Sí | CS74: Sí | CT74: No | CU74: No | CV74: No | CW74: No | CX74: Sí | CY74: No | CZ74: No | DA74: No | DB74: No | DC74: No | DD74: No | DE74: No | DG74: 7 | DH74: 7 | DI74: 2 | DJ74: 2 | DK74: 5 | DL74: 4 | DM74: 4 | DN74: 3 | DO74: Sí | DP74: Nacimiento de agua | DR74: Sí | DS74: Sí | DT74: Ene Feb Mar Abr May Jun Jul Ago Sep Oct Nov Dic | DU74: 1 | DV74: 1 | DW74: 1 | DX74: 1 | DY74: 1 | DZ74: 1 | EA74: 1 | EB74: 1 | EC74: 1 | ED74: 1 | EE74: 1 | EF74: 1 | EH74: Sí | EK74: 74540649 | EN74: SE ENCUESTO AL YERNO PORQUE ELLA NO ESTABA | ES74: 22316660 | ET74: ab7e5e5b-b922-4882-a187-ec829d08d9b8 | EU74: 46210.497 | EX74: submitted_via_web | EZ74: vBf6xt5iWdkTjghTeBLtbw | FB74: uuid:ab7e5e5b-b922-4882-a187-ec829d08d9b8 | FC74: 53
A75: ="V"&B75&"-R"&FC75 -> V3-R54 | B75: 3 | C75: 46203.427 | D75: 46210.54 | E75: 46202 | G75: Wendy | H75: Rigoberto | I75: 46203 | K75: REYES JOEL PORTILLO CRUZ | L75: 46 | M75: Mujer | O75: La Unión | P75: La Unión Norte | R75: CONCEPCION DE ORIENTE | S75: CANTON GUERIPE | V75: MARITZA DE PORTILLO | W75: Sí | Y75: Familiar del productor | AB75: Sí | AD75: No | AF75: Sí | AG75: 6 | AH75: 1 | AI75: 2 | AV75: Sí | AW75: 2022 | AX75: Sí | AY75: No | AZ75: NO RECUERDA NOMBRE | BA75: Sí | BB75: Regeneración artificial (plantación de árboles) | BC75: No | BD75: Sí | BE75: RECLIMA | BF75: 0 | BG75: 1 | BH75: 0 | BI75: 0 | BJ75: 0 | BK75: 0 | BL75: Disminuyó mucho | BM75: Sequías extremas | BO75: Bomba de agua | BP75: 0 | BQ75: 0 | BR75: 0 | BS75: 0 | BT75: 0 | BU75: 0 | BV75: 0 | BW75: 1 | BX75: 0 | BY75: 0 | BZ75: 0 | CA75: 0 | CB75: 0 | CC75: Sequías | CD75: 0 | CE75: 1 | CF75: 0 | CG75: 0 | CH75: 0 | CI75: 0 | CJ75: 0 | CK75: 0 | CL75: 0 | CM75: 4 | CO75: Jornalero agropecuario | CP75: Sí | CQ75: No | CR75: No | CS75: No | CT75: No | CU75: No | CV75: No | CW75: No | CX75: Sí | CY75: No | CZ75: No | DA75: No | DB75: No | DC75: No | DD75: No | DE75: No | DG75: 7 | DH75: 3 | DI75: 4 | DJ75: 3 | DK75: 2 | DL75: 4 | DM75: 2 | DN75: 2 | DO75: Sí | DP75: Pozo | DR75: No | DS75: No | DT75: Ago | DU75: 0 | DV75: 0 | DW75: 0 | DX75: 0 | DY75: 0 | DZ75: 0 | EA75: 0 | EB75: 1 | EC75: 0 | ED75: 0 | EE75: 0 | EF75: 0 | EH75: Sí | EI75: 13.765766 -87.764125 0 2000;13.765855 -87.763714 0 0;13.766116 -87.76366 0 0;13.76623 -87.763885 0 0;13.766319 -87.764186 0 0;13.766371 -87.764379 0 0;13.766058 -87.764695 0 0;13.765545 -87.764797 0 0;13.765088 -87.764914 0 0;13.764388 -87.764636 0 0;13.763873 -87.76429 0 0;13.764261 -87.76396 0 0;13.76487 -87.763588 0 0;13.765303 -87.763542 0 0;13.765615 -87.763121 0 0;13.766011 -87.762635 0 0;13.766678 -87.762292 0 0;13.766835 -87.763156 0 0;13.767085 -87.76381 0 0;13.766874 -87.76403 0 0;13.767517 -87.764068 0 0;13.767012 -87.764368 0 0;13.766194 -87.765393 0 0;13.764409 -87.766551 0 0;13.764039 -87.765428 0 0;13.761207 -87.764497 0 0;13.763458 -87.76292 0 0;13.765766 -87.764125 0 2000 | EN75: NINGUNO | ES75: 22322202 | ET75: 69a2aac8-f423-420b-8910-119727b210ae | EU75: 46210.79 | EX75: submitted_via_web | EZ75: vBf6xt5iWdkTjghTeBLtbw | FB75: uuid:69a2aac8-f423-420b-8910-119727b210ae | FC75: 54
A76: ="V"&B76&"-R"&FC76 -> V3-R55 | B76: 3 | C76: 46210.54 | D76: 46210.54 | E76: 46209 | ES76: 22322203 | ET76: 29bd7049-e92b-4e49-aa76-b04c7c4061da | EU76: 46210.79 | EX76: submitted_via_web | EZ76: vBf6xt5iWdkTjghTeBLtbw | FB76: uuid:29bd7049-e92b-4e49-aa76-b04c7c4061da | FC76: 55
A77: ="V"&B77&"-R"&FC77 -> V3-R56 | B77: 3 | C77: 46208.4 | D77: 46210.688 | E77: 46207 | G77: Iván | H77: Milagro | I77: 46208 | K77: MARIXA YESENIA VIGIL GOMEZ | L77: 43 | M77: Mujer | O77: Usulután | P77: Usulután Norte | Q77: Jucuapa | R77: LLANO GRANDE | S77: EL CENTRO | T77: TL-528-0 | V77: MARIXA VIGIL | W77: Sí | Y77: Productor | AB77: Sí | AD77: No | AF77: Sí | AG77: 1 | AH77: 2 | AI77: 1 | AJ77: 50 | AK77: 100 | AL77: 0 | AM77: 0 | AN77: 400 | AV77: Sí | AW77: 2025 | AX77: Sí | AY77: Sí | AZ77: NATALI GRANADOS | BA77: Sí | BB77: Regeneración artificial (plantación de árboles) | BC77: No | BD77: Sí | BE77: RECLIMA | BF77: 0 | BG77: 1 | BH77: 0 | BI77: 0 | BJ77: 0 | BK77: 0 | BL77: Aumentó algo | BM77: Sequías extremas | BO77: Bomba de agua | BP77: 0 | BQ77: 0 | BR77: 0 | BS77: 0 | BT77: 0 | BU77: 0 | BV77: 0 | BW77: 1 | BX77: 0 | BY77: 0 | BZ77: 0 | CA77: 0 | CB77: 0 | CC77: Plagas o enfermedades Sequías Vientos fuertes | CD77: 1 | CE77: 1 | CF77: 0 | CG77: 0 | CH77: 1 | CI77: 0 | CJ77: 0 | CK77: 0 | CL77: 0 | CM77: 5 | CO77: Jornalero agropecuario | CP77: Sí | CQ77: Sí | CR77: Sí | CS77: Sí | CT77: No | CU77: Sí | CV77: No | CW77: No | CX77: Sí | CY77: No | CZ77: Sí | DA77: No | DB77: No | DC77: Sí | DD77: No | DE77: No | DG77: 7 | DH77: 7 | DI77: 3 | DJ77: 1 | DK77: 3 | DL77: 1 | DM77: 7 | DN77: 7 | DO77: Sí | DP77: Agua entubada | DR77: Sí | DS77: Sí | DT77: Ene Feb Mar Abr May Jun Jul Ago Sep Oct Nov Dic | DU77: 1 | DV77: 1 | DW77: 1 | DX77: 1 | DY77: 1 | DZ77: 1 | EA77: 1 | EB77: 1 | EC77: 1 | ED77: 1 | EE77: 1 | EF77: 1 | EH77: Sí | EK77: 73330522 | EN77: PARCELA POR APLICACION | ES77: 22322973 | ET77: f61b8953-17a7-4567-b049-da54c285b823 | EU77: 46210.938 | EX77: submitted_via_web | EZ77: vBf6xt5iWdkTjghTeBLtbw | FB77: uuid:f61b8953-17a7-4567-b049-da54c285b823 | FC77: 56
A78: ="V"&B78&"-R"&FC78 -> V3-R57 | B78: 3 | C78: 46208.36 | D78: 46210.7 | E78: 46207 | G78: Iván | H78: Milagro | I78: 46208 | K78: ODALIS ESMERALDA ALVARADO DE LAINEZ | L78: 43 | M78: Mujer | O78: Usulután | P78: Usulután Norte | Q78: Jucuapa | R78: EL AMATON | S78: EL AMATON | T78: FD-938-1 | V78: ODALIS ALVARADO | W78: Sí | Y78: Productor | AB78: Sí | AD78: Sí | AF78: Sí | AG78: 1 | AH78: 2 | AI78: 1 | AJ78: 0 | AK78: 10 | AL78: 0 | AM78: 0 | AN78: 0 | AV78: Sí | AW78: 2023 | AX78: Sí | AY78: Sí | AZ78: MARIXA | BA78: No | BO78: Ningún activo | BP78: 0 | BQ78: 0 | BR78: 0 | BS78: 0 | BT78: 0 | BU78: 0 | BV78: 0 | BW78: 0 | BX78: 0 | BY78: 0 | BZ78: 0 | CA78: 0 | CB78: 1 | CC78: Plagas o enfermedades Sequías | CD78: 1 | CE78: 1 | CF78: 0 | CG78: 0 | CH78: 0 | CI78: 0 | CJ78: 0 | CK78: 0 | CL78: 0 | CM78: 6 | CO78: Producción agropecuaria | CP78: No | CQ78: No | CR78: No | CS78: Sí | CT78: No | CU78: Sí | CV78: No | CW78: No | CX78: Sí | CY78: No | CZ78: No | DA78: No | DB78: No | DC78: No | DD78: No | DE78: No | DG78: 7 | DH78: 7 | DI78: 4 | DJ78: 7 | DK78: 5 | DL78: 4 | DM78: 7 | DN78: 7 | DO78: Sí | DP78: Agua entubada | DR78: Sí | DS78: No | DT78: Ago Sep Oct Nov Dic | DU78: 0 | DV78: 0 | DW78: 0 | DX78: 0 | DY78: 0 | DZ78: 0 | EA78: 0 | EB78: 1 | EC78: 1 | ED78: 1 | EE78: 1 | EF78: 1 | EH78: No | EJ78: Productor se rehuso | EK78: 72506461 | EN78: SE TERMINO POR TELEFONO POR QUR LA PRODUCTORA NO TENIA MAS TIEMPO POR LO CUAL NO SE REGISTRO LA PARCELA | ES78: 22322993 | ET78: 9bcb3977-30fe-4140-9c6c-f3e0b79b285e | EU78: 46210.95 | EX78: submitted_via_web | EZ78: vBf6xt5iWdkTjghTeBLtbw | FB78: uuid:9bcb3977-30fe-4140-9c6c-f3e0b79b285e | FC78: 57
A79: ="V"&B79&"-R"&FC79 -> V3-R58 | B79: 3 | C79: 46208.401 | D79: 46210.839 | E79: 46207 | G79: Zaira | H79: Milagro | I79: 46208 | K79: MILTON ANTONIO GARCIA MARTINEZ | L79: 34 | M79: Hombre | O79: Usulután | P79: Usulután Norte | Q79: Jucuapa | R79: LLANO GRANDE | S79: CANCHA EL INVASOR | T79: RL2626 | V79: IDALIA | W79: Sí | Y79: Familiar del productor | AB79: Sí | AD79: No | AF79: Sí | AG79: 1 | AH79: 2 | AI79: 1 | AJ79: 90 | AK79: 0 | AL79: 0 | AM79: 100 | AN79: 400 | AV79: No | AW79: 2024 | AX79: Sí | AY79: No | AZ79: NO SABE | BA79: Sí | BB79: Regeneración artificial (plantación de árboles) | BC79: No | BD79: Sí | BE79: Cooperativa | BF79: 0 | BG79: 0 | BH79: 0 | BI79: 0 | BJ79: 0 | BK79: 1 | BL79: Sin cambió | BM79: Sequías extremas | BO79: Bomba de agua Camioneta o camión | BP79: 0 | BQ79: 0 | BR79: 0 | BS79: 0 | BT79: 0 | BU79: 0 | BV79: 0 | BW79: 1 | BX79: 0 | BY79: 0 | BZ79: 1 | CA79: 0 | CB79: 0 | CC79: Lluvia o inundaciones | CD79: 0 | CE79: 0 | CF79: 1 | CG79: 0 | CH79: 0 | CI79: 0 | CJ79: 0 | CK79: 0 | CL79: 0 | CM79: 3 | CO79: Trabajo asalariado/permanente (sueldo regular) | CP79: Sí | CQ79: Sí | CR79: No | CS79: Sí | CT79: No | CU79: Sí | CV79: No | CW79: No | CX79: Sí | CY79: No | CZ79: No | DA79: No | DB79: No | DC79: No | DD79: No | DE79: No | DG79: 7 | DH79: 7 | DI79: 4 | DJ79: 4 | DK79: 7 | DL79: 2 | DM79: 7 | DN79: 3 | DO79: Sí | DP79: Pozo | DR79: Sí | DS79: Sí | DT79: Ene Feb Mar Abr May Jun Jul Ago Sep Oct Nov Dic | DU79: 1 | DV79: 1 | DW79: 1 | DX79: 1 | DY79: 1 | DZ79: 1 | EA79: 1 | EB79: 1 | EC79: 1 | ED79: 1 | EE79: 1 | EF79: 1 | EH79: No | EJ79: Lejanía, dentro del distritio | EK79: 79986275 | ES79: 22323662 | ET79: 419b2e78-e89b-4a2c-8524-73739e10cf44 | EU79: 46211.089 | EX79: submitted_via_web | EZ79: vBf6xt5iWdkTjghTeBLtbw | FB79: uuid:419b2e78-e89b-4a2c-8524-73739e10cf44 | FC79: 58
A80: ="V"&B80&"-R"&FC80 -> V3-R59 | B80: 3 | C80: 46202.595 | D80: 46210.846 | E80: 46201 | G80: Iván | H80: Milagro | I80: 46202 | K80: MARIA LUDEVINA MONTANO ROJAS | L80: 52 | M80: Mujer | O80: Usulután | P80: Usulután Oeste | Q80: San Francisco Javier | R80: JOBALHORNO | V80: MARIA ROJAS | W80: Sí | Y80: Productor | AB80: Sí | AD80: Sí | AF80: Sí | AG80: 1 | AH80: 2 | AI80: 1 | AJ80: 80 | AK80: 150 | AL80: 75 | AM80: 150 | AN80: 0 | AO80: Bovinos (vacas, terneros, novillos, bueyes, toros) Aves (gallinas, pollos, gallos) | AP80: 1 | AQ80: 0 | AR80: 1 | AS80: 0 | AT80: 0 | AV80: Sí | AW80: 2025 | AX80: No | AY80: No | AZ80: NO SABE | BA80: No | BO80: Ningún activo | BP80: 0 | BQ80: 0 | BR80: 0 | BS80: 0 | BT80: 0 | BU80: 0 | BV80: 0 | BW80: 0 | BX80: 0 | BY80: 0 | BZ80: 0 | CA80: 0 | CB80: 1 | CC80: Plagas o enfermedades Sequías Lluvia o inundaciones Vientos fuertes | CD80: 1 | CE80: 1 | CF80: 1 | CG80: 0 | CH80: 1 | CI80: 0 | CJ80: 0 | CK80: 0 | CL80: 0 | CM80: 4 | CO80: Oficios varios (artesanías, carpintería, albañilería, etc.) | CP80: Sí | CQ80: No | CR80: Sí | CS80: Sí | CT80: Sí | CU80: Sí | CV80: Sí | CW80: Sí | CX80: Sí | CY80: Sí | CZ80: Sí | DA80: No | DB80: Sí | DC80: Sí | DD80: Sí | DE80: No | DG80: 7 | DH80: 7 | DI80: 6 | DJ80: 4 | DK80: 2 | DL80: 7 | DM80: 7 | DN80: 7 | DO80: Sí | DP80: Agua entubada | DR80: Sí | DS80: Sí | DT80: Ene Feb Mar Abr May Jun Jul Ago Sep Oct Nov Dic | DU80: 1 | DV80: 1 | DW80: 1 | DX80: 1 | DY80: 1 | DZ80: 1 | EA80: 1 | EB80: 1 | EC80: 1 | ED80: 1 | EE80: 1 | EF80: 1 | EH80: Sí | EI80: 13.395932 -88.598213 185.70001220703125 3.0999999046325684;13.39596 -88.598192 185.70001220703125 114.23600006103516;13.396227 -88.597204 185.70001220703125 7;13.396223 -88.597217 185.70001220703125 103.58799743652344;13.395932 -88.598213 185.70001220703125 3.0999999046325684 | EK80: 74584053 | ES80: 22323717 | ET80: 9ce26902-3b04-4b37-b208-9cd64bc34ca1 | EU80: 46211.096 | EX80: submitted_via_web | EZ80: vBf6xt5iWdkTjghTeBLtbw | FB80: uuid:9ce26902-3b04-4b37-b208-9cd64bc34ca1 | FC80: 59
A81: ="V"&B81&"-R"&FC81 -> V3-R60 | B81: 3 | C81: 46202.62 | D81: 46210.85 | E81: 46201 | G81: Iván | H81: Milagro | I81: 46202 | K81: MIQUEL ANTONIO ZELAYA MIRANDA | L81: 32 | M81: Hombre | O81: Usulután | P81: Usulután Oeste | Q81: Jiquilisco | R81: CABO NEGRO | S81: EL MARANON | V81: KAINA BEATRIZ TENORIO DE ZELAYA | W81: Sí | Y81: Familiar del productor | AB81: Sí | AD81: Sí | AF81: Sí | AG81: 2 | AH81: 2 | AI81: 2 | AJ81: 35 | AK81: 0 | AL81: 0 | AM81: 0 | AN81: 700 | AV81: Sí | AW81: 2025 | AX81: Sí | AY81: Sí | AZ81: NO SE ACUERDA | BA81: Sí | BB81: Regeneración artificial (plantación de árboles) | BC81: No | BD81: Sí | BE81: Entidad de gobierno central | BF81: 1 | BG81: 0 | BH81: 0 | BI81: 0 | BJ81: 0 | BK81: 0 | BL81: Sin cambió | BM81: Sequías extremas | BO81: Ningún activo | BP81: 0 | BQ81: 0 | BR81: 0 | BS81: 0 | BT81: 0 | BU81: 0 | BV81: 0 | BW81: 0 | BX81: 0 | BY81: 0 | BZ81: 0 | CA81: 0 | CB81: 1 | CC81: Vientos fuertes | CD81: 0 | CE81: 0 | CF81: 0 | CG81: 0 | CH81: 1 | CI81: 0 | CJ81: 0 | CK81: 0 | CL81: 0 | CM81: 4 | CO81: Jornalero agropecuario | CP81: Sí | CQ81: No | CR81: No | CS81: Sí | CT81: No | CU81: No | CV81: No | CW81: No | CX81: Sí | CY81: No | CZ81: No | DA81: No | DB81: No | DC81: No | DD81: No | DE81: No | DG81: 7 | DH81: 7 | DI81: 7 | DJ81: 4 | DK81: 1 | DL81: 5 | DM81: 7 | DN81: 7 | DO81: Sí | DP81: Comprada | DR81: No | DS81: No | DT81: Ene Feb Mar Abr May Jun Jul Ago Sep Oct Nov Dic | DU81: 1 | DV81: 1 | DW81: 1 | DX81: 1 | DY81: 1 | DZ81: 1 | EA81: 1 | EB81: 1 | EC81: 1 | ED81: 1 | EE81: 1 | EF81: 1 | EH81: Sí | EK81: 77355822 | EN81: POLIGONO EN APLICACION SUPERVISOR A | ES81: 22323767 | ET81: 09bcab2a-617b-4c7f-8dc9-3dc20c0b5022 | EU81: 46211.1 | EX81: submitted_via_web | EZ81: vBf6xt5iWdkTjghTeBLtbw | FB81: uuid:09bcab2a-617b-4c7f-8dc9-3dc20c0b5022 | FC81: 60
A82: ="V"&B82&"-R"&FC82 -> V3-R61 | B82: 3 | C82: 46203.373 | D82: 46210.855 | E82: 46202 | G82: Iván | H82: Milagro | I82: 46203 | K82: JOSE EVER BAYONA MALTEZ | L82: 52 | M82: Hombre | O82: La Unión | P82: La Unión Norte | Q82: Bolivar | R82: LA PAZ | S82: LA RINCONADA | T82: VM-173-5 | V82: JOSE MALTEZ | W82: Sí | Y82: Productor | AB82: Sí | AD82: No | AF82: Sí | AG82: 1 | AH82: 1 | AI82: 1 | AJ82: 64 | AK82: 240 | AL82: 150 | AM82: 800 | AN82: 0 | AV82: Sí | AW82: 2023 | AX82: Sí | AY82: No | AZ82: JOSE BAYONA | BA82: Sí | BB82: Regeneración artificial (plantación de árboles) | BC82: No | BD82: Sí | BE82: RECLIMA | BF82: 0 | BG82: 1 | BH82: 0 | BI82: 0 | BJ82: 0 | BK82: 0 | BL82: Aumentó algo | BM82: Sequías extremas | BO82: Ningún activo | BP82: 0 | BQ82: 0 | BR82: 0 | BS82: 0 | BT82: 0 | BU82: 0 | BV82: 0 | BW82: 0 | BX82: 0 | BY82: 0 | BZ82: 0 | CA82: 0 | CB82: 1 | CC82: Sequías Vientos fuertes | CD82: 0 | CE82: 1 | CF82: 0 | CG82: 0 | CH82: 1 | CI82: 0 | CJ82: 0 | CK82: 0 | CL82: 0 | CM82: 4 | CO82: Oficios varios (artesanías, carpintería, albañilería, etc.) | CP82: Sí | CQ82: No | CR82: No | CS82: No | CT82: No | CU82: No | CV82: Sí | CW82: Sí | CX82: Sí | CY82: No | CZ82: No | DA82: Sí | DB82: No | DC82: Sí | DD82: Sí | DE82: Sí | DG82: 7 | DH82: 7 | DI82: 7 | DJ82: 1 | DK82: 5 | DL82: 2 | DM82: 7 | DN82: 7 | DO82: Sí | DP82: Pozo | DR82: Sí | DS82: No | DT82: Jun Jul Ago Sep Oct Nov Dic | DU82: 0 | DV82: 0 | DW82: 0 | DX82: 0 | DY82: 0 | DZ82: 1 | EA82: 1 | EB82: 1 | EC82: 1 | ED82: 1 | EE82: 1 | EF82: 1 | EH82: Sí | EK82: 78907981 | EN82: POLIGONO APARTE | ES82: 22323812 | ET82: 1de99b7a-0a79-4ee0-9feb-573f0d20f563 | EU82: 46211.105 | EX82: submitted_via_web | EZ82: vBf6xt5iWdkTjghTeBLtbw | FB82: uuid:1de99b7a-0a79-4ee0-9feb-573f0d20f563 | FC82: 61
A83: ="V"&B83&"-R"&FC83 -> V3-R62 | B83: 3 | C83: 46203.466 | D83: 46210.859 | E83: 46202 | G83: Iván | H83: Milagro | I83: 46203 | K83: EDAR OMAR RAMIREZ GERRA | L83: 58 | M83: Hombre | O83: La Unión | P83: La Unión Norte | Q83: Bolivar | R83: EL RINCONAR | S83: RAMIREZ | T83: JA-407-3 | V83: EDAR RAMIREZ | W83: Sí | Y83: Productor | AB83: Sí | AD83: No | AF83: Sí | AG83: 3 | AH83: 2 | AI83: 2 | AJ83: 0 | AK83: 1020 | AL83: 216 | AM83: 250 | AN83: 0 | AO83: Bovinos (vacas, terneros, novillos, bueyes, toros) Aves (gallinas, pollos, gallos) | AP83: 1 | AQ83: 0 | AR83: 1 | AS83: 0 | AT83: 0 | AV83: Sí | AW83: 2023 | AX83: No | AY83: No | AZ83: NO RECUERDO | BA83: No | BO83: Equipo de fumigación Bomba de agua Camioneta o camión Bodega | BP83: 0 | BQ83: 0 | BR83: 0 | BS83: 0 | BT83: 0 | BU83: 1 | BV83: 0 | BW83: 1 | BX83: 0 | BY83: 0 | BZ83: 1 | CA83: 1 | CB83: 0 | CC83: No sufrió pérdidas de cosecha o animales | CD83: 0 | CE83: 0 | CF83: 0 | CG83: 0 | CH83: 0 | CI83: 0 | CJ83: 0 | CK83: 0 | CL83: 1 | CM83: 3 | CO83: Producción agropecuaria | CP83: No | CQ83: No | CR83: Sí | CS83: No | CT83: No | CU83: No | CV83: No | CW83: No | CX83: Sí | CY83: No | CZ83: No | DA83: No | DB83: No | DC83: No | DD83: No | DE83: No | DG83: 7 | DH83: 7 | DI83: 7 | DJ83: 1 | DK83: 7 | DL83: 5 | DM83: 7 | DN83: 7 | DO83: Sí | DP83: Pozo | DR83: Sí | DS83: Sí | DT83: Ene Feb Mar Abr May Jun Jul Ago Sep Oct Nov Dic | DU83: 1 | DV83: 1 | DW83: 1 | DX83: 1 | DY83: 1 | DZ83: 1 | EA83: 1 | EB83: 1 | EC83: 1 | ED83: 1 | EE83: 1 | EF83: 1 | EH83: Sí | EK83: 72305843 | EN83: PARCELA EN APLICACION | ES83: 22323854 | ET83: 44c47a6d-5f1f-457f-8b16-9842a8e48b78 | EU83: 46211.109 | EX83: submitted_via_web | EZ83: vBf6xt5iWdkTjghTeBLtbw | FB83: uuid:44c47a6d-5f1f-457f-8b16-9842a8e48b78 | FC83: 62
A84: ="V"&B84&"-R"&FC84 -> V3-R63 | B84: 3 | C84: 46210.846 | D84: 46210.869 | E84: 46209 | G84: Iván | H84: Milagro | I84: 46199 | K84: GERSON ANTONIO PEREZ FUNES | L84: 25 | M84: Hombre | O84: La Paz | P84: La Paz Centro | Q84: El Rosario | R84: EL TUNAL | S84: PUENTE VIEJO | T84: HV-675-4 | V84: GERSON PEREZ | W84: Sí | Y84: Productor | AB84: Sí | AD84: No sabe / no responde | AF84: No | EH84: No | EJ84: Productor se rehuso | EK84: 60776103 | EN84: EL PRODUCTOR COMENTO QUE LE DIERON LS HERRAMIENTAS PERO QUE YA O COSECHABA POR QUE TENIA PROBLEMAS DE SALUD | ES84: 22324022 | ET84: b87f1bd5-0227-4d42-9e40-c5e6cbce972a | EU84: 46211.119 | EX84: submitted_via_web | EZ84: vBf6xt5iWdkTjghTeBLtbw | FB84: uuid:b87f1bd5-0227-4d42-9e40-c5e6cbce972a | FC84: 63
A85: ="V"&B85&"-R"&FC85 -> V3-R64 | B85: 3 | C85: 46211.638 | D85: 46211.694 | E85: 46210 | G85: Nancy | H85: Milagro | I85: 46211 | K85: CLAUDIA ELIZABETH GAMERO SALAZAR | L85: 37 | M85: Mujer | O85: Ahuachapán | P85: Ahuachapán Norte | Q85: Turín | R85: EL JOBO | S85: LINEA FERREA | T85: TW-528-5 | V85: LAZARO GAMERO | W85: Sí | Y85: Familiar del productor | AB85: Sí | AD85: No | AF85: Sí | AG85: 1 | AH85: 2 | AI85: 1 | AJ85: 53 | AK85: 125 | AL85: 9999 | AM85: 60 | AN85: 0 | AV85: Sí | AW85: 2023 | AX85: No | AY85: No | AZ85: NO SABE | BA85: No | BO85: Equipo de fumigación | BP85: 0 | BQ85: 0 | BR85: 0 | BS85: 0 | BT85: 0 | BU85: 1 | BV85: 0 | BW85: 0 | BX85: 0 | BY85: 0 | BZ85: 0 | CA85: 0 | CB85: 0 | CC85: Sequías | CD85: 0 | CE85: 1 | CF85: 0 | CG85: 0 | CH85: 0 | CI85: 0 | CJ85: 0 | CK85: 0 | CL85: 0 | CM85: 3 | CO85: Producción agropecuaria | CP85: No | CQ85: No | CR85: No | CS85: No | CT85: No | CU85: No | CV85: No | CW85: No | CX85: Sí | CY85: No | CZ85: No | DA85: No | DB85: No | DC85: No | DD85: No | DE85: No | DG85: 7 | DH85: 7 | DI85: 3 | DJ85: 2 | DK85: 7 | DL85: 7 | DM85: 7 | DN85: 7 | DO85: Sí | DP85: Pozo | DR85: No | DS85: Sí | DT85: Ene Feb Mar Abr May Jun Jul Ago Sep Oct Nov Dic | DU85: 1 | DV85: 1 | DW85: 1 | DX85: 1 | DY85: 1 | DZ85: 1 | EA85: 1 | EB85: 1 | EC85: 1 | ED85: 1 | EE85: 1 | EF85: 1 | EH85: No | EJ85: Productor se rehuso | EK85: 79467657 | EN85: NO SE ENCONTRO A LA BENEFICIARIA SE ENTREVISTO AL HERMANO NO QUISO QUE SE LE MIDIERA LA PARCELA PORQUE ES ALQUILADA | ES85: 22338427 | ET85: 41382501-0d59-43d5-aa34-0c91d1b0bfb2 | EU85: 46211.944 | EX85: submitted_via_web | EZ85: vBf6xt5iWdkTjghTeBLtbw | FB85: uuid:41382501-0d59-43d5-aa34-0c91d1b0bfb2 | FC85: 64
A86: ="V"&B86&"-R"&FC86 -> V3-R65 | B86: 3 | C86: 46210.841 | D86: 46212.838 | E86: 46209 | G86: Zaira | H86: Milagro | I86: 46202 | K86: ROSA IRIS LOPEZ CORTEZ | L86: 49 | M86: Mujer | O86: Usulután | P86: Usulután Oeste | Q86: Jiquilisco | R86: CANTON LA NORIA | S86: LA NORIA | T86: EM-810-4 | V86: ROSA LOPEZ | W86: Sí | Y86: Productor | AB86: Sí | AD86: No | AF86: Sí | AG86: 1 | AH86: 1 | AI86: 1 | AJ86: 75 | AK86: 0 | AL86: 75 | AM86: 0 | AN86: 500 | AV86: Sí | AW86: 2024 | AX86: Sí | AY86: Sí | AZ86: MAIRA VIGIL | BA86: Sí | BB86: Regeneración artificial (plantación de árboles) | BC86: No | BD86: Sí | BE86: RECLIMA | BF86: 0 | BG86: 1 | BH86: 0 | BI86: 0 | BJ86: 0 | BK86: 0 | BL86: Sin cambió | BM86: Sequías extremas | BO86: Equipo de fumigación Tanque para almacenamiento de agua | BP86: 0 | BQ86: 0 | BR86: 0 | BS86: 0 | BT86: 0 | BU86: 1 | BV86: 1 | BW86: 0 | BX86: 0 | BY86: 0 | BZ86: 0 | CA86: 0 | CB86: 0 | CC86: Lluvia o inundaciones Vientos fuertes | CD86: 0 | CE86: 0 | CF86: 1 | CG86: 0 | CH86: 1 | CI86: 0 | CJ86: 0 | CK86: 0 | CL86: 0 | CM86: 5 | CO86: Producción agropecuaria | CP86: Sí | CQ86: Sí | CR86: Sí | CS86: No | CT86: Sí | CU86: Sí | CV86: Sí | CW86: No | CX86: Sí | CY86: No | CZ86: Sí | DA86: No | DB86: No | DC86: No | DD86: No | DE86: No | DG86: 6 | DH86: 0 | DI86: 0 | DJ86: 2 | DK86: 7 | DL86: 7 | DM86: 7 | DN86: 7 | DO86: Sí | DP86: Agua entubada | DR86: Sí | DS86: Sí | DT86: Ene Feb Mar Abr May Jun Jul Ago Sep Oct Nov Dic | DU86: 1 | DV86: 1 | DW86: 1 | DX86: 1 | DY86: 1 | DZ86: 1 | EA86: 1 | EB86: 1 | EC86: 1 | ED86: 1 | EE86: 1 | EF86: 1 | EH86: No | EJ86: Otra | EK86: 76080188 | ES86: 22355734 | ET86: 267eb5e0-4d02-4f8a-985c-fb3dd9275a0e | EU86: 46213.088 | EX86: submitted_via_web | EZ86: vBf6xt5iWdkTjghTeBLtbw | FB86: uuid:267eb5e0-4d02-4f8a-985c-fb3dd9275a0e | FC86: 65
A87: ="V"&B87&"-R"&FC87 -> V3-R66 | B87: 3 | C87: 46214.329 | D87: 46214.412 | E87: 46213 | G87: Nancy | H87: Milagro | I87: 46214 | K87: CANDIDA GARCIA DE MALDINERA | L87: 55 | M87: Mujer | O87: Ahuachapán | P87: Ahuachapán Sur | Q87: Guaymango | R87: SAN ANDRES ZONA DOS | S87: CASERIO LOS VASQUEZ | T87: NM-902-6 | V87: CANDIDA GARCIA | W87: Sí | Y87: Productor | AB87: Sí | AD87: Sí | AF87: Sí | AG87: 1 | AH87: 4 | AI87: 1 | AJ87: 141 | AK87: 120 | AL87: 11 | AM87: 70 | AN87: 0 | AV87: Sí | AW87: 2024 | AX87: Sí | AY87: Sí | AZ87: NO SABE | BA87: No | BO87: Equipo de fumigación | BP87: 0 | BQ87: 0 | BR87: 0 | BS87: 0 | BT87: 0 | BU87: 1 | BV87: 0 | BW87: 0 | BX87: 0 | BY87: 0 | BZ87: 0 | CA87: 0 | CB87: 0 | CC87: Plagas o enfermedades Lluvia o inundaciones | CD87: 1 | CE87: 0 | CF87: 1 | CG87: 0 | CH87: 0 | CI87: 0 | CJ87: 0 | CK87: 0 | CL87: 0 | CM87: 3 | CO87: Producción agropecuaria | CP87: Sí | CQ87: Sí | CR87: Sí | CS87: Sí | CT87: Sí | CU87: Sí | CV87: Sí | CW87: Sí | CX87: Sí | CY87: Sí | CZ87: Sí | DA87: Sí | DB87: Sí | DC87: Sí | DD87: Sí | DE87: No | DG87: 5 | DI87: 7 | DJ87: 1 | DK87: 2 | DL87: 7 | DM87: 7 | DN87: 0 | DO87: Sí | DP87: Agua entubada | DR87: No | DS87: Sí | DT87: Ago Sep Oct | DU87: 0 | DV87: 0 | DW87: 0 | DX87: 0 | DY87: 0 | DZ87: 0 | EA87: 0 | EB87: 1 | EC87: 1 | ED87: 1 | EE87: 0 | EF87: 0 | EH87: Sí | EK87: 70847626 | EN87: EL NOMBRE DEL LISTADO ESTA INCORRECTO | ES87: 22375850 | ET87: 19382e8f-a5b1-4dd1-9be1-53e316ef1c37 | EU87: 46214.662 | EX87: submitted_via_web | EZ87: vm6MVxpqhFEmodn9Rf6v9F | FB87: uuid:19382e8f-a5b1-4dd1-9be1-53e316ef1c37 | FC87: 66
A88: ="V"&B88&"-R"&FC88 -> V3-R67 | B88: 3 | C88: 46214.341 | D88: 46214.474 | E88: 46213 | G88: Zaira | H88: Milagro | I88: 46214 | K88: LUIS ANGEL TOBAR | L88: 49 | M88: Hombre | O88: Ahuachapán | P88: Ahuachapán Sur | Q88: Guaymango | R88: SAN MARTIN | S88: LOS GARCIA | T88: FJ-164-9 | V88: LUIS | W88: Sí | Y88: Productor | AB88: Sí | AD88: No | AF88: Sí | AG88: 1 | AH88: 5 | AI88: 1 | AJ88: 0 | AK88: 7.5 | AL88: 17 | AM88: 250 | AN88: 450 | AV88: Sí | AW88: 2024 | AX88: Sí | AY88: Sí | AZ88: OSCAR BAUDILIO | BA88: Sí | BB88: Regeneración natural asistida | BC88: No | BD88: No | BL88: Sin cambió | BM88: Sequías extremas | BO88: Ningún activo | BP88: 0 | BQ88: 0 | BR88: 0 | BS88: 0 | BT88: 0 | BU88: 0 | BV88: 0 | BW88: 0 | BX88: 0 | BY88: 0 | BZ88: 0 | CA88: 0 | CB88: 1 | CC88: No sufrió pérdidas de cosecha o animales | CD88: 0 | CE88: 0 | CF88: 0 | CG88: 0 | CH88: 0 | CI88: 0 | CJ88: 0 | CK88: 0 | CL88: 1 | CM88: 4 | CO88: Producción agropecuaria | CP88: Sí | CQ88: Sí | CR88: Sí | CS88: Sí | CT88: Sí | CU88: Sí | CV88: Sí | CW88: No | CX88: Sí | CY88: Sí | CZ88: Sí | DA88: Sí | DB88: Sí | DC88: Sí | DD88: Sí | DE88: No | DG88: 7 | DH88: 7 | DI88: 3 | DJ88: 2 | DK88: 7 | DL88: 7 | DM88: 7 | DN88: 2 | DO88: Sí | DP88: Agua entubada | DR88: Sí | DS88: Sí | DT88: Ene Feb Mar Abr May Jun Jul Ago Sep Oct Nov Dic | DU88: 1 | DV88: 1 | DW88: 1 | DX88: 1 | DY88: 1 | DZ88: 1 | EA88: 1 | EB88: 1 | EC88: 1 | ED88: 1 | EE88: 1 | EF88: 1 | EH88: No | EJ88: Lejanía, dentro del distritio | EK88: 74828016 | ES88: 22378321 | ET88: 44260a4e-6723-417c-89e7-0b3a19c6b289 | EU88: 46214.724 | EX88: submitted_via_web | EZ88: vBf6xt5iWdkTjghTeBLtbw | FB88: uuid:44260a4e-6723-417c-89e7-0b3a19c6b289 | FC88: 67
A89: ="V"&B89&"-R"&FC89 -> V3-R68 | B89: 3 | C89: 46215.674 | D89: 46215.685 | E89: 46214 | G89: Iván | H89: Milagro | I89: 46215 | K89: DIGNA CANDIDA ORELLANA | L89: 54 | M89: Mujer | O89: La Paz | P89: La Paz Centro | Q89: El Rosario | R89: EL TUNAL | S89: LA COQUERA | V89: GIGNA ORELLANA | W89: Sí | Y89: Productor | AB89: Sí | AD89: No sabe / no responde | AF89: Sí | AG89: 1 | AH89: 1 | AI89: 1 | AJ89: 0 | AK89: 25 | AL89: 0 | AM89: 100 | AN89: 0 | AV89: Sí | AW89: 2020 | AX89: Sí | AY89: No | AZ89: NO RECUERDA | BA89: No | BO89: Ningún activo | BP89: 0 | BQ89: 0 | BR89: 0 | BS89: 0 | BT89: 0 | BU89: 0 | BV89: 0 | BW89: 0 | BX89: 0 | BY89: 0 | BZ89: 0 | CA89: 0 | CB89: 1 | CC89: Plagas o enfermedades Sequías | CD89: 1 | CE89: 1 | CF89: 0 | CG89: 0 | CH89: 0 | CI89: 0 | CJ89: 0 | CK89: 0 | CL89: 0 | CM89: 8 | CO89: Trabajo asalariado/permanente (sueldo regular) | CP89: Sí | CQ89: Sí | CR89: Sí | CS89: Sí | CT89: No | CU89: No | CV89: Sí | CW89: No | CX89: Sí | CY89: Sí | CZ89: Sí | DA89: No | DB89: No | DC89: No | DD89: No | DE89: No | DG89: 7 | DH89: 7 | DI89: 3 | DJ89: 6 | DK89: 4 | DL89: 3 | DM89: 7 | DN89: 7 | DO89: Sí | DP89: Agua entubada | DR89: Sí | DS89: No | DT89: Jul Ago Sep Oct Nov Dic | DU89: 0 | DV89: 0 | DW89: 0 | DX89: 0 | DY89: 0 | DZ89: 0 | EA89: 1 | EB89: 1 | EC89: 1 | ED89: 1 | EE89: 1 | EF89: 1 | EH89: No | EJ89: Otra | EK89: 78029268 | EN89: LA PARCELA NO SE MIDIO POR QUE ELLA ALQUILABA EL TERRENO Y YA NO TIENE ACCESO | ES89: 22401718 | ET89: 19d09d9a-1f54-4818-ad05-89c52d82918b | EU89: 46215.935 | EX89: submitted_via_web | EZ89: vm6MVxpqhFEmodn9Rf6v9F | FB89: uuid:19d09d9a-1f54-4818-ad05-89c52d82918b | FC89: 68
A90: ="V"&B90&"-R"&FC90 -> V3-R69 | B90: 3 | C90: 46214.467 | D90: 46215.812 | E90: 46213 | G90: Iván | H90: Milagro | I90: 46214 | K90: AGUSTINA AREVALO SIGUENZA | L90: 41 | M90: Mujer | O90: Ahuachapán | P90: Ahuachapán Sur | Q90: Guaymango | R90: SAN MARTIN | S90: SAN MARTIN | T90: EH-789-4 | V90: AGUSTINA AREVALO SIGUENZA | W90: Sí | Y90: Productor | AB90: Sí | AD90: Sí | AF90: Sí | AG90: 1 | AH90: 3 | AI90: 1 | AJ90: 30 | AK90: 0 | AL90: 20 | AM90: 20 | AN90: 0 | AV90: Sí | AW90: 2022 | AX90: Sí | AY90: Sí | AZ90: NO RECUERDA | BA90: Sí | BB90: Regeneración artificial (plantación de árboles) | BC90: No | BD90: No | BL90: Aumentó algo | BM90: Sequías extremas | BO90: Ningún activo | BP90: 0 | BQ90: 0 | BR90: 0 | BS90: 0 | BT90: 0 | BU90: 0 | BV90: 0 | BW90: 0 | BX90: 0 | BY90: 0 | BZ90: 0 | CA90: 0 | CB90: 1 | CC90: Plagas o enfermedades Sequías | CD90: 1 | CE90: 1 | CF90: 0 | CG90: 0 | CH90: 0 | CI90: 0 | CJ90: 0 | CK90: 0 | CL90: 0 | CM90: 5 | CO90: Servicios domésticos | CP90: Sí | CQ90: No | CR90: Sí | CS90: No | CT90: No | CU90: No | CV90: No | CW90: No | CX90: Sí | CY90: Sí | CZ90: No | DA90: No | DB90: No | DC90: No | DD90: No | DE90: No | DG90: 4 | DH90: 7 | DI90: 0 | DJ90: 1 | DK90: 0 | DL90: 0 | DM90: 3 | DN90: 7 | DO90: No | EH90: No | EJ90: Lejanía, dentro del distritio | EK90: 72310749 | EL90: SEISCIATROCUATROCUATROUNOOCHOSEISSEIS | EN90: LA PARCELA ESTABA LEJOS | ES90: 22402263 | ET90: 9402764c-cfa3-4b4a-8250-cb03b6c15677 | EU90: 46216.062 | EX90: submitted_via_web | EZ90: vm6MVxpqhFEmodn9Rf6v9F | FB90: uuid:9402764c-cfa3-4b4a-8250-cb03b6c15677 | FC90: 69
A91: ="V"&B91&"-R"&FC91 -> V3-R70 | B91: 3 | C91: 46214.364 | D91: 46215.812 | E91: 46213 | G91: Iván | H91: Milagro | I91: 46214 | K91: JAIRO NEFTALI RUIZ AREVALO | L91: 33 | M91: Mujer | O91: Ahuachapán | P91: Ahuachapán Sur | Q91: Guaymango | R91: SAN MARTIN CENTRO | S91: SAN MARTIN | T91: EP-474-8 | V91: JAIRO NEFTALI RUIZ | W91: Sí | Y91: Productor | AB91: Sí | AD91: No sabe / no responde | AF91: Sí | AG91: 1 | AH91: 2 | AI91: 1 | AJ91: 40 | AK91: 260 | AL91: 90 | AM91: 200 | AN91: 0 | AV91: Sí | AW91: 2022 | AX91: Sí | AY91: No | AZ91: BAUTILIO GRACIA | BA91: Sí | BB91: Regeneración artificial (plantación de árboles) | BC91: No | BD91: No | BL91: Aumentó algo | BM91: Sequías extremas | BO91: Ningún activo | BP91: 0 | BQ91: 0 | BR91: 0 | BS91: 0 | BT91: 0 | BU91: 0 | BV91: 0 | BW91: 0 | BX91: 0 | BY91: 0 | BZ91: 0 | CA91: 0 | CB91: 1 | CC91: Plagas o enfermedades Sequías Vientos fuertes | CD91: 1 | CE91: 1 | CF91: 0 | CG91: 0 | CH91: 1 | CI91: 0 | CJ91: 0 | CK91: 0 | CL91: 0 | CM91: 5 | CO91: Trabajo asalariado/permanente (sueldo regular) | CP91: Sí | CQ91: No | CR91: No | CS91: No | CT91: No | CU91: Sí | CV91: Sí | CW91: No | CX91: Sí | CY91: Sí | CZ91: Sí | DA91: No | DB91: No | DC91: No | DD91: No | DE91: No | DG91: 7 | DH91: 7 | DI91: 3 | DJ91: 3 | DK91: 5 | DL91: 3 | DM91: 5 | DN91: 7 | DO91: Sí | DP91: Agua entubada | DR91: Sí | DS91: Sí | DT91: May Jun Jul Ago Sep Oct | DU91: 0 | DV91: 0 | DW91: 0 | DX91: 0 | DY91: 1 | DZ91: 1 | EA91: 1 | EB91: 1 | EC91: 1 | ED91: 1 | EE91: 0 | EF91: 0 | EH91: Sí | EK91: 60689880 | EN91: POLIGONO EN APLICACION | ES91: 22402271 | ET91: 095d30bd-9383-49c2-a530-8b07ae0ddc88 | EU91: 46216.062 | EX91: submitted_via_web | EZ91: vm6MVxpqhFEmodn9Rf6v9F | FB91: uuid:095d30bd-9383-49c2-a530-8b07ae0ddc88 | FC91: 70
A92: ="V"&B92&"-R"&FC92 -> V3-R71 | B92: 3 | C92: 46205.609 | D92: 46215.821 | E92: 46204 | G92: Iván | H92: Milagro | I92: 46205 | K92: JOSE WILIAN GARCIA CLAROS | L92: 0 | M92: Hombre | O92: Morazán | P92: Morazán Sur | Q92: Gualococti | R92: GUALOCOCTI | S92: LA VILLA | T92: WV-035-8 | V92: JOSE CLAROS | W92: Sí | Y92: Productor | AB92: Sí | AD92: No | AF92: Sí | AG92: 1 | AH92: 1 | AI92: 1 | AJ92: 25 | AK92: 0 | AL92: 65 | AM92: 72 | AN92: 0 | AV92: Sí | AW92: 2024 | AX92: Sí | AY92: Sí | AZ92: LUIS ALONSO | BA92: Sí | BB92: Regeneración artificial (plantación de árboles) | BC92: No | BD92: Sí | BE92: RECLIMA | BF92: 0 | BG92: 1 | BH92: 0 | BI92: 0 | BJ92: 0 | BK92: 0 | BL92: Disminuyó algo | BM92: Sequías extremas | BO92: Podadora | BP92: 0 | BQ92: 0 | BR92: 0 | BS92: 0 | BT92: 1 | BU92: 0 | BV92: 0 | BW92: 0 | BX92: 0 | BY92: 0 | BZ92: 0 | CA92: 0 | CB92: 0 | CC92: Sequías | CD92: 0 | CE92: 1 | CF92: 0 | CG92: 0 | CH92: 0 | CI92: 0 | CJ92: 0 | CK92: 0 | CL92: 0 | CM92: 4 | CO92: Jornalero agropecuario | CP92: Sí | CQ92: Sí | CR92: Sí | CS92: Sí | CT92: No | CU92: No | CV92: Sí | CW92: Sí | CX92: Sí | CY92: Sí | CZ92: Sí | DA92: No | DB92: Sí | DC92: Sí | DD92: No | DE92: No | DG92: 7 | DH92: 7 | DI92: 7 | DJ92: 7 | DK92: 7 | DL92: 7 | DM92: 7 | DO92: Sí | DP92: Agua entubada | DR92: Sí | DS92: Sí | DT92: Ene Feb Mar Abr May Jun Jul Ago Sep Oct Nov Dic | DU92: 1 | DV92: 1 | DW92: 1 | DX92: 1 | DY92: 1 | DZ92: 1 | EA92: 1 | EB92: 1 | EC92: 1 | ED92: 1 | EE92: 1 | EF92: 1 | EH92: No | EJ92: Lejanía, dentro del distritio | EK92: 73830749 | EN92: EL FORMULARIO DIO FALLAS Y TUCE QUE LLENAR DOS | ES92: 22402365 | ET92: e2c83b1b-3ef9-476f-871c-6a0f13003af4 | EU92: 46216.071 | EX92: submitted_via_web | EZ92: vm6MVxpqhFEmodn9Rf6v9F | FB92: uuid:e2c83b1b-3ef9-476f-871c-6a0f13003af4 | FC92: 71
A93: ="V"&B93&"-R"&FC93 -> V3-R72 | B93: 3 | C93: 46203.623 | D93: 46215.827 | E93: 46202 | G93: Iván | H93: Milagro | I93: 46203 | K93: RICARDO GUILLEN ORTEZ | L93: 54 | M93: Hombre | O93: La Unión | P93: La Unión Norte | Q93: Bolivar | R93: LA PAZ | S93: LA PAZ | T93: DX-003-9 | V93: JOSE RICARDO GUILLEN | W93: Sí | Y93: Familiar del productor | AB93: Sí | AD93: Sí | AF93: Sí | AG93: 1 | AH93: 1 | AI93: 1 | AJ93: 108 | AK93: 180 | AL93: 75 | AM93: 190 | AN93: 400 | AV93: Sí | AW93: 2023 | AX93: Sí | AY93: Sí | AZ93: JOSE BAYONA | BA93: No | BO93: Ningún activo | BP93: 0 | BQ93: 0 | BR93: 0 | BS93: 0 | BT93: 0 | BU93: 0 | BV93: 0 | BW93: 0 | BX93: 0 | BY93: 0 | BZ93: 0 | CA93: 0 | CB93: 1 | CC93: Plagas o enfermedades Sequías | CD93: 1 | CE93: 1 | CF93: 0 | CG93: 0 | CH93: 0 | CI93: 0 | CJ93: 0 | CK93: 0 | CL93: 0 | CM93: 3 | CO93: Jornalero agropecuario | CP93: Sí | CQ93: No | CR93: No | CS93: No | CT93: No | CU93: No | CV93: No | CW93: No | CX93: No | DG93: 7 | DH93: 7 | DI93: 3 | DJ93: 7 | DL93: 5 | DM93: 7 | DN93: 7 | DO93: Sí | DP93: Pozo | DR93: Sí | DS93: No | DT93: Ene Sep Oct Nov Dic | DU93: 1 | DV93: 0 | DW93: 0 | DX93: 0 | DY93: 0 | DZ93: 0 | EA93: 0 | EB93: 0 | EC93: 1 | ED93: 1 | EE93: 1 | EF93: 1 | EH93: No | EJ93: Lejanía, dentro del distritio | EK93: 69222475 | EN93: LA PARCELA ESTABA LEJOS DEL LUGAR | ES93: 22402414 | ET93: 0394140c-5ce7-4e13-b02a-d7858c5b9560 | EU93: 46216.077 | EX93: submitted_via_web | EZ93: vm6MVxpqhFEmodn9Rf6v9F | FB93: uuid:0394140c-5ce7-4e13-b02a-d7858c5b9560 | FC93: 72
A94: ="V"&B94&"-R"&FC94 -> V3-R73 | B94: 3 | C94: 46215.829 | D94: 46215.844 | E94: 46214 | G94: Iván | H94: Milagro | I94: 46203 | K94: JOSE ADOAY ESPINAL SORTO | L94: 60 | M94: Hombre | O94: La Unión | P94: La Unión Norte | Q94: Bolivar | R94: LA PAZ | S94: LOS MANCILLAS | T94: XP-448-7 | V94: ESTELA DEL CARMEN TURCIO | W94: Sí | Y94: Familiar del productor | AB94: Sí | AD94: No | AF94: Sí | AG94: 1 | AH94: 1 | AI94: 1 | AJ94: 9999 | AK94: 9999 | AL94: 9999 | AM94: 150 | AN94: 0 | AV94: Sí | AW94: 2023 | AX94: Sí | AY94: Sí | AZ94: JOSE BAYONA | BA94: No | BO94: Bomba de agua | BP94: 0 | BQ94: 0 | BR94: 0 | BS94: 0 | BT94: 0 | BU94: 0 | BV94: 0 | BW94: 1 | BX94: 0 | BY94: 0 | BZ94: 0 | CA94: 0 | CB94: 0 | CC94: No sufrió pérdidas de cosecha o animales | CD94: 0 | CE94: 0 | CF94: 0 | CG94: 0 | CH94: 0 | CI94: 0 | CJ94: 0 | CK94: 0 | CL94: 1 | CM94: 5 | CO94: Servicios domésticos | CP94: Sí | CQ94: Sí | CR94: Sí | CS94: Sí | CT94: No | CU94: Sí | CV94: No | CW94: No | CX94: Sí | CY94: Sí | CZ94: Sí | DA94: No | DB94: No | DC94: No | DD94: No | DE94: No | DG94: 7 | DH94: 7 | DI94: 2 | DJ94: 0 | DK94: 6 | DL94: 2 | DM94: 7 | DN94: 7 | DO94: No | EH94: No | EJ94: Otra | EK94: 74261081 | EN94: ALGUNAS PREGUNTAS NO SE CONTESTARON POR QUE LA ESPOSA DEL PRODUCTOR NO SABIA EL PRODUCTOR ESTAB EN CAMA CON PERDIDA DE VISTA Y LE COSTABA OIR | ES94: 22402522 | ET94: 5fa74614-5738-4fa6-a897-dc6b4e8fda71 | EU94: 46216.094 | EX94: submitted_via_web | EZ94: vm6MVxpqhFEmodn9Rf6v9F | FB94: uuid:5fa74614-5738-4fa6-a897-dc6b4e8fda71 | FC94: 73
A95: ="V"&B95&"-R"&FC95 -> V3-R74 | B95: 3 | C95: 46207.647 | D95: 46215.852 | E95: 46206 | G95: Iván | H95: Milagro | I95: 46207 | K95: JUAN ANTONIO PACAS | L95: 60 | M95: Hombre | O95: Usulután | P95: Usulután Norte | Q95: Jucuapa | R95: EL AMATON | S95: LOS SANTOS | V95: MARIA CORINA ROBLES | W95: Sí | Y95: Familiar del productor | AB95: Sí | AD95: No | AF95: Sí | AG95: 2 | AH95: 2 | AI95: 2 | AJ95: 20 | AK95: 100 | AL95: 24 | AM95: 60 | AN95: 350 | AV95: Sí | AW95: 2025 | AX95: Sí | AY95: No | AZ95: RAMIRO | BA95: No | BO95: Bomba de agua Autos particulares | BP95: 0 | BQ95: 0 | BR95: 0 | BS95: 0 | BT95: 0 | BU95: 0 | BV95: 0 | BW95: 1 | BX95: 0 | BY95: 1 | BZ95: 0 | CA95: 0 | CB95: 0 | CC95: Plagas o enfermedades Sequías Lluvia o inundaciones Vientos fuertes Robo | CD95: 1 | CE95: 1 | CF95: 1 | CG95: 0 | CH95: 1 | CI95: 0 | CJ95: 0 | CK95: 1 | CL95: 0 | CM95: 2 | CO95: Producción agropecuaria | CP95: Sí | CQ95: Sí | CR95: Sí | CS95: Sí | CT95: Sí | CU95: Sí | CV95: Sí | CW95: Sí | CX95: No | DG95: 7 | DH95: 7 | DI95: 2 | DJ95: 7 | DK95: 7 | DL95: 2 | DM95: 7 | DN95: 7 | DO95: Sí | DP95: Agua entubada | DR95: No | DS95: Sí | DT95: Ene Feb Mar Abr May Jun Jul Ago Sep Oct Nov Dic | DU95: 1 | DV95: 1 | DW95: 1 | DX95: 1 | DY95: 1 | DZ95: 1 | EA95: 1 | EB95: 1 | EC95: 1 | ED95: 1 | EE95: 1 | EF95: 1 | EH95: No | EJ95: Lejanía, dentro del distritio | EK95: 71421879 | EN95: LA PARCELA SE ENCONTRABA LEJOS Y AL ESPOSA NO PODIA IR | ES95: 22402581 | ET95: 520f8184-4dc1-4243-bbe0-ff12d368a4c8 | EU95: 46216.102 | EX95: submitted_via_web | EZ95: vm6MVxpqhFEmodn9Rf6v9F | FB95: uuid:520f8184-4dc1-4243-bbe0-ff12d368a4c8 | FC95: 74
A96: ="V"&B96&"-R"&FC96 -> V3-R75 | B96: 3 | C96: 46206.566 | D96: 46215.859 | E96: 46205 | G96: Iván | H96: Milagro | I96: 46207 | K96: IGNACIO MIQUEL PEREZ | L96: 48 | M96: Hombre | O96: La Unión | P96: La Unión Sur | Q96: Yucuaiquín | R96: EL CARMEN | S96: EL CARMEN | T96: MR-135-9 | V96: IGNACIO PEREZ | W96: Sí | Y96: Productor | AB96: Sí | AD96: No | AF96: Sí | AG96: 1 | AH96: 1 | AI96: 1 | AJ96: 0 | AK96: 165 | AL96: 65 | AM96: 130 | AN96: 0 | AV96: Sí | AW96: 2025 | AX96: Sí | AY96: No | AZ96: ERODITA MENDOZA | BA96: Sí | BB96: Regeneración artificial (plantación de árboles) | BC96: No | BD96: Sí | BE96: RECLIMA | BF96: 0 | BG96: 1 | BH96: 0 | BI96: 0 | BJ96: 0 | BK96: 0 | BL96: Disminuyó algo | BM96: Sequías extremas | BO96: Ningún activo | BP96: 0 | BQ96: 0 | BR96: 0 | BS96: 0 | BT96: 0 | BU96: 0 | BV96: 0 | BW96: 0 | BX96: 0 | BY96: 0 | BZ96: 0 | CA96: 0 | CB96: 1 | CC96: Sequías | CD96: 0 | CE96: 1 | CF96: 0 | CG96: 0 | CH96: 0 | CI96: 0 | CJ96: 0 | CK96: 0 | CL96: 0 | CM96: 3 | CO96: Oficios varios (artesanías, carpintería, albañilería, etc.) | CP96: Sí | CQ96: No | CR96: No | CS96: Sí | CT96: Sí | CU96: Sí | CV96: No | CW96: No | CX96: No | DG96: 7 | DH96: 7 | DJ96: 3 | DK96: 4 | DL96: 7 | DM96: 7 | DN96: 2 | DO96: No | EH96: No | EJ96: Lejanía, dentro del distritio | EK96: 73164162 | EN96: PARCELA LEJOS DEL LUGAR A UNA HORA CAMINANDO | ES96: 22402748 | ET96: b327c280-669d-4eec-88f7-fe73373009bc | EU96: 46216.109 | EX96: submitted_via_web | EZ96: vm6MVxpqhFEmodn9Rf6v9F | FB96: uuid:b327c280-669d-4eec-88f7-fe73373009bc | FC96: 75
A97: ="V"&B97&"-R"&FC97 -> V3-R76 | B97: 3 | C97: 46214.412 | D97: 46215.868 | E97: 46213 | G97: Nancy | H97: Milagro | I97: 46214 | K97: EDGARDO AREVALO RAMIREZ | L97: 42 | M97: Hombre | O97: Ahuachapán | P97: Ahuachapán Sur | Q97: Guaymango | R97: CAUTA ABAJO | S97: LOS GARCIA | T97: MK-537-8 | V97: PAOLA AREVALO SIGUENZA | W97: Sí | Y97: Familiar del productor | AB97: Sí | AD97: Sí | AF97: Sí | AG97: 1 | AH97: 2 | AI97: 1 | AJ97: 150 | AK97: 80 | AL97: 150 | AM97: 80 | AN97: 100 | AV97: Sí | AW97: 2025 | AX97: No | AY97: No | AZ97: NO SABE | BA97: No | BO97: Equipo de fumigación | BP97: 0 | BQ97: 0 | BR97: 0 | BS97: 0 | BT97: 0 | BU97: 1 | BV97: 0 | BW97: 0 | BX97: 0 | BY97: 0 | BZ97: 0 | CA97: 0 | CB97: 0 | CC97: Plagas o enfermedades Sequías | CD97: 1 | CE97: 1 | CF97: 0 | CG97: 0 | CH97: 0 | CI97: 0 | CJ97: 0 | CK97: 0 | CL97: 0 | CM97: 4 | CO97: Producción agropecuaria | CP97: Sí | CQ97: Sí | CR97: Sí | CS97: Sí | CT97: Sí | CU97: Sí | CV97: Sí | CW97: Sí | CX97: Sí | CY97: No | CZ97: Sí | DA97: Sí | DB97: Sí | DC97: Sí | DD97: Sí | DE97: Sí | DG97: 7 | DH97: 7 | DI97: 0 | DJ97: 0 | DK97: 7 | DL97: 5 | DM97: 1 | DN97: 2 | DO97: Sí | DP97: Agua entubada | DR97: Sí | DS97: Sí | DT97: Ene Feb Mar Abr May Jun | DU97: 1 | DV97: 1 | DW97: 1 | DX97: 1 | DY97: 1 | DZ97: 1 | EA97: 0 | EB97: 0 | EC97: 0 | ED97: 0 | EE97: 0 | EF97: 0 | EH97: Sí | EK97: 72556452 | ES97: 22402798 | ET97: 8133e5b7-2e92-45d4-bade-980368c9be4a | EU97: 46216.118 | EX97: submitted_via_web | EZ97: vm6MVxpqhFEmodn9Rf6v9F | FB97: uuid:8133e5b7-2e92-45d4-bade-980368c9be4a | FC97: 76
A98: ="V"&B98&"-R"&FC98 -> V3-R77 | B98: 3 | C98: 46215.844 | D98: 46215.873 | E98: 46214 | G98: Iván | H98: Milagro | I98: 46206 | K98: EMILDA ALEJANDRA RAMOS PEREZ | L98: 24 | M98: Mujer | O98: Morazán | P98: Morazán Norte | Q98: Perquín | R98: CASA BLANCA | S98: LOS MANGOS | T98: AX-479-7 | V98: EMILDA RAMOS | W98: Sí | Y98: Productor | AB98: Sí | AD98: No sabe / no responde | AF98: Sí | AG98: 1 | AH98: 1 | AI98: 1 | AJ98: 0 | AK98: 0 | AL98: 0 | AM98: 0 | AN98: 0 | AV98: Sí | AW98: 2023 | AX98: Sí | AY98: No | AZ98: NO RECUERDA | BA98: No | BO98: Ningún activo | BP98: 0 | BQ98: 0 | BR98: 0 | BS98: 0 | BT98: 0 | BU98: 0 | BV98: 0 | BW98: 0 | BX98: 0 | BY98: 0 | BZ98: 0 | CA98: 0 | CB98: 1 | CC98: Plagas o enfermedades Sequías | CD98: 1 | CE98: 1 | CF98: 0 | CG98: 0 | CH98: 0 | CI98: 0 | CJ98: 0 | CK98: 0 | CL98: 0 | CM98: 2 | CO98: Jornalero agropecuario | CP98: Sí | CQ98: Sí | CR98: Sí | CS98: Sí | CT98: Sí | CU98: Sí | CV98: Sí | CW98: No | CX98: Sí | CY98: No | CZ98: Sí | DA98: No | DB98: No | DC98: No | DD98: No | DE98: No | DG98: 7 | DH98: 7 | DI98: 6 | DJ98: 7 | DK98: 7 | DL98: 7 | DM98: 7 | DN98: 6 | DO98: Sí | DP98: Agua entubada | DR98: No | DS98: No | DT98: Ene Feb Mar Abr May Jun Jul Ago Sep Oct Nov Dic | DU98: 1 | DV98: 1 | DW98: 1 | DX98: 1 | DY98: 1 | DZ98: 1 | EA98: 1 | EB98: 1 | EC98: 1 | ED98: 1 | EE98: 1 | EF98: 1 | EH98: No | EJ98: Lejanía, dentro del distritio | EK98: 63034148 | EN98: ERA MADRE SOLTERA LA PARCELA SE ENCONTRABA LEOS DEL LUGAR COMO A UNA HORA Y MEDIA HABIA QUE SALIR DEL CANTON TOMAR BUS Y ELLA NO PODIA POR LA NINA QUE TENIAN QUE HACER TAREAS | ES98: 22402845 | ET98: 76dffff5-ec46-4d6f-8102-96abe75a184f | EU98: 46216.123 | EX98: submitted_via_web | EZ98: vm6MVxpqhFEmodn9Rf6v9F | FB98: uuid:76dffff5-ec46-4d6f-8102-96abe75a184f | FC98: 77
A99: ="V"&B99&"-R"&FC99 -> V3-R78 | B99: 3 | C99: 46205.627 | D99: 46215.884 | E99: 46204 | G99: Iván | H99: Milagro | I99: 46205 | K99: JOSE ELICEO MATA BENITES | L99: 51 | M99: Hombre | O99: Morazán | P99: Morazán Sur | Q99: Chilanga | R99: EL CHAPARRAL | S99: EL MENDOZA | T99: NK-726-8 | V99: JOSE MATA | W99: Sí | Y99: Productor | AB99: Sí | AD99: No | AF99: Sí | AG99: 2 | AH99: 1 | AI99: 2 | AJ99: 180 | AK99: 350 | AL99: 70 | AM99: 300 | AN99: 300 | AV99: Sí | AW99: 2024 | AX99: Sí | AY99: Sí | AZ99: ROSA ALVARES FLORES | BA99: Sí | BB99: Regeneración artificial (plantación de árboles) | BC99: No | BD99: Sí | BE99: RECLIMA | BF99: 0 | BG99: 1 | BH99: 0 | BI99: 0 | BJ99: 0 | BK99: 0 | BL99: Sin cambió | BM99: Sequías extremas | BO99: Bomba de agua | BP99: 0 | BQ99: 0 | BR99: 0 | BS99: 0 | BT99: 0 | BU99: 0 | BV99: 0 | BW99: 1 | BX99: 0 | BY99: 0 | BZ99: 0 | CA99: 0 | CB99: 0 | CC99: Plagas o enfermedades Sequías | CD99: 1 | CE99: 1 | CF99: 0 | CG99: 0 | CH99: 0 | CI99: 0 | CJ99: 0 | CK99: 0 | CL99: 0 | CM99: 6 | CO99: Oficios varios (artesanías, carpintería, albañilería, etc.) | CP99: Sí | CQ99: No | CR99: Sí | CS99: Sí | CT99: Sí | CU99: Sí | CV99: No | CW99: Sí | CX99: Sí | CY99: No | CZ99: Sí | DA99: No | DB99: Sí | DC99: Sí | DD99: No | DE99: No | DG99: 2 | DH99: 5 | DI99: 2 | DJ99: 3 | DK99: 7 | DL99: 1 | DM99: 7 | DN99: 3 | DO99: Sí | DP99: Agua entubada | DR99: Sí | DS99: Sí | DT99: Mar Abr | DU99: 0 | DV99: 0 | DW99: 1 | DX99: 1 | DY99: 0 | DZ99: 0 | EA99: 0 | EB99: 0 | EC99: 0 | ED99: 0 | EE99: 0 | EF99: 0 | EH99: Sí | EK99: 68204725 | EN99: POLIGONO EN APLICACION | ES99: 22403008 | ET99: 22cd3b8c-d522-44ea-bbf5-cbdaa0192084 | EU99: 46216.134 | EX99: submitted_via_web | EZ99: vm6MVxpqhFEmodn9Rf6v9F | FB99: uuid:22cd3b8c-d522-44ea-bbf5-cbdaa0192084 | FC99: 78
A100: ="V"&B100&"-R"&FC100 -> V3-R79 | B100: 3 | C100: 46216.359 | D100: 46216.392 | E100: 46215 | G100: Blanca Argelia | H100: Milagro | I100: 46216 | K100: FRANCISCO RUBEN CERON | L100: 43 | M100: Hombre | O100: La Paz | P100: La Paz Centro | Q100: El Rosario | R100: JALPUNGUITA | S100: OJO FE DE AGUA | T100: JX-256-6 | V100: FRANCISCO CERON MENDDEZ | W100: Sí | Y100: Productor | AB100: Sí | AD100: No | AF100: Sí | AG100: 1 | AH100: 1 | AI100: 1 | AJ100: 0 | AK100: 9999 | AL100: 9999 | AM100: 0 | AN100: 0 | AO100: Bovinos (vacas, terneros, novillos, bueyes, toros) Aves (gallinas, pollos, gallos) | AP100: 1 | AQ100: 0 | AR100: 1 | AS100: 0 | AT100: 0 | AU100: 0 | AV100: Sí | AW100: 2023 | AX100: No | AY100: No | AZ100: OSMIN ALONSO | BA100: Sí | BB100: Regeneración artificial (plantación de árboles) | BC100: No | BD100: Sí | BE100: ONG | BF100: 0 | BG100: 0 | BH100: 0 | BI100: 1 | BJ100: 0 | BK100: 0 | BL100: Sin cambió | BM100: Incendios forestales | BO100: Tanque para almacenamiento de agua | BP100: 0 | BQ100: 0 | BR100: 0 | BS100: 0 | BT100: 0 | BU100: 0 | BV100: 1 | BW100: 0 | BX100: 0 | BY100: 0 | BZ100: 0 | CA100: 0 | CB100: 0 | CC100: No sufrió pérdidas de cosecha o animales | CD100: 0 | CE100: 0 | CF100: 0 | CG100: 0 | CH100: 0 | CI100: 0 | CJ100: 0 | CK100: 0 | CL100: 1 | CM100: 5 | CO100: Producción agropecuaria | CP100: Sí | CQ100: No | CR100: No | CS100: Sí | CT100: No | CU100: No | CV100: No | CW100: No | CX100: Sí | CY100: No | CZ100: No | DA100: No | DB100: No | DC100: No | DD100: No | DE100: No | DG100: 2 | DH100: 2 | DI100: 7 | DJ100: 1 | DK100: 2 | DL100: 1 | DM100: 7 | DN100: 7 | DO100: Sí | DP100: Pozo | DR100: Sí | DS100: Sí | DT100: Jul | DU100: 0 | DV100: 0 | DW100: 0 | DX100: 0 | DY100: 0 | DZ100: 0 | EA100: 1 | EB100: 0 | EC100: 0 | ED100: 0 | EE100: 0 | EF100: 0 | EH100: No | EJ100: Lejanía, dentro del distritio | EK100: 64319518 | ES100: 22414074 | ET100: 5f4cfe83-b157-4425-bd5f-59d53a842378 | EU100: 46216.642 | EX100: submitted_via_web | EZ100: vm6MVxpqhFEmodn9Rf6v9F | FB100: uuid:5f4cfe83-b157-4425-bd5f-59d53a842378 | FC100: 79
...

Sheet Poligonos_SINASIGNAR
A1: Poligonos ingresados sin asignar | F1: Identificador Prácticas
F2: NL-990-7
A3: Registre el polígono de la parcela | B3: Ingrese acá el código del beneficiario | F3: LR-865-9
A4: 13.771965 -87.7691236 0.0 0.0;13.773730353210176 -87.76787873357534 0.0 0.0;13.773790921270189 -87.77087040245533 0.0 0.0;13.76981098021808 -87.77029372751713 0.0 0.0;13.76766207044374 -87.7668035030365 0.0 0.0;13.770416344627984 -87.76607125997543 0.0 0.0;13.772307976191716 -87.76600889861584 0.0 0.0;13.773730353210176 -87.76787873357534 0.0 0.0 | B4: NV-938-B | C4: =VLOOKUP(B4,$F$1:$F$1051,1,FALSE) -> #N/A | F4: FR-815-1
A5: 13.5667309 -87.9386796 0.0 0.0; 13.5665931 -87.9384614 0.0 0.0; 13.5670558 -87.9380062 0.0 0.0; 13.5672953 -87.9383673 0.0 0.0; 13.5667253 -87.9386821 0.0 0.0 | B5: JT-694-9 | C5: =VLOOKUP(B5,$F$1:$F$1051,1,FALSE) -> #N/A | F5: WL-559-1
A6: 13.7619608 -87.773101 0.0 0.0;13.7621491 -87.7731041 0.0 0.0;13.7619886 -87.7734047 0.0 0.0;13.7617909 -87.7733579 0.0 0.0 | B6: NC-475-8 | C6: =VLOOKUP(B6,$F$1:$F$1051,1,FALSE) -> #N/A | F6: FX-129-6
A7: 13.7666507 -87.7645633 0.0 0.0;13.7663029 -87.7643542 0.0 0.0;13.7661438 -87.7644788 0.0 0.0;13.7661189 -87.7646865 0.0 0.0;13.766436671773288 -87.76474054902792 0.0 0.0;13.7665609 -87.7647775 0.0 0.0;13.7666507 -87.7645633 0.0 0.0 | B7: TY-622-2 | C7: =VLOOKUP(B7,$F$1:$F$1051,1,FALSE) -> #N/A | F7: JM-861-6
A8: 13.9199829 -88.2346066 0.0 0.0;13.920121 -88.2344317 0.0 0.0;13.920017824387397 -88.23446609079838 0.0 0.0;13.9199829 -88.2346066 0.0 0.0 | B8: VY-224-9 | C8: =VLOOKUP(B8,$F$1:$F$1051,1,FALSE) -> #N/A | F8: LK-177-7
A9: 13.9533095 -88.1657879 0.0 0.0; 13.953314 -88.165802 0.0 0.0; 13.9533095 -88.1657879 0.0 0.0; 13.953314 -88.165802 0.0 0.0; 13.9533264274934 -88.16581193357706 0.0 0.0; 13.953331959003622 -88.16580958664417 0.0 0.0; 13.9533095 -88.1657879 0.0 0.0 | B9: LJ-668-6 | C9: =VLOOKUP(B9,$F$1:$F$1051,1,FALSE) -> #N/A | F9: CK-036-6
A10: 13.9781323 -88.1708904 0.0 0.0; 13.9783975 -88.1706592 0.0 0.0; 13.9783136 -88.1705848 0.0 0.0; 13.9783157 -88.1705457 0.0 0.0; 13.9780252 -88.1707937 0.0 0.0 | B10: MH-227-7 | C10: =VLOOKUP(B10,$F$1:$F$1051,1,FALSE) -> #N/A | F10: EH-789-4
A11: 13.825403 -88.2121965 0.0 0.0;13.8254147 -88.2120914 0.0 0.0;13.8252311 -88.2120053 0.0 0.0;13.8250374 -88.2122304 0.0 0.0;13.8253918 -88.2124307 0.0 0.0;13.8253801 -88.2122485 0.0 0.0;13.825403 -88.2121965 0.0 0.0 | B11: CV-495-9 | C11: =VLOOKUP(B11,$F$1:$F$1051,1,FALSE) -> #N/A | F11: HX-142-0
A12: 13.824485 -88.214675 0.0 0.0; 13.826739302914868 -88.21252461522818 0.0 0.0; 13.828237203250579 -88.2128206640482 0.0 0.0; 13.828691031617087 -88.21640443056822 0.0 0.0; 13.82664456470824 -88.21990638971329 0.0 0.0; 13.820365712264621 -88.22140239179134 0.0 0.0; 13.817309243937082 -88.22070099413395 0.0 0.0; 13.81768430484237 -88.21745753288269 0.0 0.0; 13.819590529536567 -88.21435689926147 0.0 0.0; 13.821705102128632 -88.21017801761627 0.0 0.0; 13.824761512767335 -88.20936765521765 0.0 0.0; 13.82511702788925 -88.21116875857115 0.0 0.0; 13.824485 -88.214675 0.0 0.0; 13.826593777200133 -88.21085091680288 0.0 0.0; 13.82895408237422 -88.21100682020187 0.0 0.0; 13.830948440200434 -88.21371417492628 0.0 0.0; 13.824578871545826 -88.21751587092876 0.0 0.0; 13.822774589962405 -88.21388315409422 0.0 0.0; 13.826976962163942 -88.20780325680971 0.0 0.0; 13.830577958436066 -88.20953294634819 0.0 0.0; 13.828237203250579 -88.2128206640482 0.0 0.0 | B12: PN-092-9 | C12: =VLOOKUP(B12,$F$1:$F$1051,1,FALSE) -> #N/A | F12: XN-243-1
A13: 13.8222965 -88.2058837 0.0 0.0; 13.82512581809144 -88.20413868874311 0.0 0.0; 13.825953072300326 -88.20725005120039 0.0 0.0; 13.822274193983114 -88.21039360016584 0.0 0.0; 13.817459007912657 -88.20814691483974 0.0 0.0; 13.818681208583836 -88.20376586169004 0.0 0.0; 13.819612342777535 -88.20210825651884 0.0 0.0; 13.823166245922122 -88.20152923464775 0.0 0.0; 13.826399417211057 -88.20154130458832 0.0 0.0; 13.827076583640011 -88.20532254874706 0.0 0.0; 13.825805918283686 -88.20884395390749 0.0 0.0; 13.817024692118245 -88.21141015738249 0.0 0.0; 13.814884356429413 -88.20476565510035 0.0 0.0; 13.816076292070589 -88.20004228502512 0.0 0.0; 13.81968917746084 -88.19700133055449 0.0 0.0; 13.824573011397298 -88.1950195133686 0.0 0.0; 13.828564715058741 -88.1983357295394 0.0 0.0; 13.827076583640011 -88.20532254874706 0.0 0.0; 13.828820278127735 -88.20531986653805 0.0 0.0; 13.83058609732124 -88.19810170680285 0.0 0.0; 13.827731935620847 -88.194166906178 0.0 0.0; 13.822690593835379 -88.19343198090792 0.0 0.0; 13.820330225165423 -88.19463193416595 0.0 0.0; 13.81448389594089 -88.20024881511927 0.0 0.0; 13.814884356429413 -88.20476565510035 0.0 0.0 | B13: RK-126-4 | C13: =VLOOKUP(B13,$F$1:$F$1051,1,FALSE) -> #N/A | F13: LJ-975-4
A14: 13.5247662 -87.9920726 0.0 0.0;13.5247909 -87.992028 0.0 0.0;13.5247423 -87.9918636 0.0 0.0;13.5248448 -87.9918617 0.0 0.0;13.5248458 -87.9920257 0.0 0.0;13.5247662 -87.9920726 0.0 0.0 | B14: RV-539-6 | C14: =VLOOKUP(B14,$F$1:$F$1051,1,FALSE) -> #N/A | F14: KH-031-3
A15: 13.6006228 -88.09112 0.0 0.0; 13.6004795 -88.0913836 0.0 0.0; 13.6005004 -88.0914291 0.0 0.0; 13.6006371 -88.09138 0.0 0.0; 13.600623 -88.0913761 0.0 0.0; 13.6006712 -88.0913066 0.0 0.0; 13.600649969872432 -88.0911197885871 0.0 0.0 | B15: TA-373-9 | C15: =VLOOKUP(B15,$F$1:$F$1051,1,FALSE) -> #N/A | F15: CE-221-5
... A24: 13.7456538 -88.0875708 0.0 0.0; 13.7453769 -88.0876605 0.0 0.0; 13.7453654 -88.0869019 0.0 0.0; 13.7456867 -88.0868802 0.0 0.0; 13.7456538 -88.0875708 0.0 0.0 | B24: NY-364-2 | C24: =VLOOKUP(B24,$F$1:$F$1051,1,FALSE) -> #N/A | F24: AC-646-9
F25: TA-226-9
F26: JT-056-5
F27: CL-594-6
F28: XT-725-9
F29: NT-329-9
F30: WD-167-9
F31: RL-617-3
F32: KA-319-1
F33: YL-557-3
F34: AV-327-2
F35: EC-526-3
F36: HV-845-4
... F1051: NT-452-1

Sheet roster_parcela
A1: CODIGO_PARCELA | B1: INDEX | C1: Version | D1: ¿Me puede dar el nombre de la parcela o terreno propia o ajena en la que el productor realizó sus actividades durante la temporada agrícola de mayo 2025 a abril 2026? | E1: Durante la temporada agrícola de mayo 2025 a abril 2026, ¿${PARCELA} fue destinada a la agricultura? | F1: Durante la temporada agrícola de mayo 2025 a abril 2026, ¿${PARCELA} fue destinada a la ganadería? | G1: Durante la temporada agrícola de mayo 2025 a abril 2026, ¿${PARCELA} fue destinada a la silvicultura? | H1: Durante la temporada agrícola de mayo 2025 a abril 2026, ¿${PARCELA} fue destinada a otro uso? | I1: ¿Podría especificar a qué otro uso fue destinada la ${PARCELA}? | J1: ¿Cuál es el área de ${PARCELA} ? | K1: M1_Q6b | L1: Especifique | M1: ¿En qué distrito se encuentra ubicada ${PARCELA} ? | N1: Durante la temporada agrícola de mayo 2025 a abril 2026, ¿${PARCELA} era...? | O1: Especifique | P1: ¿${PARCELA} se cultiva en pendiente/ladera o planicie? | Q1: Durante la temporada agrícola de mayo 2025 a abril 2026, ¿cuántos cultivos tuvo en ${PARCELA} ? | R1: Durante la temporada agrícola de mayo 2025 a abril 2026, ¿los cultivos en ${PARCELA} fueron…? | S1: ¿El cultivo o cultivos que tuvo en ${PARCELA} fueron los mismos a los que tuvo en el ciclo anterior a temporada agrícola de mayo 2025 a abril 2026? | T1: Durante la temporada agrícola de mayo 2025 a abril 2026, ¿qué practica agrícola de adaptación al cambio climático realizó en ${PARCELA} ? | U1: Durante la temporada agrícola de mayo 2025 a abril 2026, ¿qué practica agrícola de adaptación al cambio climático realizó en ${PARCELA} ?/Labranza de conservación y cobertura de suelo | V1: Durante la temporada agrícola de mayo 2025 a abril 2026, ¿qué practica agrícola de adaptación al cambio climático realizó en ${PARCELA} ?/Uso de variedades de granos básicos y vegetales resistentes al cambio climático | W1: Durante la temporada agrícola de mayo 2025 a abril 2026, ¿qué practica agrícola de adaptación al cambio climático realizó en ${PARCELA} ?/La construcción de terrazas y zanjas | X1: Durante la temporada agrícola de mayo 2025 a abril 2026, ¿qué practica agrícola de adaptación al cambio climático realizó en ${PARCELA} ?/Elaboración de fertilizantes orgánicos | Y1: Durante la temporada agrícola de mayo 2025 a abril 2026, ¿qué practica agrícola de adaptación al cambio climático realizó en ${PARCELA} ?/Combinación de cultivos con siembra de árboles | Z1: Durante la temporada agrícola de mayo 2025 a abril 2026, ¿qué practica agrícola de adaptación al cambio climático realizó en ${PARCELA} ?/Combinación de ganado con siembra de árboles | AA1: Durante la temporada agrícola de mayo 2025 a abril 2026, ¿qué practica agrícola de adaptación al cambio climático realizó en ${PARCELA} ?/La creación de banco de forrajes | AB1: Durante la temporada agrícola de mayo 2025 a abril 2026, ¿qué practica agrícola de adaptación al cambio climático realizó en ${PARCELA} ?/Riego | AC1: ¿Utilizó fertilizantes para cultivar en ${PARCELA} ? | AD1: ¿Cuál fue el principal tipo de fertilizante que usaron para sus cultivos en ${PARCELA} ? | AE1: Especifique | AF1: ¿Qué tipo de producto natural usó en ${PARCELA} ? | AG1: Especifique | AH1: ¿Cuál es el origen del o los productos naturales que usó en ${PARCELA} ? | AI1: Especifique | AJ1: ¿Qué cantidad total de fertilizantes utilizó para los cultivos de ${PARCELA} ? | AK1: M1_Q18b | AL1: Especifique | AM1: Sin considerar los fertilizantes, ¿utilizó otros agroquímicos para cultivar en ${PARCELA} ? | AN1: ¿Cuál fue el plaguicida o herbicida principal que usó para cultivar en ${PARCELA} ? | AO1: ¿Qué cantidad de ${M1_Q20} utilizó para los cultivos de ${PARCELA} ? | AP1: M1_Q21b | AQ1: Especifique | AR1: ¿De dónde obtiene principalmente el agua que utiliza para sus actividades agrícolas? | AS1: Especifique | AT1: ¿Qué destino tuvieron los residuos de la cosecha de la temporada PREVIA a la temporada agrícola de mayo 2025 a abril 2026 en ${PARCELA} ? | AU1: ¿Qué destino tuvieron los residuos de la cosecha de la temporada PREVIA a la temporada agrícola de mayo 2025 a abril 2026 en ${PARCELA} ?/Cobertura de suelo | AV1: ¿Qué destino tuvieron los residuos de la cosecha de la temporada PREVIA a la temporada agrícola de mayo 2025 a abril 2026 en ${PARCELA} ?/Quema | AW1: ¿Qué destino tuvieron los residuos de la cosecha de la temporada PREVIA a la temporada agrícola de mayo 2025 a abril 2026 en ${PARCELA} ?/Remoción | AX1: ¿Qué destino tuvieron los residuos de la cosecha de la temporada PREVIA a la temporada agrícola de mayo 2025 a abril 2026 en ${PARCELA} ?/Alimento de animales | AY1: ¿Qué destino tuvieron los residuos de la cosecha de la temporada PREVIA a la temporada agrícola de mayo 2025 a abril 2026 en ${PARCELA} ?/Compostaje | AZ1: ¿Qué destino tuvieron los residuos de la cosecha de la temporada PREVIA a la temporada agrícola de mayo 2025 a abril 2026 en ${PARCELA} ?/Combustible u otro uso | BA1: ¿Cuál fue el área aproximada en la que dejó el rastrojo en ${PARCELA}? | BB1: Durante la temporada agrícola de mayo 2025 a abril 2026, ¿cuál fue el principal método de irrigación utilizado en ${PARCELA} ? | BC1: Durante la temporada agrícola de mayo 2025 a abril 2026, ¿cuál fue el área aproximada en el que aplicó riego por goteo en ${PARCELA} ? | BD1: Durante la temporada agrícola de mayo 2025 a abril 2026, ¿cuántos árboles tenía en ${PARCELA} incluyendo los linderos? | BE1: En los últimos 12 meses, ¿cuántos árboles plantó en ${PARCELA} , incluyendo los linderos? | BF1: En los últimos 12 meses, ¿cuál fue la principal especie de arbol que plantó en ${PARCELA}, incluyendo los linderos? | BG1: En los últimos 12 meses, ¿cuál o cuáles son los motivos principales para plantar nuevos árboles? | BH1: En los últimos 12 meses, ¿cuál o cuáles son los motivos principales para plantar nuevos árboles?/Prevención de erosión | BI1: En los últimos 12 meses, ¿cuál o cuáles son los motivos principales para plantar nuevos árboles?/Prevención de estrés en el cultivo por sequía | BJ1: En los últimos 12 meses, ¿cuál o cuáles son los motivos principales para plantar nuevos árboles?/Prevención de estrés en el ganado por temperatura | BK1: En los últimos 12 meses, ¿cuál o cuáles son los motivos principales para plantar nuevos árboles?/Protección contra el viento | BL1: En los últimos 12 meses, ¿cuál o cuáles son los motivos principales para plantar nuevos árboles?/Alimentación animal (creación de banco de forraje) | BM1: En los últimos 12 meses, ¿cuál o cuáles son los motivos principales para plantar nuevos árboles?/Leña | BN1: En los últimos 12 meses, ¿cuál o cuáles son los motivos principales para plantar nuevos árboles?/Semillas o frutas | BO1: Considerando la parcela ${PARCELA}, ¿cuáles fueron los cultivos que sembraron, plantaron o cosecharon durante la temporada agrícola de mayo 2025 a abril 2026? | BP1: Considerando la parcela ${PARCELA}, ¿cuáles fueron los cultivos que sembraron, plantaron o cosecharon durante la temporada agrícola de mayo 2025 a abril 2026?/Maíz (incluye forraje verde) | BQ1: Considerando la parcela ${PARCELA}, ¿cuáles fueron los cultivos que sembraron, plantaron o cosecharon durante la temporada agrícola de mayo 2025 a abril 2026?/Frijol | BR1: Considerando la parcela ${PARCELA}, ¿cuáles fueron los cultivos que sembraron, plantaron o cosecharon durante la temporada agrícola de mayo 2025 a abril 2026?/Maicillo o sorgo (incluye forraje verde) | BS1: Considerando la parcela ${PARCELA}, ¿cuáles fueron los cultivos que sembraron, plantaron o cosecharon durante la temporada agrícola de mayo 2025 a abril 2026?/Arroz | BT1: Considerando la parcela ${PARCELA}, ¿cuáles fueron los cultivos que sembraron, plantaron o cosecharon durante la temporada agrícola de mayo 2025 a abril 2026?/Hortalizas (especificar) | BU1: Considerando la parcela ${PARCELA}, ¿cuáles fueron los cultivos que sembraron, plantaron o cosecharon durante la temporada agrícola de mayo 2025 a abril 2026?/Pastos | BV1: Considerando la parcela ${PARCELA}, ¿cuáles fueron los cultivos que sembraron, plantaron o cosecharon durante la temporada agrícola de mayo 2025 a abril 2026?/Otro, especificar | BW1: Especifique | BX1: Considerando la parcela ${PARCELA}, ¿cuáles fueron los DOS cultivos principales que sembraron, plantaron o cosecharon durante la temporada agrícola de mayo 2025 a abril 2026? | BY1: Considerando la parcela ${PARCELA}, ¿cuáles fueron los DOS cultivos principales que sembraron, plantaron o cosecharon durante la temporada agrícola de mayo 2025 a abril 2026?/Maíz (incluye forraje verde) | BZ1: Considerando la parcela ${PARCELA}, ¿cuáles fueron los DOS cultivos principales que sembraron, plantaron o cosecharon durante la temporada agrícola de mayo 2025 a abril 2026?/Frijol | CA1: Considerando la parcela ${PARCELA}, ¿cuáles fueron los DOS cultivos principales que sembraron, plantaron o cosecharon durante la temporada agrícola de mayo 2025 a abril 2026?/Maicillo o sorgo (incluye forraje verde) | CB1: Considerando la parcela ${PARCELA}, ¿cuáles fueron los DOS cultivos principales que sembraron, plantaron o cosecharon durante la temporada agrícola de mayo 2025 a abril 2026?/Arroz | CC1: Considerando la parcela ${PARCELA}, ¿cuáles fueron los DOS cultivos principales que sembraron, plantaron o cosecharon durante la temporada agrícola de mayo 2025 a abril 2026?/Hortalizas (especificar) | CD1: Considerando la parcela ${PARCELA}, ¿cuáles fueron los DOS cultivos principales que sembraron, plantaron o cosecharon durante la temporada agrícola de mayo 2025 a abril 2026?/Pastos | CE1: Considerando la parcela ${PARCELA}, ¿cuáles fueron los DOS cultivos principales que sembraron, plantaron o cosecharon durante la temporada agrícola de mayo 2025 a abril 2026?/Otro, especificar | CF1: Especifique | CG1: KoboIndex | CH1: _parent_table_name | CI1: _parent_index | CJ1: _submission__id | CK1: _submission__uuid | CL1: _submission__submission_time | CM1: _submission__validation_status | CN1: _submission__notes | CO1: _submission__status | CP1: _submission__submitted_by | CQ1: _submission___version__ | CR1: _submission__tags | CS1: _submission_meta/rootUuid
